Workbook

Sheet Пояснения
B2: Расчётная модель ГКМ «Северное сияние» — версия 4 (25.10.2026)
B3: Кейс-чемпионат газовой отрасли. Все стоимостные показатели — реальные цены 2026 г., млрд руб. без НДС; горизонт 2027–2066 гг.
B5: Назначение | C5: Технико-экономическая оценка освоения ГКМ «Северное сияние» (НГЗ 320 млрд м³) и сравнение вариантов подготовки газа; выбор решения команды — НТС на ТДА + GTL-установка 40 тыс. т ДТ и 30 тыс. т авиакеросина в год для внутренних нужд кластера.
B6: Главный результат | C6: ="NPV нашего варианта при реальной ставке 10 %: "&TEXT(Расчёт_Наш!C5,"0.0")&" млрд руб; IRR "&TEXT(Расчёт_Наш!C6,"0.0%")&"; CAPEX "&TEXT(Расчёт_Наш!C9,"0")&" млрд руб; окупаемость (дисконт.) — "&Расчёт_Наш!C7&" г." -> NPV нашего варианта при реальной ставке 10 %: 22.5 млрд руб; IRR 11.0%; CAPEX 362 млрд руб; окупаемость (дисконт.) — 2048 г.
B7: Структура | C7: «Исходные» — общие данные с источниками; «Баланс» — выход продуктов на 1000 м³ по технологиям; «CAPEX_нормы» — состав и график объектов; «Сценарии» — параметры вариантов; «Расчёт_…» — профиль добычи, продукция, выручка, налоги, CAPEX, FCF и NPV по годам; «Сравнение» — сводка; «Чувствительность» — как достигнута прибыльность, полки, торнадо, пороги; «Источники».
B8: Варианты | C8: А — НТС + стабилизация; Б — ТДА + ГФУ (СУГ); В — Б + этан; Г — НТС на ТДА без GTL; Наш выбор — Г + GTL 40+30. Стресс-сценарии нашего варианта: дебит 0,55; цены GTL команды 40 000 / 47 500; без льготы Кр.
B9: Что изменилось в v4 | C9: GTL уменьшен до 40 + 30 тыс. т/год (внутренние нужды); скважина 1,5 млрд руб; ВЖК у УКПГ возвращён (4 млрд руб); горизонтальные скважины 0,75 млн м³/сут; полка 12 млрд м³/год; учтён Кр (п-ов Ямал) в НДПИ; продукты GTL оценены по трансфертной цене (80 % биржи без НДС).
B10: Как пользоваться | C10: Меняйте синие ячейки на листах «Исходные» и «Сценарии» — все расчёты пересчитываются формулами. Если меняете полку добычи, подберите темп падения (строка «Темп падения» на «Сценарии») так, чтобы проверка на листе расчёта (C11) была ≈ 0.
B11: Цвета | C11: Синий шрифт — ввод; чёрный — формулы; зелёный — ссылки на другие листы; жёлтая заливка — ключевые решения команды.
B12: Методика | C12: Реальные цены 2026 г. без НДС; дисконтирование на середину года к началу 2027 г.; амортизация линейная 15 лет; налог на имущество 2,2 % от остаточной стоимости; налог на прибыль 25 % без переноса убытков (консервативно).
B13: Ограничения | C13: Базовая часть НДПИ, OPEX и часть CAPEX — оценки команды; будут уточнены при дальнейших расчётах. Экспортный нетбэк для «Силы Сибири — 2» в модели не учитывается — газ продаётся в ЕСГ по цене ФАС.

Sheet Сравнение
B2: Сравнение вариантов и сценариев
B3: Все значения — формулы-ссылки на листы «Расчёт_…». Изменяйте параметры на листе «Сценарии».
B5: Показатель | C5: А. НТС + стабилизация | D5: Б. ТДА + ГФУ (СУГ) | E5: В. Б + этан | F5: Г. НТС на ТДА, без GTL | G5: Наш выбор: ТДА + GTL 40+30 | H5: Наш выбор — дебит 0,55 | I5: Наш выбор — цены ДТ/керосина 40 000/47 500 | J5: Наш выбор — без коэффициента Кр
B6: ЧДД (NPV), млрд руб | C6: =Расчёт_А!C5 -> 15.105132 | D6: =Расчёт_Б!C5 -> -9.3797347 | E6: =Расчёт_В!C5 -> -75.259733 | F6: =Расчёт_Г!C5 -> 16.893083 | G6: =Расчёт_Наш!C5 -> 22.511796 | H6: =Расчёт_Наш_дебит!C5 -> -1.5517793 | I6: =Расчёт_Наш_цены!C5 -> 17.588383 | J6: =Расчёт_Наш_безКр!C5 -> 13.729305
B7: ВНД (IRR) | C7: =Расчёт_А!C6 -> 0.10741094 | D7: =Расчёт_Б!C6 -> 0.096053345 | E7: =Расчёт_В!C6 -> 0.071124893 | F7: =Расчёт_Г!C6 -> 0.10816471 | G7: =Расчёт_Наш!C6 -> 0.11044479 | H7: =Расчёт_Наш_дебит!C6 -> 0.099321669 | I7: =Расчёт_Наш_цены!C6 -> 0.10824739 | J7: =Расчёт_Наш_безКр!C6 -> 0.10632689
B8: Дисконтированная окупаемость, год | C8: =Расчёт_А!C7 -> 2050 | D8: =Расчёт_Б!C7 -> нет | E8: =Расчёт_В!C7 -> нет | F8: =Расчёт_Г!C7 -> 2049 | G8: =Расчёт_Наш!C7 -> 2048 | H8: =Расчёт_Наш_дебит!C7 -> нет | I8: =Расчёт_Наш_цены!C7 -> 2049 | J8: =Расчёт_Наш_безКр!C7 -> 2051
B9: Индекс доходности (PI) | C9: =Расчёт_А!C8 -> 1.0613708 | D9: =Расчёт_Б!C8 -> 0.96857102 | E9: =Расчёт_В!C8 -> 0.78210017 | F9: =Расчёт_Г!C8 -> 1.0677063 | G9: =Расчёт_Наш!C8 -> 1.0878941 | H9: =Расчёт_Наш_дебит!C8 -> 0.99442881 | I9: =Расчёт_Наш_цены!C8 -> 1.0686713 | J9: =Расчёт_Наш_безКр!C8 -> 1.0536041
B10: CAPEX всего, млрд руб | C10: =Расчёт_А!C9 -> 347.05583 | D10: =Расчёт_Б!C9 -> 423.0023 | E10: =Расчёт_В!C9 -> 485.84218 | F10: =Расчёт_Г!C9 -> 351.54439 | G10: =Расчёт_Наш!C9 -> 362.29439 | H10: =Расчёт_Наш_дебит!C9 -> 393.46322 | I10: =Расчёт_Наш_цены!C9 -> 362.29439 | J10: =Расчёт_Наш_безКр!C9 -> 362.29439
B11: Фонд скважин, шт. | C11: =Расчёт_А!C10 -> 57.142857 | D11: =Расчёт_Б!C10 -> 57.142857 | E11: =Расчёт_В!C10 -> 57.142857 | F11: =Расчёт_Г!C10 -> 57.142857 | G11: =Расчёт_Наш!C10 -> 57.142857 | H11: =Расчёт_Наш_дебит!C10 -> 77.922078 | I11: =Расчёт_Наш_цены!C10 -> 57.142857 | J11: =Расчёт_Наш_безКр!C10 -> 57.142857
B13: Добыча газа за период, млрд м³ | C13: =Расчёт_А!D52 -> 275.20035 | D13: =Расчёт_Б!D52 -> 275.20035 | E13: =Расчёт_В!D52 -> 275.20035 | F13: =Расчёт_Г!D52 -> 275.20035 | G13: =Расчёт_Наш!D52 -> 275.20035 | H13: =Расчёт_Наш_дебит!D52 -> 275.20035 | I13: =Расчёт_Наш_цены!D52 -> 275.20035 | J13: =Расчёт_Наш_безКр!D52 -> 275.20035
B14: Товарный газ, млрд м³ | C14: =Расчёт_А!D60 -> 263.95723 | D14: =Расчёт_Б!D60 -> 254.75682 | E14: =Расчёт_В!D60 -> 241.57984 | F14: =Расчёт_Г!D60 -> 263.57572 | G14: =Расчёт_Наш!D60 -> 257.23159 | H14: =Расчёт_Наш_дебит!D60 -> 257.23159 | I14: =Расчёт_Наш_цены!D60 -> 257.23159 | J14: =Расчёт_Наш_безКр!D60 -> 257.23159
B15: Конденсат + нафта, млн т | C15: =Расчёт_А!D61 -> 9.9518493 | D15: =Расчёт_Б!D61 -> 8.7840914 | E15: =Расчёт_В!D61 -> 8.8284555 | F15: =Расчёт_Г!D61 -> 11.022304 | G15: =Расчёт_Наш!D61 -> 11.022304 | H15: =Расчёт_Наш_дебит!D61 -> 11.022304 | I15: =Расчёт_Наш_цены!D61 -> 11.022304 | J15: =Расчёт_Наш_безКр!D61 -> 11.022304
B16: СУГ, млн т | C16: =Расчёт_А!D62 -> 0 | D16: =Расчёт_Б!D62 -> 19.457821 | E16: =Расчёт_В!D62 -> 20.760515 | F16: =Расчёт_Г!D62 -> 0 | G16: =Расчёт_Наш!D62 -> 0 | H16: =Расчёт_Наш_дебит!D62 -> 0 | I16: =Расчёт_Наш_цены!D62 -> 0 | J16: =Расчёт_Наш_безКр!D62 -> 0
B17: ДТ GTL, млн т | C17: =Расчёт_А!D64 -> 0 | D17: =Расчёт_Б!D64 -> 0 | E17: =Расчёт_В!D64 -> 0 | F17: =Расчёт_Г!D64 -> 0 | G17: =Расчёт_Наш!D64 -> 1.36 | H17: =Расчёт_Наш_дебит!D64 -> 1.36 | I17: =Расчёт_Наш_цены!D64 -> 1.36 | J17: =Расчёт_Наш_безКр!D64 -> 1.36
B18: Керосин GTL, млн т | C18: =Расчёт_А!D65 -> 0 | D18: =Расчёт_Б!D65 -> 0 | E18: =Расчёт_В!D65 -> 0 | F18: =Расчёт_Г!D65 -> 0 | G18: =Расчёт_Наш!D65 -> 1.02 | H18: =Расчёт_Наш_дебит!D65 -> 1.02 | I18: =Расчёт_Наш_цены!D65 -> 1.02 | J18: =Расчёт_Наш_безКр!D65 -> 1.02
B19: Выручка, млрд руб | C19: =Расчёт_А!D73 -> 1749.8583 | D19: =Расчёт_Б!D73 -> 1975.2311 | E19: =Расчёт_В!D73 -> 1888.5832 | F19: =Расчёт_Г!D73 -> 1782.93 | G19: =Расчёт_Наш!D73 -> 1900.2813 | H19: =Расчёт_Наш_дебит!D73 -> 1900.2813 | I19: =Расчёт_Наш_цены!D73 -> 1861.0453 | J19: =Расчёт_Наш_безКр!D73 -> 1900.2813
B20: НДПИ, млрд руб | C20: =Расчёт_А!D74 -> 234.56078 | D20: =Расчёт_Б!D74 -> 269.73584 | E20: =Расчёт_В!D74 -> 263.62312 | F20: =Расчёт_Г!D74 -> 239.12514 | G20: =Расчёт_Наш!D74 -> 240.23307 | H20: =Расчёт_Наш_дебит!D74 -> 240.23307 | I20: =Расчёт_Наш_цены!D74 -> 240.23307 | J20: =Расчёт_Наш_безКр!D74 -> 265.41494
B21: OPEX, млрд руб | C21: =Расчёт_А!D97 -> 225.79578 | D21: =Расчёт_Б!D97 -> 294.27861 | E21: =Расчёт_В!D97 -> 330.18836 | F21: =Расчёт_Г!D97 -> 228.75483 | G21: =Расчёт_Наш!D97 -> 248.83412 | H21: =Расчёт_Наш_дебит!D97 -> 265.30061 | I21: =Расчёт_Наш_цены!D97 -> 248.83412 | J21: =Расчёт_Наш_безКр!D97 -> 248.83412
B22: Налог на прибыль, млрд руб | C22: =Расчёт_А!D103 -> 223.03102 | D22: =Расчёт_Б!D103 -> 232.40299 | E22: =Расчёт_В!D103 -> 187.09147 | F22: =Расчёт_Г!D103 -> 228.11384 | G22: =Расчёт_Наш!D103 -> 249.03413 | H22: =Расчёт_Наш_дебит!D103 -> 236.55117 | I22: =Расчёт_Наш_цены!D103 -> 239.22513 | J22: =Расчёт_Наш_безКр!D103 -> 243.14004
B23: FCF недисконтированный, млрд руб | C23: =Расчёт_А!D105 -> 664.50494 | D23: =Расчёт_Б!D105 -> 688.96865 | E23: =Расчёт_В!D105 -> 545.31799 | F23: =Расчёт_Г!D105 -> 679.79063 | G23: =Расчёт_Наш!D105 -> 742.39239 | H23: =Расчёт_Наш_дебит!D105 -> 702.30289 | I23: =Расчёт_Наш_цены!D105 -> 712.96539 | J23: =Расчёт_Наш_безКр!D105 -> 723.10461
B25: Разница NPV с нашим базовым вариантом, млрд руб | C25: =C6-$G$6 -> -7.4066643 | D25: =D6-$G$6 -> -31.891531 | E25: =E6-$G$6 -> -97.771529 | F25: =F6-$G$6 -> -5.6187134 | G25: =G6-$G$6 -> 0 | H25: =H6-$G$6 -> -24.063576 | I25: =I6-$G$6 -> -4.9234132 | J25: =J6-$G$6 -> -8.7824914
B27: Вывод
B28: =IF(G6>0,"Наш вариант (ТДА + GTL 40+30) прибылен: NPV = "&TEXT(G6,"0.0")&" млрд руб, IRR = "&TEXT(G7,"0.0%")&" — лучший среди вариантов А–Г.","Наш вариант пока не окупается при ставке сценария.") -> Наш вариант (ТДА + GTL 40+30) прибылен: NPV = 22.5 млрд руб, IRR = 11.0% — лучший среди вариантов А–Г.

Sheet Исходные
B2: Исходные данные и допущения, общие для всех вариантов
B3: Синий шрифт — вводимые значения, чёрный — формулы, зелёный — ссылки. Источник и дата указаны для каждой строки.
B5: Параметр | C5: Значение | D5: Ед. | E5: Источник / обоснование | F5: Дата
B6: Начальные запасы газа (НГЗ) | C6: 320 | D6: млрд м³ | E6: Задание кейса | F6: 2026
B7: Коэффициент извлечения газа (КИГ) | C7: 0.86 | D7: д. ед. | E7: Задание кейса | F7: 2026
B8: Извлекаемые запасы | C8: =C6*C7 -> 275.2 | D8: млрд м³ | E8: НГЗ × КИГ
B9: Первый год добычи | C9: 2031 | D9: год | E9: Допущение команды: 2027 — доразведка и ПД, 2028–2030 — строительство
B10: Отбор до начала падения добычи | C10: 0.56 | D10: доля извл. | E10: Допущение: полка до отбора 56 % извлекаемых запасов (типично для ГКМ Ямала)
B11: Молярный объём газа | C11: 24.055 | D11: м³/кмоль | E11: ГОСТ 2939-63: стандартные условия 20 °C, 101,325 кПа
B12: Базисная теплота сгорания для цены ФАС | C12: 33.07572 | D12: МДж/м³ | E12: 7900 ккал/м³ × 4,1868 — базис оптовых цен ФАС
B13: Оптовая цена газа, ЯНАО (база) | C13: 4705 | D13: руб/1000 м³ | E13: Приказ ФАС № 1213/25: среднее мин./макс. для ЯНАО — https://pravo.ppt.ru/prikaz/fas/n-1213-25-326387 | F13: 2025
B14: Brent (база) | C14: 65 | D14: $/барр. | E14: Котировки октября 2026 — https://index.minfin.com.ua/markets/oil/2026-10/ | F14: 10.2026
B15: Курс | C15: 85 | D15: руб/$ | E15: Допущение на уровне октября 2026 | F15: 10.2026
B16: Дисконт конденсата к Brent | C16: 3 | D16: $/барр. | E16: Допущение
B17: Баррелей в тонне конденсата | C17: 8.8 | D17: барр./т | E17: Справочно для лёгкого конденсата
B18: Логистика конденсата до порта | C18: 9000 | D18: руб/т | E18: Допущение: конденсатопровод → ж/д Обская–Бованенково → Усть-Луга, перевалка
B19: Цена СУГ (нетбэк на промысле) | C19: 20000 | D19: руб/т | E19: Допущение (консервативно)
B20: Цена этана (нетбэк) | C20: 0 | D20: руб/т | E20: Нет потребителя этана в регионе — 0
B21: Собственные нужды до ДКС | C21: 0.02 | D21: доля | E21: Допущение
B22: Собственные нужды после ввода ДКС (с 2038 г.) | C22: 0.035 | D22: доля | E22: Допущение
B23: НДПИ газ: показатель Ккг (Газпром) | C23: 494 | D23: руб/1000 м³ | E23: С 01.10.2026 — https://www.interfax.ru/business/1056714 | F23: 10.2026
B24: НДПИ газ: базовая часть (35×Еут×Кс + Тг) до Кр | C24: 250 | D24: руб/1000 м³ | E24: Оценка команды; будет уточнена при дальнейших расчётах
B25: НДПИ жидких УВ, доля от нетбэка (до Кр) | C25: 0.15 | D25: доля | E25: Упрощённая оценка
B26: Кр (п-ов Ямал): коэффициент при n | C26: 0.066 | E26: НК РФ ст. 342.4 п. 9: Кр = 0,066 × n + 0,144 на 144 налоговых периода — https://pravo.ppt.ru/kodeks/nk/st-342.4 | F26: 10.2026
B27: Кр (п-ов Ямал): свободный член | C27: 0.144 | E27: То же | F27: 10.2026
B28: Срок действия Кр | C28: 12 | D28: лет | E28: 144 месяца с года, когда выработанность впервые > 1 %
B29: Порог выработанности для старта Кр | C29: 0.01 | D29: доля НГЗ | E29: НК РФ ст. 342.4 п. 9
B30: Налог на прибыль | C30: 0.25 | D30: доля | E30: НК РФ с 2025 г. — 25 % | F30: 2025
B31: Налог на имущество | C31: 0.022 | D31: доля/год | E31: Ставка 2,2 % от остаточной стоимости
B32: Срок амортизации | C32: 15 | D32: лет | E32: Линейно, с года ввода (капвложения до 2031 г. — с 2031 г.)
B33: Постоянные OPEX | C33: 0.015 | D33: доля накопл. CAPEX/год | E33: Допущение; включает содержание ВЖК у УКПГ
B34: Переменные OPEX | C34: 150 | D34: руб/1000 м³ сырого газа | E34: Допущение
B35: OPEX по СУГ | C35: 1000 | D35: руб/т | E35: Допущение
B36: Тариф терминала / перевалки жидких УВ | C36: 500 | D36: руб/т | E36: Допущение
B37: GTL: выход синтетических УВ | C37: 0.41 | D37: т/1000 м³ | E37: INFRA Technology: 390–440 кг на 1000 м³ — https://ru.infratechnology.ru/technology/ | F37: 10.2026
B38: GTL: доля ДТ + керосина в синтетических УВ | C38: 0.915 | D38: доля | E38: Допущение; остаток — нафта, сдаётся с конденсатом
B39: GTL: выпуск ДТ | C39: 40 | D39: тыс. т/год | E39: Решение команды (внутренние нужды кластера) | F39: 25.10.2026
B40: GTL: выпуск авиакеросина | C40: 30 | D40: тыс. т/год | E40: Решение команды (внутренние нужды кластера) | F40: 25.10.2026
B41: GTL: OPEX | C41: 5525 | D41: руб/т синт. УВ | E41: INFRA: $35–65/т × 85 руб/$ (верх диапазона) | F41: 10.2026
B42: GTL: первый год работы | C42: 2033 | D42: год | E42: Строительство 2031–2032
B43: Биржевая цена зимнего ДТ (с НДС) | C43: 85485 | D43: руб/т | E43: Нефть и капитал, 22.10.2026 — https://oilcapital.ru/news/2026-10-22/minenergo-na-toplivnom-rynke-otmechen-rost-proizvodstva-nachali-formirovatsya-zapasy-5714138 | F43: 22.10.2026
B44: Цена авиакеросина (с НДС) | C44: 98426 | D44: руб/т | E44: Данные команды (биржевая цена в сентябре 2026 г. выше — 126 263 руб/т, The Moscow Times) | F44: 10.2026
B45: НДС | C45: 0.22 | D45: доля | E45: С 2026 г. — https://www.nalog.gov.ru/new2026/ | F45: 2026
B46: Трансфертная цена GTL, доля от биржи без НДС | C46: 0.8 | D46: доля | E46: Решение команды: продукты идут на внутренние нужды и замещают закупку с доставкой; 20 % — запас на акциз и риски | F46: 25.10.2026
B47: Трансфертная цена ДТ (расчётная) | C47: =ROUND(C43/(1+C45)*C46,-2) -> 56100 | D47: руб/т | E47: Формула: биржа / (1 + НДС) × доля
B48: Трансфертная цена керосина (расчётная) | C48: =ROUND(C44/(1+C45)*C46,-2) -> 64500 | D48: руб/т | E48: Формула: цена / (1 + НДС) × доля

Sheet Баланс
B2: Материальный баланс на 1000 м³ сырого газа по технологиям
B3: Состав газа — задание кейса (сумма 99,95 % нормируется). Степени извлечения — допущения по типовым технологиям.
B5: Компонент | C5: Мол. % | D5: M, кг/кмоль | E5: Qн, МДж/м³ | F5: Извл. A | G5: Извл. B | H5: Извл. T | I5: Извл. C
B6: C1 | C6: 88.5 | D6: 16.043 | E6: 33.4101 | F6: 0 | G6: 0 | H6: 0 | I6: 0
B7: C2 | C7: 5.5 | D7: 30.069 | E7: 59.458 | F7: 0 | G7: 0 | H7: 0 | I7: 0.85
B8: C3 | C8: 3 | D8: 44.096 | E8: 85.0243 | F8: 0 | G8: 0.9 | H8: 0 | I8: 0.98
B9: iC4 | C9: 0.45 | D9: 58.122 | E9: 110.1876 | F9: 0.25 | G9: 0.97 | H9: 0.35 | I9: 0.99
B10: nC4 | C10: 0.55 | D10: 58.122 | E10: 110.5808 | F10: 0.3 | G10: 0.97 | H10: 0.42 | I10: 0.99
B11: C5+ | C11: 0.8 | D11: 100 | E11: 188.233 | F11: 0.92 | G11: 0.99 | H11: 0.96 | I11: 0.995
B12: N2 | C12: 0.5 | D12: 28.013 | E12: 0 | F12: 0 | G12: 0 | H12: 0 | I12: 0
B13: CO2 | C13: 0.65 | D13: 44.01 | E13: 0 | F13: 0 | G13: 0 | H13: 0 | I13: 0
B14: Сумма | C14: =SUM(C6:C13) -> 99.95
B15: Количество кмоль в 1000 м³ | C15: =1000/Исходные!$C$11 -> 41.571399
B17: Продукт, на 1000 м³ сырого газа | C17: Ед. | D17: A | E17: B | F17: T | G17: C
B18: Стабильный конденсат (C5+, для A и T — с частью C4) | C18: кг | D18: =$C$11/$C$14*$C$15*$D$11*F$11+($C$9/$C$14*$C$15*$D$9*F$9+$C$10/$C$14*$C$15*$D$10*F$10) -> 37.3202 | E18: =$C$11/$C$14*$C$15*$D$11*G$11 -> 32.941018 | F18: =$C$11/$C$14*$C$15*$D$11*H$11+($C$9/$C$14*$C$15*$D$9*H$9+$C$10/$C$14*$C$15*$D$10*H$10) -> 41.334488 | G18: =$C$11/$C$14*$C$15*$D$11*I$11 -> 33.107387
B19: СПБТ (C3 + C4) | C19: кг | D19: 0 | E19: =$C$8/$C$14*$C$15*$D$8*G$8+($C$9/$C$14*$C$15*$D$9*G$9+$C$10/$C$14*$C$15*$D$10*G$10) -> 72.968324 | F19: 0 | G19: =$C$8/$C$14*$C$15*$D$8*I$8+($C$9/$C$14*$C$15*$D$9*I$9+$C$10/$C$14*$C$15*$D$10*I$10) -> 77.853527
B20: Этан | C20: кг | D20: =$C$7/$C$14*$C$15*$D$7*F$7 -> 0 | E20: =$C$7/$C$14*$C$15*$D$7*G$7 -> 0 | F20: =$C$7/$C$14*$C$15*$D$7*H$7 -> 0 | G20: =$C$7/$C$14*$C$15*$D$7*I$7 -> 58.467219
B21: Товарный газ, объём | C21: м³ | D21: =SUMPRODUCT($C$6:$C$13,1-F$6:F$13)/$C$14*1000 -> 989.85993 | E21: =SUMPRODUCT($C$6:$C$13,1-G$6:G$13)/$C$14*1000 -> 955.35768 | F21: =SUMPRODUCT($C$6:$C$13,1-H$6:H$13)/$C$14*1000 -> 988.42921 | G21: =SUMPRODUCT($C$6:$C$13,1-I$6:I$13)/$C$14*1000 -> 905.94297
B22: Теплота сгорания товарного газа | C22: МДж/м³ | D22: =SUMPRODUCT($C$6:$C$13,1-F$6:F$13,$E$6:$E$13)/SUMPRODUCT($C$6:$C$13,1-F$6:F$13) -> 36.697221 | E22: =SUMPRODUCT($C$6:$C$13,1-G$6:G$13,$E$6:$E$13)/SUMPRODUCT($C$6:$C$13,1-G$6:G$13) -> 34.707378 | F22: =SUMPRODUCT($C$6:$C$13,1-H$6:H$13,$E$6:$E$13)/SUMPRODUCT($C$6:$C$13,1-H$6:H$13) -> 36.565304 | G22: =SUMPRODUCT($C$6:$C$13,1-I$6:I$13,$E$6:$E$13)/SUMPRODUCT($C$6:$C$13,1-I$6:I$13) -> 33.272649
B24: A — НТС (−30 °C) + стабилизация; B — ТДА (−60…−70 °C) + ГФУ (СУГ); T — НТС на ТДА (−35…−40 °C) + стабилизация (наш выбор); C — B + криогенное извлечение этана.

Sheet CAPEX_нормы
B2: Нормативы капитальных вложений (при полке 14 млрд м³/год) и график освоения
B3: Масштаб «да» — × (полка / 14)^0,7; «нет» — фиксированная сумма; «скв» — число скважин × стоимость скважины. Флаги показывают, в каких вариантах есть объект.
B5: Объект | C5: Сумма, млрд руб | D5: Масштаб | E5: A | F5: B | G5: C | H5: T0 | I5: T | J5: 2027 | K5: 2028 | L5: 2029 | M5: 2030 | N5: 2031 | O5: 2032 | P5: 2033 | Q5: 2034 | R5: 2035 | S5: 2036 | T5: 2037 | U5: 2038 | V5: 2039 | W5: 2040 | X5: 2041 | Y5: 2042 | Z5: 2043 | AA5: 2044 | AB5: 2045 | AC5: Σ долей | AD5: Обоснование
B6: Доразведка, 3D, ТЭО и проектная документация | C6: 15 | D6: нет | E6: 1 | F6: 1 | G6: 1 | H6: 1 | I6: 1 | J6: 1 | K6: 0 | L6: 0 | M6: 0 | N6: 0 | O6: 0 | P6: 0 | Q6: 0 | R6: 0 | S6: 0 | T6: 0 | U6: 0 | V6: 0 | W6: 0 | X6: 0 | Y6: 0 | Z6: 0 | AA6: 0 | AB6: 0 | AC6: =SUM(J6:AB6) -> 1 | AD6: Оценка команды: 3D-сейсмика, разведочные скважины, ТЭО, ПД
B7: Эксплуатационные скважины | C7: — | D7: скв | E7: 1 | F7: 1 | G7: 1 | H7: 1 | I7: 1 | J7: 0 | K7: 0.2 | L7: 0.3 | M7: 0.3 | N7: 0.08 | O7: 0 | P7: 0 | Q7: 0 | R7: 0 | S7: 0.03 | T7: 0.03 | U7: 0.03 | V7: 0.03 | W7: 0 | X7: 0 | Y7: 0 | Z7: 0 | AA7: 0 | AB7: 0 | AC7: =SUM(J7:AB7) -> 1 | AD7: Стоимость скважины — решение команды 1,5 млрд руб (лист «Сценарии»)
B8: Кусты скважин и газосборная сеть | C8: 46.5 | D8: да | E8: 1 | F8: 1 | G8: 1 | H8: 1 | I8: 1 | J8: 0 | K8: 0.3 | L8: 0.4 | M8: 0.3 | N8: 0 | O8: 0 | P8: 0 | Q8: 0 | R8: 0 | S8: 0 | T8: 0 | U8: 0 | V8: 0 | W8: 0 | X8: 0 | Y8: 0 | Z8: 0 | AA8: 0 | AB8: 0 | AC8: =SUM(J8:AB8) -> 1 | AD8: 50 млрд × 0,93 (снижение металлоёмкости эстакад — материалы кейса)
B9: УКПГ: НТС, регенерация метанола, стабилизация | C9: 78.12 | D9: да | E9: 1 | F9: 1 | G9: 1 | H9: 1 | I9: 1 | J9: 0 | K9: 0.297619 | L9: 0.416667 | M9: 0.285714 | N9: 0 | O9: 0 | P9: 0 | Q9: 0 | R9: 0 | S9: 0 | T9: 0 | U9: 0 | V9: 0 | W9: 0 | X9: 0 | Y9: 0 | Z9: 0 | AA9: 0 | AB9: 0 | AC9: =SUM(J9:AB9) -> 1 | AD9: 84 млрд × 0,93 (то же)
B10: Турбодетандерные агрегаты (5 шт.) | C10: 5 | D10: да | E10: 0 | F10: 0 | G10: 0 | H10: 1 | I10: 1 | J10: 0 | K10: 0 | L10: 0.5 | M10: 0.5 | N10: 0 | O10: 0 | P10: 0 | Q10: 0 | R10: 0 | S10: 0 | T10: 0 | U10: 0 | V10: 0 | W10: 0 | X10: 0 | Y10: 0 | Z10: 0 | AA10: 0 | AB10: 0 | AC10: =SUM(J10:AB10) -> 1 | AD10: 5 ТДА (4 раб. + 1 рез.) по 8,4 млн м³/сут — оценка
B11: ТДА + деэтанизация + ГФУ + парк СУГ | C11: 60 | D11: да | E11: 0 | F11: 1 | G11: 1 | H11: 0 | I11: 0 | J11: 0 | K11: 0 | L11: 0.416667 | M11: 0.583333 | N11: 0 | O11: 0 | P11: 0 | Q11: 0 | R11: 0 | S11: 0 | T11: 0 | U11: 0 | V11: 0 | W11: 0 | X11: 0 | Y11: 0 | Z11: 0 | AA11: 0 | AB11: 0 | AC11: =SUM(J11:AB11) -> 1 | AD11: Оценка для варианта B
B12: Продуктопровод СУГ 120 км | C12: 9.6 | D12: да | E12: 0 | F12: 1 | G12: 1 | H12: 0 | I12: 0 | J12: 0 | K12: 0 | L12: 0.520833 | M12: 0.479167 | N12: 0 | O12: 0 | P12: 0 | Q12: 0 | R12: 0 | S12: 0 | T12: 0 | U12: 0 | V12: 0 | W12: 0 | X12: 0 | Y12: 0 | Z12: 0 | AA12: 0 | AB12: 0 | AC12: =SUM(J12:AB12) -> 1 | AD12: Оценка для вариантов B, C
B13: Налив СУГ на ж/д | C13: 3 | D13: да | E13: 0 | F13: 1 | G13: 1 | H13: 0 | I13: 0 | J13: 0 | K13: 0 | L13: 0.5 | M13: 0.5 | N13: 0 | O13: 0 | P13: 0 | Q13: 0 | R13: 0 | S13: 0 | T13: 0 | U13: 0 | V13: 0 | W13: 0 | X13: 0 | Y13: 0 | Z13: 0 | AA13: 0 | AB13: 0 | AC13: =SUM(J13:AB13) -> 1 | AD13: Оценка для вариантов B, C
B14: Пропановая холодильная установка | C14: 12 | D14: да | E14: 0 | F14: 1 | G14: 1 | H14: 0 | I14: 0 | J14: 0 | K14: 0 | L14: 0 | M14: 0 | N14: 0 | O14: 0 | P14: 0 | Q14: 0 | R14: 0 | S14: 0 | T14: 0 | U14: 1 | V14: 0 | W14: 0 | X14: 0 | Y14: 0 | Z14: 0 | AA14: 0 | AB14: 0 | AC14: =SUM(J14:AB14) -> 1 | AD14: Оценка: поддержание −60 °C при падении давления
B15: Криогенный блок извлечения этана | C15: 70 | D15: да | E15: 0 | F15: 0 | G15: 1 | H15: 0 | I15: 0 | J15: 0 | K15: 0 | L15: 0.428571 | M15: 0.571429 | N15: 0 | O15: 0 | P15: 0 | Q15: 0 | R15: 0 | S15: 0 | T15: 0 | U15: 0 | V15: 0 | W15: 0 | X15: 0 | Y15: 0 | Z15: 0 | AA15: 0 | AB15: 0 | AC15: =SUM(J15:AB15) -> 1 | AD15: Оценка для варианта C
B16: Энергоцентр (ЭСН), промбаза | C16: 12 | D16: да | E16: 1 | F16: 1 | G16: 1 | H16: 1 | I16: 1 | J16: 0 | K16: 0.416667 | L16: 0.416667 | M16: 0.166667 | N16: 0 | O16: 0 | P16: 0 | Q16: 0 | R16: 0 | S16: 0 | T16: 0 | U16: 0 | V16: 0 | W16: 0 | X16: 0 | Y16: 0 | Z16: 0 | AA16: 0 | AB16: 0 | AC16: =SUM(J16:AB16) -> 1.000001 | AD16: Оценка; ВЖК вынесен отдельной строкой
B17: Вахтовый жилой комплекс у УКПГ | C17: — | D17: нет | E17: 1 | F17: 1 | G17: 1 | H17: 1 | I17: 1 | J17: 0 | K17: 0.375 | L17: 0.375 | M17: 0.25 | N17: 0 | O17: 0 | P17: 0 | Q17: 0 | R17: 0 | S17: 0 | T17: 0 | U17: 0 | V17: 0 | W17: 0 | X17: 0 | Y17: 0 | Z17: 0 | AA17: 0 | AB17: 0 | AC17: =SUM(J17:AB17) -> 1 | AD17: Оценка ≈20 млн руб/место × 200 мест (аналог: ВЖК Семаковского, 200 мест — https://neftegas.info/news/article/20669)
B18: Автодорога до Бованенково 120 км | C18: — | D18: нет | E18: 1 | F18: 1 | G18: 1 | H18: 1 | I18: 1 | J18: 0 | K18: 0.4 | L18: 0.4 | M18: 0.2 | N18: 0 | O18: 0 | P18: 0 | Q18: 0 | R18: 0 | S18: 0 | T18: 0 | U18: 0 | V18: 0 | W18: 0 | X18: 0 | Y18: 0 | Z18: 0 | AA18: 0 | AB18: 0 | AC18: =SUM(J18:AB18) -> 1 | AD18: 120 км × 0,20 млрд руб/км (ЯНАО: $2,4–2,5 млн/км — goarctic.ru, Минтранс)
B19: Газопровод 120 км до Бованенково | C19: 42 | D19: да | E19: 1 | F19: 1 | G19: 1 | H19: 1 | I19: 1 | J19: 0 | K19: 0.285714 | L19: 0.47619 | M19: 0.238095 | N19: 0 | O19: 0 | P19: 0 | Q19: 0 | R19: 0 | S19: 0 | T19: 0 | U19: 0 | V19: 0 | W19: 0 | X19: 0 | Y19: 0 | Z19: 0 | AA19: 0 | AB19: 0 | AC19: =SUM(J19:AB19) -> 0.999999 | AD19: Оценка 120 км до врезки в «Бованенково — Ухта»
B20: Конденсатопровод 120 км | C20: 9.6 | D20: да | E20: 1 | F20: 1 | G20: 1 | H20: 1 | I20: 1 | J20: 0 | K20: 0 | L20: 0.625 | M20: 0.375 | N20: 0 | O20: 0 | P20: 0 | Q20: 0 | R20: 0 | S20: 0 | T20: 0 | U20: 0 | V20: 0 | W20: 0 | X20: 0 | Y20: 0 | Z20: 0 | AA20: 0 | AB20: 0 | AC20: =SUM(J20:AB20) -> 1 | AD20: Оценка 120 км до ст. Бованенково
B21: ДКС (2 очереди) | C21: 55 | D21: да | E21: 1 | F21: 1 | G21: 1 | H21: 1 | I21: 1 | J21: 0 | K21: 0 | L21: 0 | M21: 0 | N21: 0 | O21: 0 | P21: 0 | Q21: 0 | R21: 0 | S21: 0 | T21: 0.272727 | U21: 0.363636 | V21: 0 | W21: 0 | X21: 0 | Y21: 0 | Z21: 0 | AA21: 0 | AB21: 0.363636 | AC21: =SUM(J21:AB21) -> 0.999999 | AD21: Оценка, 2 очереди
B22: GTL-установка у ст. Бованенково + налив | C22: — | D22: нет | E22: 0 | F22: 0 | G22: 0 | H22: 0 | I22: 1 | J22: 0 | K22: 0 | L22: 0 | M22: 0 | N22: 0.4 | O22: 0.6 | P22: 0 | Q22: 0 | R22: 0 | S22: 0 | T22: 0 | U22: 0 | V22: 0 | W22: 0 | X22: 0 | Y22: 0 | Z22: 0 | AA22: 0 | AB22: 0 | AC22: =SUM(J22:AB22) -> 1 | AD22: 76,5 тыс. т/год синт. УВ × $1500 за т/год × 85 руб/$ ≈ 9,75 + налив и резервуары ≈ 1,0 (INFRA)
B24: Суммы для ВЖК, автодороги и GTL задаются на листе «Сценарии» (меняются по вариантам).

Sheet Сценарии
B2: Параметры вариантов и сценариев
B3: Каждый столбец управляет своим листом «Расчёт_…». Жёлтым выделены ключевые решения команды.
B5: Параметр | C5: Ед. | D5: А. НТС + стабилизация | E5: Б. ТДА + ГФУ (СУГ) | F5: В. Б + этан | G5: Г. НТС на ТДА, без GTL | H5: Наш выбор: ТДА + GTL 40+30 | I5: Наш выбор — дебит 0,55 | J5: Наш выбор — цены ДТ/керосина 40 000/47 500 | K5: Наш выбор — без коэффициента Кр
B6: Технология подготовки (столбец баланса) | C6: код | D6: A | E6: B | F6: C | G6: T | H6: T | I6: T | J6: T | K6: T
B7: Состав объектов CAPEX (флаг на листе «CAPEX_нормы») | C7: код | D7: A | E7: B | F7: C | G7: T0 | H7: T | I7: T | J7: T | K7: T
B8: GTL-установка (1 — есть) | C8: 0/1 | D8: 0 | E8: 0 | F8: 0 | G8: 0 | H8: 1 | I8: 1 | J8: 1 | K8: 1
B9: Полка добычи | C9: млрд м³/год | D9: 12 | E9: 12 | F9: 12 | G9: 12 | H9: 12 | I9: 12 | J9: 12 | K9: 12
B10: Темп падения после полки (подобран: Σ добычи = извлекаемые) | C10: 1/год | D10: 0.071752 | E10: 0.071752 | F10: 0.071752 | G10: 0.071752 | H10: 0.071752 | I10: 0.071752 | J10: 0.071752 | K10: 0.071752
B11: Стоимость скважины | C11: млрд руб | D11: 1.5 | E11: 1.5 | F11: 1.5 | G11: 1.5 | H11: 1.5 | I11: 1.5 | J11: 1.5 | K11: 1.5
B12: Дебит скважины | C12: млн м³/сут | D12: 0.75 | E12: 0.75 | F12: 0.75 | G12: 0.75 | H12: 0.75 | I12: 0.55 | J12: 0.75 | K12: 0.75
B13: Применять Кр (п-ов Ямал) в НДПИ (1 — да) | C13: 0/1 | D13: 1 | E13: 1 | F13: 1 | G13: 1 | H13: 1 | I13: 1 | J13: 1 | K13: 0
B14: Цена ДТ GTL | C14: руб/т | D14: =Исходные!$C$47 -> 56100 | E14: =Исходные!$C$47 -> 56100 | F14: =Исходные!$C$47 -> 56100 | G14: =Исходные!$C$47 -> 56100 | H14: =Исходные!$C$47 -> 56100 | I14: =Исходные!$C$47 -> 56100 | J14: 40000 | K14: =Исходные!$C$47 -> 56100
B15: Цена авиакеросина GTL | C15: руб/т | D15: =Исходные!$C$48 -> 64500 | E15: =Исходные!$C$48 -> 64500 | F15: =Исходные!$C$48 -> 64500 | G15: =Исходные!$C$48 -> 64500 | H15: =Исходные!$C$48 -> 64500 | I15: =Исходные!$C$48 -> 64500 | J15: 47500 | K15: =Исходные!$C$48 -> 64500
B16: Оптовая цена газа (7900 ккал/м³) | C16: руб/1000 м³ | D16: =Исходные!$C$13 -> 4705 | E16: =Исходные!$C$13 -> 4705 | F16: =Исходные!$C$13 -> 4705 | G16: =Исходные!$C$13 -> 4705 | H16: =Исходные!$C$13 -> 4705 | I16: =Исходные!$C$13 -> 4705 | J16: =Исходные!$C$13 -> 4705 | K16: =Исходные!$C$13 -> 4705
B17: Brent | C17: $/барр. | D17: =Исходные!$C$14 -> 65 | E17: =Исходные!$C$14 -> 65 | F17: =Исходные!$C$14 -> 65 | G17: =Исходные!$C$14 -> 65 | H17: =Исходные!$C$14 -> 65 | I17: =Исходные!$C$14 -> 65 | J17: =Исходные!$C$14 -> 65 | K17: =Исходные!$C$14 -> 65
B18: Ставка дисконтирования (реальная) | C18: доля | D18: 0.1 | E18: 0.1 | F18: 0.1 | G18: 0.1 | H18: 0.1 | I18: 0.1 | J18: 0.1 | K18: 0.1
B19: Множитель CAPEX | C19: x | D19: 1 | E19: 1 | F19: 1 | G19: 1 | H19: 1 | I19: 1 | J19: 1 | K19: 1
B20: Множитель добычи | C20: x | D20: 1 | E20: 1 | F20: 1 | G20: 1 | H20: 1 | I20: 1 | J20: 1 | K20: 1
B21: ВЖК у УКПГ | C21: млрд руб | D21: 4 | E21: 4 | F21: 4 | G21: 4 | H21: 4 | I21: 4 | J21: 4 | K21: 4
B22: Автодорога 120 км | C22: млрд руб | D22: 24 | E22: 24 | F22: 24 | G22: 24 | H22: 24 | I22: 24 | J22: 24 | K22: 24
B23: GTL-установка + налив | C23: млрд руб | D23: 10.75 | E23: 10.75 | F23: 10.75 | G23: 10.75 | H23: 10.75 | I23: 10.75 | J23: 10.75 | K23: 10.75
B24: Услуги чужого ВЖК (проживание, транспорт) | C24: млрд руб/год | D24: 0 | E24: 0 | F24: 0 | G24: 0 | H24: 0 | I24: 0 | J24: 0 | K24: 0
B26: Описание | D26: Базовая технология без ТДА и без GTL | E26: Глубокое извлечение C3+, СУГ по ж/д | F26: Криогенное извлечение этана, потребителя нет | G26: Наша технология подготовки без GTL | H26: Базовый вариант решения команды | I26: Стресс: дебит как у наклонных скважин | J26: Цены продукции GTL по оценке команды | K26: Без льготы НДПИ для п-ова Ямал
B28: Темп падения подбирается так, чтобы суммарная добыча за 2031–2066 гг. равнялась извлекаемым запасам (проверка — на каждом листе «Расчёт», ячейка C11). При изменении полки подберите темп через «Подбор параметра».

Sheet Расчёт_А
B2: Расчёт: А. НТС + стабилизация
B3: Базовая технология без ТДА и без GTL. Денежный поток по годам, млрд руб. (реальные цены 2026 г.)
B5: ЧДД (NPV) при ставке варианта, млрд руб | C5: =SUM(E107:AR107) -> 15.105132
B6: ВНД (IRR), реальная | C6: =IRR(E105:AR105,0.1) -> 0.10741094
B7: Дисконтированная окупаемость, год | C7: =IF(SUM(E109:AR109)=0,"нет",2067-SUM(E109:AR109)) -> 2050
B8: Индекс доходности (PI) | C8: =1+C5/SUMPRODUCT(E93:AR93,E106:AR106) -> 1.0613708
B9: CAPEX всего, млрд руб | C9: =D93 -> 347.05583
B10: Фонд скважин, шт. | C10: =$D$42 -> 57.142857
B11: Проверка: Σ профиля − извлекаемые (должно быть ≈ 0), млрд м³ | C11: =D50-Исходные!$C$8 -> 0.0003531191
B13: Показатель | C13: Ед. | D13: Итого / знач. | E13: 2027 | F13: 2028 | G13: 2029 | H13: 2030 | I13: 2031 | J13: 2032 | K13: 2033 | L13: 2034 | M13: 2035 | N13: 2036 | O13: 2037 | P13: 2038 | Q13: 2039 | R13: 2040 | S13: 2041 | T13: 2042 | U13: 2043 | V13: 2044 | W13: 2045 | X13: 2046 | Y13: 2047 | Z13: 2048 | AA13: 2049 | AB13: 2050 | AC13: 2051 | AD13: 2052 | AE13: 2053 | AF13: 2054 | AG13: 2055 | AH13: 2056 | AI13: 2057 | AJ13: 2058 | AK13: 2059 | AL13: 2060 | AM13: 2061 | AN13: 2062 | AO13: 2063 | AP13: 2064 | AQ13: 2065 | AR13: 2066
B14: Параметры варианта (ссылки на «Сценарии» и «Исходные»)
B15: Технология (столбец баланса) | C15: код | D15: =Сценарии!$D$6 -> A
B16: Состав CAPEX | C16: код | D16: =Сценарии!$D$7 -> A
B17: GTL (1 — есть) | C17: 0/1 | D17: =Сценарии!$D$8 -> 0
B18: Полка добычи | C18: млрд м³/год | D18: =Сценарии!$D$9 -> 12
B19: Темп падения | C19: 1/год | D19: =Сценарии!$D$10 -> 0.071752
B20: Стоимость скважины | C20: млрд руб | D20: =Сценарии!$D$11 -> 1.5
B21: Дебит скважины | C21: млн м³/сут | D21: =Сценарии!$D$12 -> 0.75
B22: Кр (п-ов Ямал) в НДПИ | C22: 0/1 | D22: =Сценарии!$D$13 -> 1
B23: Цена ДТ GTL | C23: руб/т | D23: =Сценарии!$D$14 -> 56100
B24: Цена керосина GTL | C24: руб/т | D24: =Сценарии!$D$15 -> 64500
B25: Цена газа | C25: руб/1000 м³ | D25: =Сценарии!$D$16 -> 4705
B26: Brent | C26: $/барр. | D26: =Сценарии!$D$17 -> 65
B27: Ставка дисконтирования | C27: доля | D27: =Сценарии!$D$18 -> 0.1
B28: Множитель CAPEX | C28: x | D28: =Сценарии!$D$19 -> 1
B29: Множитель добычи | C29: x | D29: =Сценарии!$D$20 -> 1
B30: ВЖК у УКПГ | C30: млрд руб | D30: =Сценарии!$D$21 -> 4
B31: Автодорога | C31: млрд руб | D31: =Сценарии!$D$22 -> 24
B32: GTL + налив | C32: млрд руб | D32: =Сценарии!$D$23 -> 10.75
B33: Услуги чужого ВЖК | C33: млрд руб/год | D33: =Сценарии!$D$24 -> 0
B34: Выход конденсата | C34: кг/1000 м³ | D34: =INDEX(Баланс!$D$18:$G$18,MATCH($D$15,Баланс!$D$17:$G$17,0)) -> 37.3202
B35: Выход СУГ | C35: кг/1000 м³ | D35: =INDEX(Баланс!$D$19:$G$19,MATCH($D$15,Баланс!$D$17:$G$17,0)) -> 0
B36: Выход этана | C36: кг/1000 м³ | D36: =INDEX(Баланс!$D$20:$G$20,MATCH($D$15,Баланс!$D$17:$G$17,0)) -> 0
B37: Товарный газ | C37: м³/1000 м³ | D37: =INDEX(Баланс!$D$21:$G$21,MATCH($D$15,Баланс!$D$17:$G$17,0)) -> 989.85993
B38: Теплота сгорания товарного газа | C38: МДж/м³ | D38: =INDEX(Баланс!$D$22:$G$22,MATCH($D$15,Баланс!$D$17:$G$17,0)) -> 36.697221
B39: Цена товарного газа с учётом теплоты | C39: руб/1000 м³ | D39: =$D$25*$D$38/Исходные!$C$12 -> 5220.1562
B40: Нетбэк конденсата на промысле | C40: руб/т | D40: =($D$26-Исходные!$C$16)*Исходные!$C$17*Исходные!$C$15-Исходные!$C$18 -> 37376
B41: Коэффициент масштаба объектов (полка/14)^0,7 | C41: x | D41: =($D$18/14)^0.7 -> 0.89771245
B42: Фонд эксплуатационных скважин | C42: шт. | D42: =100*$D$18/14*0.5/$D$21 -> 57.142857
B43: GTL: синтетические УВ | C43: млн т/год | D43: =(Исходные!$C$39+Исходные!$C$40)/Исходные!$C$38/1000 -> 0.076502732
B44: GTL: газ на установку | C44: млрд м³/год | D44: =$D$43/Исходные!$C$37 -> 0.18659203
B45: Добыча и продукция
B46: Год | E46: 2027 | F46: 2028 | G46: 2029 | H46: 2030 | I46: 2031 | J46: 2032 | K46: 2033 | L46: 2034 | M46: 2035 | N46: 2036 | O46: 2037 | P46: 2038 | Q46: 2039 | R46: 2040 | S46: 2041 | T46: 2042 | U46: 2043 | V46: 2044 | W46: 2045 | X46: 2046 | Y46: 2047 | Z46: 2048 | AA46: 2049 | AB46: 2050 | AC46: 2051 | AD46: 2052 | AE46: 2053 | AF46: 2054 | AG46: 2055 | AH46: 2056 | AI46: 2057 | AJ46: 2058 | AK46: 2059 | AL46: 2060 | AM46: 2061 | AN46: 2062 | AO46: 2063 | AP46: 2064 | AQ46: 2065 | AR46: 2066
B47: Номер года от начала (для дисконтирования) | E47: =E46-2027 -> 0 | F47: =F46-2027 -> 1 | G47: =G46-2027 -> 2 | H47: =H46-2027 -> 3 | I47: =I46-2027 -> 4 | J47: =J46-2027 -> 5 | K47: =K46-2027 -> 6 | L47: =L46-2027 -> 7 | ... AR47: =AR46-2027 -> 39
B48: Признак падения добычи | C48: 0/1 | E48: 0 | F48: =IF(F46<=Исходные!$C$9+1,0,IF(OR(E48=1,E51+$D$18>Исходные!$C$10*Исходные!$C$8),1,0)) -> 0 | G48: =IF(G46<=Исходные!$C$9+1,0,IF(OR(F48=1,F51+$D$18>Исходные!$C$10*Исходные!$C$8),1,0)) -> 0 | H48: =IF(H46<=Исходные!$C$9+1,0,IF(OR(G48=1,G51+$D$18>Исходные!$C$10*Исходные!$C$8),1,0)) -> 0 | I48: =IF(I46<=Исходные!$C$9+1,0,IF(OR(H48=1,H51+$D$18>Исходные!$C$10*Исходные!$C$8),1,0)) -> 0 | J48: =IF(J46<=Исходные!$C$9+1,0,IF(OR(I48=1,I51+$D$18>Исходные!$C$10*Исходные!$C$8),1,0)) -> 0 | K48: =IF(K46<=Исходные!$C$9+1,0,IF(OR(J48=1,J51+$D$18>Исходные!$C$10*Исходные!$C$8),1,0)) -> 0 | L48: =IF(L46<=Исходные!$C$9+1,0,IF(OR(K48=1,K51+$D$18>Исходные!$C$10*Исходные!$C$8),1,0)) -> 0 | M48: =IF(M46<=Исходные!$C$9+1,0,IF(OR(L48=1,L51+$D$18>Исходные!$C$10*Исходные!$C$8),1,0)) -> 0 | ... AR48: =IF(AR46<=Исходные!$C$9+1,0,IF(OR(AQ48=1,AQ51+$D$18>Исходные!$C$10*Исходные!$C$8),1,0)) -> 1
B49: Год падения, порядковый | E49: 0 | F49: =IF(F48=1,E49+1,0) -> 0 | G49: =IF(G48=1,F49+1,0) -> 0 | H49: =IF(H48=1,G49+1,0) -> 0 | I49: =IF(I48=1,H49+1,0) -> 0 | J49: =IF(J48=1,I49+1,0) -> 0 | K49: =IF(K48=1,J49+1,0) -> 0 | L49: =IF(L48=1,K49+1,0) -> 0 | M49: =IF(M48=1,L49+1,0) -> 0 | ... AR49: =IF(AR48=1,AQ49+1,0) -> 23
B50: Профиль добычи (до множителя) | C50: млрд м³ | D50: =SUM(E50:AR50) -> 275.20035 | E50: =IF(E46<Исходные!$C$9,0,IF(E46=Исходные!$C$9,$D$18*5/14,IF(E46=Исходные!$C$9+1,$D$18*10/14,IF(E48=1,$D$18*EXP(-$D$19*E49),$D$18)))) -> 0 | F50: =IF(F46<Исходные!$C$9,0,IF(F46=Исходные!$C$9,$D$18*5/14,IF(F46=Исходные!$C$9+1,$D$18*10/14,IF(F48=1,$D$18*EXP(-$D$19*F49),$D$18)))) -> 0 | G50: =IF(G46<Исходные!$C$9,0,IF(G46=Исходные!$C$9,$D$18*5/14,IF(G46=Исходные!$C$9+1,$D$18*10/14,IF(G48=1,$D$18*EXP(-$D$19*G49),$D$18)))) -> 0 | H50: =IF(H46<Исходные!$C$9,0,IF(H46=Исходные!$C$9,$D$18*5/14,IF(H46=Исходные!$C$9+1,$D$18*10/14,IF(H48=1,$D$18*EXP(-$D$19*H49),$D$18)))) -> 0 | I50: =IF(I46<Исходные!$C$9,0,IF(I46=Исходные!$C$9,$D$18*5/14,IF(I46=Исходные!$C$9+1,$D$18*10/14,IF(I48=1,$D$18*EXP(-$D$19*I49),$D$18)))) -> 4.2857143 | J50: =IF(J46<Исходные!$C$9,0,IF(J46=Исходные!$C$9,$D$18*5/14,IF(J46=Исходные!$C$9+1,$D$18*10/14,IF(J48=1,$D$18*EXP(-$D$19*J49),$D$18)))) -> 8.5714286 | K50: =IF(K46<Исходные!$C$9,0,IF(K46=Исходные!$C$9,$D$18*5/14,IF(K46=Исходные!$C$9+1,$D$18*10/14,IF(K48=1,$D$18*EXP(-$D$19*K49),$D$18)))) -> 12 | L50: =IF(L46<Исходные!$C$9,0,IF(L46=Исходные!$C$9,$D$18*5/14,IF(L46=Исходные!$C$9+1,$D$18*10/14,IF(L48=1,$D$18*EXP(-$D$19*L49),$D$18)))) -> 12 | ... AR50: =IF(AR46<Исходные!$C$9,0,IF(AR46=Исходные!$C$9,$D$18*5/14,IF(AR46=Исходные!$C$9+1,$D$18*10/14,IF(AR48=1,$D$18*EXP(-$D$19*AR49),$D$18)))) -> 2.3039168
B51: Накопленный профиль | C51: млрд м³ | E51: =E50 -> 0 | F51: =E51+F50 -> 0 | G51: =F51+G50 -> 0 | H51: =G51+H50 -> 0 | I51: =H51+I50 -> 4.2857143 | J51: =I51+J50 -> 12.857143 | K51: =J51+K50 -> 24.857143 | L51: =K51+L50 -> 36.857143 | M51: =L51+M50 -> 48.857143 | ... AR51: =AQ51+AR50 -> 275.20035
B52: Добыча сырого газа | C52: млрд м³ | D52: =SUM(E52:AR52) -> 275.20035 | E52: =E50*$D$29 -> 0 | F52: =F50*$D$29 -> 0 | G52: =G50*$D$29 -> 0 | H52: =H50*$D$29 -> 0 | I52: =I50*$D$29 -> 4.2857143 | J52: =J50*$D$29 -> 8.5714286 | K52: =K50*$D$29 -> 12 | L52: =L50*$D$29 -> 12 | ... AR52: =AR50*$D$29 -> 2.3039168
B53: Накопленная добыча | C53: млрд м³ | E53: =E52 -> 0 | F53: =E53+F52 -> 0 | G53: =F53+G52 -> 0 | H53: =G53+H52 -> 0 | I53: =H53+I52 -> 4.2857143 | J53: =I53+J52 -> 12.857143 | K53: =J53+K52 -> 24.857143 | L53: =K53+L52 -> 36.857143 | M53: =L53+M52 -> 48.857143 | ... AR53: =AQ53+AR52 -> 275.20035
B54: Выработанность > 1 % НГЗ (старт Кр) | C54: 0/1 | E54: =IF(E53/Исходные!$C$6>Исходные!$C$29,1,0) -> 0 | F54: =IF(OR(E54=1,F53/Исходные!$C$6>Исходные!$C$29),1,0) -> 0 | G54: =IF(OR(F54=1,G53/Исходные!$C$6>Исходные!$C$29),1,0) -> 0 | H54: =IF(OR(G54=1,H53/Исходные!$C$6>Исходные!$C$29),1,0) -> 0 | I54: =IF(OR(H54=1,I53/Исходные!$C$6>Исходные!$C$29),1,0) -> 1 | J54: =IF(OR(I54=1,J53/Исходные!$C$6>Исходные!$C$29),1,0) -> 1 | K54: =IF(OR(J54=1,K53/Исходные!$C$6>Исходные!$C$29),1,0) -> 1 | L54: =IF(OR(K54=1,L53/Исходные!$C$6>Исходные!$C$29),1,0) -> 1 | M54: =IF(OR(L54=1,M53/Исходные!$C$6>Исходные!$C$29),1,0) -> 1 | ... AR54: =IF(OR(AQ54=1,AR53/Исходные!$C$6>Исходные!$C$29),1,0) -> 1
B55: n для Кр (порядковый год) | E55: =1 -> 1 | F55: =IF(F54=1,IF(E54=1,E55+1,1),1) -> 1 | G55: =IF(G54=1,IF(F54=1,F55+1,1),1) -> 1 | H55: =IF(H54=1,IF(G54=1,G55+1,1),1) -> 1 | I55: =IF(I54=1,IF(H54=1,H55+1,1),1) -> 1 | J55: =IF(J54=1,IF(I54=1,I55+1,1),1) -> 2 | K55: =IF(K54=1,IF(J54=1,J55+1,1),1) -> 3 | L55: =IF(L54=1,IF(K54=1,K55+1,1),1) -> 4 | M55: =IF(M54=1,IF(L54=1,L55+1,1),1) -> 5 | ... AR55: =IF(AR54=1,IF(AQ54=1,AQ55+1,1),1) -> 36
B56: Коэффициент Кр | E56: =IF($D$22=0,1,IF(E55>Исходные!$C$28,1,MIN(1,Исходные!$C$26*E55+Исходные!$C$27))) -> 0.21 | F56: =IF($D$22=0,1,IF(F55>Исходные!$C$28,1,MIN(1,Исходные!$C$26*F55+Исходные!$C$27))) -> 0.21 | G56: =IF($D$22=0,1,IF(G55>Исходные!$C$28,1,MIN(1,Исходные!$C$26*G55+Исходные!$C$27))) -> 0.21 | H56: =IF($D$22=0,1,IF(H55>Исходные!$C$28,1,MIN(1,Исходные!$C$26*H55+Исходные!$C$27))) -> 0.21 | I56: =IF($D$22=0,1,IF(I55>Исходные!$C$28,1,MIN(1,Исходные!$C$26*I55+Исходные!$C$27))) -> 0.21 | J56: =IF($D$22=0,1,IF(J55>Исходные!$C$28,1,MIN(1,Исходные!$C$26*J55+Исходные!$C$27))) -> 0.276 | K56: =IF($D$22=0,1,IF(K55>Исходные!$C$28,1,MIN(1,Исходные!$C$26*K55+Исходные!$C$27))) -> 0.342 | L56: =IF($D$22=0,1,IF(L55>Исходные!$C$28,1,MIN(1,Исходные!$C$26*L55+Исходные!$C$27))) -> 0.408 | ... AR56: =IF($D$22=0,1,IF(AR55>Исходные!$C$28,1,MIN(1,Исходные!$C$26*AR55+Исходные!$C$27))) -> 1
B57: Собственные нужды | C57: доля | E57: =IF(E46>=2038,Исходные!$C$22,Исходные!$C$21) -> 0.02 | F57: =IF(F46>=2038,Исходные!$C$22,Исходные!$C$21) -> 0.02 | G57: =IF(G46>=2038,Исходные!$C$22,Исходные!$C$21) -> 0.02 | H57: =IF(H46>=2038,Исходные!$C$22,Исходные!$C$21) -> 0.02 | I57: =IF(I46>=2038,Исходные!$C$22,Исходные!$C$21) -> 0.02 | J57: =IF(J46>=2038,Исходные!$C$22,Исходные!$C$21) -> 0.02 | K57: =IF(K46>=2038,Исходные!$C$22,Исходные!$C$21) -> 0.02 | L57: =IF(L46>=2038,Исходные!$C$22,Исходные!$C$21) -> 0.02 | ... AR57: =IF(AR46>=2038,Исходные!$C$22,Исходные!$C$21) -> 0.035
B58: Газ на подготовку | C58: млрд м³ | D58: =SUM(E58:AR58) -> 266.6612 | E58: =E52*(1-E57) -> 0 | F58: =F52*(1-F57) -> 0 | G58: =G52*(1-G57) -> 0 | H58: =H52*(1-H57) -> 0 | I58: =I52*(1-I57) -> 4.2 | J58: =J52*(1-J57) -> 8.4 | K58: =K52*(1-K57) -> 11.76 | L58: =L52*(1-L57) -> 11.76 | ... AR58: =AR52*(1-AR57) -> 2.2232798
B59: Газ на GTL | C59: млрд м³ | D59: =SUM(E59:AR59) -> 0 | E59: =IF(AND($D$17=1,E46>=Исходные!$C$42,E52>0),$D$44,0) -> 0 | F59: =IF(AND($D$17=1,F46>=Исходные!$C$42,F52>0),$D$44,0) -> 0 | G59: =IF(AND($D$17=1,G46>=Исходные!$C$42,G52>0),$D$44,0) -> 0 | H59: =IF(AND($D$17=1,H46>=Исходные!$C$42,H52>0),$D$44,0) -> 0 | I59: =IF(AND($D$17=1,I46>=Исходные!$C$42,I52>0),$D$44,0) -> 0 | J59: =IF(AND($D$17=1,J46>=Исходные!$C$42,J52>0),$D$44,0) -> 0 | K59: =IF(AND($D$17=1,K46>=Исходные!$C$42,K52>0),$D$44,0) -> 0 | L59: =IF(AND($D$17=1,L46>=Исходные!$C$42,L52>0),$D$44,0) -> 0 | ... AR59: =IF(AND($D$17=1,AR46>=Исходные!$C$42,AR52>0),$D$44,0) -> 0
B60: Товарный газ в ЕСГ | C60: млрд м³ | D60: =SUM(E60:AR60) -> 263.95723 | E60: =E58*$D$37/1000-E59 -> 0 | F60: =F58*$D$37/1000-F59 -> 0 | G60: =G58*$D$37/1000-G59 -> 0 | H60: =H58*$D$37/1000-H59 -> 0 | I60: =I58*$D$37/1000-I59 -> 4.1574117 | J60: =J58*$D$37/1000-J59 -> 8.3148234 | K60: =K58*$D$37/1000-K59 -> 11.640753 | L60: =L58*$D$37/1000-L59 -> 11.640753 | ... AR60: =AR58*$D$37/1000-AR59 -> 2.2007355
B61: Стабильный конденсат | C61: млн т | D61: =SUM(E61:AR61) -> 9.9518493 | E61: =E58*$D$34/1000 -> 0 | F61: =F58*$D$34/1000 -> 0 | G61: =G58*$D$34/1000 -> 0 | H61: =H58*$D$34/1000 -> 0 | I61: =I58*$D$34/1000 -> 0.15674484 | J61: =J58*$D$34/1000 -> 0.31348968 | K61: =K58*$D$34/1000 -> 0.43888556 | L61: =L58*$D$34/1000 -> 0.43888556 | ... AR61: =AR58*$D$34/1000 -> 0.082973246
B62: СУГ | C62: млн т | D62: =SUM(E62:AR62) -> 0 | E62: =E58*$D$35/1000 -> 0 | F62: =F58*$D$35/1000 -> 0 | G62: =G58*$D$35/1000 -> 0 | H62: =H58*$D$35/1000 -> 0 | I62: =I58*$D$35/1000 -> 0 | J62: =J58*$D$35/1000 -> 0 | K62: =K58*$D$35/1000 -> 0 | L62: =L58*$D$35/1000 -> 0 | ... AR62: =AR58*$D$35/1000 -> 0
B63: Этан | C63: млн т | D63: =SUM(E63:AR63) -> 0 | E63: =E58*$D$36/1000 -> 0 | F63: =F58*$D$36/1000 -> 0 | G63: =G58*$D$36/1000 -> 0 | H63: =H58*$D$36/1000 -> 0 | I63: =I58*$D$36/1000 -> 0 | J63: =J58*$D$36/1000 -> 0 | K63: =K58*$D$36/1000 -> 0 | L63: =L58*$D$36/1000 -> 0 | ... AR63: =AR58*$D$36/1000 -> 0
B64: Синтетическое ДТ | C64: млн т | D64: =SUM(E64:AR64) -> 0 | E64: =IF(E59>0,Исходные!$C$39/1000,0) -> 0 | F64: =IF(F59>0,Исходные!$C$39/1000,0) -> 0 | G64: =IF(G59>0,Исходные!$C$39/1000,0) -> 0 | H64: =IF(H59>0,Исходные!$C$39/1000,0) -> 0 | I64: =IF(I59>0,Исходные!$C$39/1000,0) -> 0 | J64: =IF(J59>0,Исходные!$C$39/1000,0) -> 0 | K64: =IF(K59>0,Исходные!$C$39/1000,0) -> 0 | L64: =IF(L59>0,Исходные!$C$39/1000,0) -> 0 | ... AR64: =IF(AR59>0,Исходные!$C$39/1000,0) -> 0
B65: Синтетический авиакеросин | C65: млн т | D65: =SUM(E65:AR65) -> 0 | E65: =IF(E59>0,Исходные!$C$40/1000,0) -> 0 | F65: =IF(F59>0,Исходные!$C$40/1000,0) -> 0 | G65: =IF(G59>0,Исходные!$C$40/1000,0) -> 0 | H65: =IF(H59>0,Исходные!$C$40/1000,0) -> 0 | I65: =IF(I59>0,Исходные!$C$40/1000,0) -> 0 | J65: =IF(J59>0,Исходные!$C$40/1000,0) -> 0 | K65: =IF(K59>0,Исходные!$C$40/1000,0) -> 0 | L65: =IF(L59>0,Исходные!$C$40/1000,0) -> 0 | ... AR65: =IF(AR59>0,Исходные!$C$40/1000,0) -> 0
B66: Нафта GTL (сдаётся с конденсатом) | C66: млн т | D66: =SUM(E66:AR66) -> 0 | E66: =IF(E59>0,$D$43-E64-E65,0) -> 0 | F66: =IF(F59>0,$D$43-F64-F65,0) -> 0 | G66: =IF(G59>0,$D$43-G64-G65,0) -> 0 | H66: =IF(H59>0,$D$43-H64-H65,0) -> 0 | I66: =IF(I59>0,$D$43-I64-I65,0) -> 0 | J66: =IF(J59>0,$D$43-J64-J65,0) -> 0 | K66: =IF(K59>0,$D$43-K64-K65,0) -> 0 | L66: =IF(L59>0,$D$43-L64-L65,0) -> 0 | ... AR66: =IF(AR59>0,$D$43-AR64-AR65,0) -> 0
B67: Выручка, налоги, затраты, млрд руб
B68: Выручка: газ | C68: млрд руб | D68: =SUM(E68:AR68) -> 1377.898 | E68: =E60*$D$39/1000 -> 0 | F68: =F60*$D$39/1000 -> 0 | G68: =G60*$D$39/1000 -> 0 | H68: =H60*$D$39/1000 -> 0 | I68: =I60*$D$39/1000 -> 21.702338 | J68: =J60*$D$39/1000 -> 43.404677 | K68: =K60*$D$39/1000 -> 60.766547 | L68: =L60*$D$39/1000 -> 60.766547 | ... AR68: =AR60*$D$39/1000 -> 11.488183
B69: Выручка: конденсат и нафта | C69: млрд руб | D69: =SUM(E69:AR69) -> 371.96032 | E69: =(E61+E66)*$D$40/1000 -> 0 | F69: =(F61+F66)*$D$40/1000 -> 0 | G69: =(G61+G66)*$D$40/1000 -> 0 | H69: =(H61+H66)*$D$40/1000 -> 0 | I69: =(I61+I66)*$D$40/1000 -> 5.8584952 | J69: =(J61+J66)*$D$40/1000 -> 11.71699 | K69: =(K61+K66)*$D$40/1000 -> 16.403787 | L69: =(L61+L66)*$D$40/1000 -> 16.403787 | ... AR69: =(AR61+AR66)*$D$40/1000 -> 3.101208
B70: Выручка: СУГ и этан | C70: млрд руб | D70: =SUM(E70:AR70) -> 0 | E70: =E62*Исходные!$C$19/1000+E63*Исходные!$C$20/1000 -> 0 | F70: =F62*Исходные!$C$19/1000+F63*Исходные!$C$20/1000 -> 0 | G70: =G62*Исходные!$C$19/1000+G63*Исходные!$C$20/1000 -> 0 | H70: =H62*Исходные!$C$19/1000+H63*Исходные!$C$20/1000 -> 0 | I70: =I62*Исходные!$C$19/1000+I63*Исходные!$C$20/1000 -> 0 | J70: =J62*Исходные!$C$19/1000+J63*Исходные!$C$20/1000 -> 0 | K70: =K62*Исходные!$C$19/1000+K63*Исходные!$C$20/1000 -> 0 | L70: =L62*Исходные!$C$19/1000+L63*Исходные!$C$20/1000 -> 0 | ... AR70: =AR62*Исходные!$C$19/1000+AR63*Исходные!$C$20/1000 -> 0
B71: Выручка: ДТ GTL | C71: млрд руб | D71: =SUM(E71:AR71) -> 0 | E71: =E64*$D$23/1000 -> 0 | F71: =F64*$D$23/1000 -> 0 | G71: =G64*$D$23/1000 -> 0 | H71: =H64*$D$23/1000 -> 0 | I71: =I64*$D$23/1000 -> 0 | J71: =J64*$D$23/1000 -> 0 | K71: =K64*$D$23/1000 -> 0 | L71: =L64*$D$23/1000 -> 0 | ... AR71: =AR64*$D$23/1000 -> 0
B72: Выручка: керосин GTL | C72: млрд руб | D72: =SUM(E72:AR72) -> 0 | E72: =E65*$D$24/1000 -> 0 | F72: =F65*$D$24/1000 -> 0 | G72: =G65*$D$24/1000 -> 0 | H72: =H65*$D$24/1000 -> 0 | I72: =I65*$D$24/1000 -> 0 | J72: =J65*$D$24/1000 -> 0 | K72: =K65*$D$24/1000 -> 0 | L72: =L65*$D$24/1000 -> 0 | ... AR72: =AR65*$D$24/1000 -> 0
B73: Выручка всего | C73: млрд руб | D73: =SUM(E73:AR73) -> 1749.8583 | E73: =SUM(E68:E72) -> 0 | F73: =SUM(F68:F72) -> 0 | G73: =SUM(G68:G72) -> 0 | H73: =SUM(H68:H72) -> 0 | I73: =SUM(I68:I72) -> 27.560834 | J73: =SUM(J68:J72) -> 55.121667 | K73: =SUM(K68:K72) -> 77.170334 | L73: =SUM(L68:L72) -> 77.170334 | ... AR73: =SUM(AR68:AR72) -> 14.589391
B74: НДПИ (газ + жидкие УВ, с Кр) | C74: млрд руб | D74: =SUM(E74:AR74) -> 234.56078 | E74: =E52*$D$37/1000*(Исходные!$C$23+Исходные!$C$24*E56)/1000+Исходные!$C$25*E56*(E69+E70) -> 0 | F74: =F52*$D$37/1000*(Исходные!$C$23+Исходные!$C$24*F56)/1000+Исходные!$C$25*F56*(F69+F70) -> 0 | G74: =G52*$D$37/1000*(Исходные!$C$23+Исходные!$C$24*G56)/1000+Исходные!$C$25*G56*(G69+G70) -> 0 | H74: =H52*$D$37/1000*(Исходные!$C$23+Исходные!$C$24*H56)/1000+Исходные!$C$25*H56*(H69+H70) -> 0 | I74: =I52*$D$37/1000*(Исходные!$C$23+Исходные!$C$24*I56)/1000+Исходные!$C$25*I56*(I69+I70) -> 2.502936 | J74: =J52*$D$37/1000*(Исходные!$C$23+Исходные!$C$24*J56)/1000+Исходные!$C$25*J56*(J69+J70) -> 5.2618646 | K74: =K52*$D$37/1000*(Исходные!$C$23+Исходные!$C$24*K56)/1000+Исходные!$C$25*K56*(K69+K70) -> 7.7250002 | L74: =L52*$D$37/1000*(Исходные!$C$23+Исходные!$C$24*L56)/1000+Исходные!$C$25*L56*(L69+L70) -> 8.08339 | ... AR74: =AR52*$D$37/1000*(Исходные!$C$23+Исходные!$C$24*AR56)/1000+Исходные!$C$25*AR56*(AR69+AR70) -> 2.1619141
B75: Капитальные вложения, млрд руб
B76: Доразведка, 3D, ТЭО и проектная документация | C76: млрд руб | D76: =CAPEX_нормы!$C$6*INDEX(CAPEX_нормы!$E$6:$I$6,MATCH($D$16,CAPEX_нормы!$E$5:$I$5,0))*$D$28 -> 15 | E76: =$D76*CAPEX_нормы!J$6 -> 15 | F76: =$D76*CAPEX_нормы!K$6 -> 0 | G76: =$D76*CAPEX_нормы!L$6 -> 0 | H76: =$D76*CAPEX_нормы!M$6 -> 0 | I76: =$D76*CAPEX_нормы!N$6 -> 0 | J76: =$D76*CAPEX_нормы!O$6 -> 0 | K76: =$D76*CAPEX_нормы!P$6 -> 0 | L76: =$D76*CAPEX_нормы!Q$6 -> 0 | ... W76: =$D76*CAPEX_нормы!AB$6 -> 0 | X76: 0 | Y76: 0 | Z76: 0 | AA76: 0 | AB76: 0 | AC76: 0 | AD76: 0 | AE76: 0 | AF76: 0 | AG76: 0 | AH76: 0 | AI76: 0 | AJ76: 0 | AK76: 0 | AL76: 0 | AM76: 0 | AN76: 0 | AO76: 0 | AP76: 0 | AQ76: 0 | AR76: 0
B77: Эксплуатационные скважины | C77: млрд руб | D77: =$D$42*$D$20*INDEX(CAPEX_нормы!$E$7:$I$7,MATCH($D$16,CAPEX_нормы!$E$5:$I$5,0))*$D$28 -> 85.714286 | E77: =$D77*CAPEX_нормы!J$7 -> 0 | F77: =$D77*CAPEX_нормы!K$7 -> 17.142857 | G77: =$D77*CAPEX_нормы!L$7 -> 25.714286 | H77: =$D77*CAPEX_нормы!M$7 -> 25.714286 | I77: =$D77*CAPEX_нормы!N$7 -> 6.8571429 | J77: =$D77*CAPEX_нормы!O$7 -> 0 | K77: =$D77*CAPEX_нормы!P$7 -> 0 | L77: =$D77*CAPEX_нормы!Q$7 -> 0 | ... W77: =$D77*CAPEX_нормы!AB$7 -> 0 | X77: 0 | Y77: 0 | Z77: 0 | AA77: 0 | AB77: 0 | AC77: 0 | AD77: 0 | AE77: 0 | AF77: 0 | AG77: 0 | AH77: 0 | AI77: 0 | AJ77: 0 | AK77: 0 | AL77: 0 | AM77: 0 | AN77: 0 | AO77: 0 | AP77: 0 | AQ77: 0 | AR77: 0
B78: Кусты скважин и газосборная сеть | C78: млрд руб | D78: =CAPEX_нормы!$C$8*$D$41*INDEX(CAPEX_нормы!$E$8:$I$8,MATCH($D$16,CAPEX_нормы!$E$5:$I$5,0))*$D$28 -> 41.743629 | E78: =$D78*CAPEX_нормы!J$8 -> 0 | F78: =$D78*CAPEX_нормы!K$8 -> 12.523089 | G78: =$D78*CAPEX_нормы!L$8 -> 16.697452 | H78: =$D78*CAPEX_нормы!M$8 -> 12.523089 | I78: =$D78*CAPEX_нормы!N$8 -> 0 | J78: =$D78*CAPEX_нормы!O$8 -> 0 | K78: =$D78*CAPEX_нормы!P$8 -> 0 | L78: =$D78*CAPEX_нормы!Q$8 -> 0 | ... W78: =$D78*CAPEX_нормы!AB$8 -> 0 | X78: 0 | Y78: 0 | Z78: 0 | AA78: 0 | AB78: 0 | AC78: 0 | AD78: 0 | AE78: 0 | AF78: 0 | AG78: 0 | AH78: 0 | AI78: 0 | AJ78: 0 | AK78: 0 | AL78: 0 | AM78: 0 | AN78: 0 | AO78: 0 | AP78: 0 | AQ78: 0 | AR78: 0
B79: УКПГ: НТС, регенерация метанола, стабилизация | C79: млрд руб | D79: =CAPEX_нормы!$C$9*$D$41*INDEX(CAPEX_нормы!$E$9:$I$9,MATCH($D$16,CAPEX_нормы!$E$5:$I$5,0))*$D$28 -> 70.129296 | E79: =$D79*CAPEX_нормы!J$9 -> 0 | F79: =$D79*CAPEX_нормы!K$9 -> 20.871811 | G79: =$D79*CAPEX_нормы!L$9 -> 29.220564 | H79: =$D79*CAPEX_нормы!M$9 -> 20.036922 | I79: =$D79*CAPEX_нормы!N$9 -> 0 | J79: =$D79*CAPEX_нормы!O$9 -> 0 | K79: =$D79*CAPEX_нормы!P$9 -> 0 | L79: =$D79*CAPEX_нормы!Q$9 -> 0 | ... W79: =$D79*CAPEX_нормы!AB$9 -> 0 | X79: 0 | Y79: 0 | Z79: 0 | AA79: 0 | AB79: 0 | AC79: 0 | AD79: 0 | AE79: 0 | AF79: 0 | AG79: 0 | AH79: 0 | AI79: 0 | AJ79: 0 | AK79: 0 | AL79: 0 | AM79: 0 | AN79: 0 | AO79: 0 | AP79: 0 | AQ79: 0 | AR79: 0
B80: Турбодетандерные агрегаты (5 шт.) | C80: млрд руб | D80: =CAPEX_нормы!$C$10*$D$41*INDEX(CAPEX_нормы!$E$10:$I$10,MATCH($D$16,CAPEX_нормы!$E$5:$I$5,0))*$D$28 -> 0 | E80: =$D80*CAPEX_нормы!J$10 -> 0 | F80: =$D80*CAPEX_нормы!K$10 -> 0 | G80: =$D80*CAPEX_нормы!L$10 -> 0 | H80: =$D80*CAPEX_нормы!M$10 -> 0 | I80: =$D80*CAPEX_нормы!N$10 -> 0 | J80: =$D80*CAPEX_нормы!O$10 -> 0 | K80: =$D80*CAPEX_нормы!P$10 -> 0 | L80: =$D80*CAPEX_нормы!Q$10 -> 0 | ... W80: =$D80*CAPEX_нормы!AB$10 -> 0 | X80: 0 | Y80: 0 | Z80: 0 | AA80: 0 | AB80: 0 | AC80: 0 | AD80: 0 | AE80: 0 | AF80: 0 | AG80: 0 | AH80: 0 | AI80: 0 | AJ80: 0 | AK80: 0 | AL80: 0 | AM80: 0 | AN80: 0 | AO80: 0 | AP80: 0 | AQ80: 0 | AR80: 0
B81: ТДА + деэтанизация + ГФУ + парк СУГ | C81: млрд руб | D81: =CAPEX_нормы!$C$11*$D$41*INDEX(CAPEX_нормы!$E$11:$I$11,MATCH($D$16,CAPEX_нормы!$E$5:$I$5,0))*$D$28 -> 0 | E81: =$D81*CAPEX_нормы!J$11 -> 0 | F81: =$D81*CAPEX_нормы!K$11 -> 0 | G81: =$D81*CAPEX_нормы!L$11 -> 0 | H81: =$D81*CAPEX_нормы!M$11 -> 0 | I81: =$D81*CAPEX_нормы!N$11 -> 0 | J81: =$D81*CAPEX_нормы!O$11 -> 0 | K81: =$D81*CAPEX_нормы!P$11 -> 0 | L81: =$D81*CAPEX_нормы!Q$11 -> 0 | ... W81: =$D81*CAPEX_нормы!AB$11 -> 0 | X81: 0 | Y81: 0 | Z81: 0 | AA81: 0 | AB81: 0 | AC81: 0 | AD81: 0 | AE81: 0 | AF81: 0 | AG81: 0 | AH81: 0 | AI81: 0 | AJ81: 0 | AK81: 0 | AL81: 0 | AM81: 0 | AN81: 0 | AO81: 0 | AP81: 0 | AQ81: 0 | AR81: 0
B82: Продуктопровод СУГ 120 км | C82: млрд руб | D82: =CAPEX_нормы!$C$12*$D$41*INDEX(CAPEX_нормы!$E$12:$I$12,MATCH($D$16,CAPEX_нормы!$E$5:$I$5,0))*$D$28 -> 0 | E82: =$D82*CAPEX_нормы!J$12 -> 0 | F82: =$D82*CAPEX_нормы!K$12 -> 0 | G82: =$D82*CAPEX_нормы!L$12 -> 0 | H82: =$D82*CAPEX_нормы!M$12 -> 0 | I82: =$D82*CAPEX_нормы!N$12 -> 0 | J82: =$D82*CAPEX_нормы!O$12 -> 0 | K82: =$D82*CAPEX_нормы!P$12 -> 0 | L82: =$D82*CAPEX_нормы!Q$12 -> 0 | ... W82: =$D82*CAPEX_нормы!AB$12 -> 0 | X82: 0 | Y82: 0 | Z82: 0 | AA82: 0 | AB82: 0 | AC82: 0 | AD82: 0 | AE82: 0 | AF82: 0 | AG82: 0 | AH82: 0 | AI82: 0 | AJ82: 0 | AK82: 0 | AL82: 0 | AM82: 0 | AN82: 0 | AO82: 0 | AP82: 0 | AQ82: 0 | AR82: 0
B83: Налив СУГ на ж/д | C83: млрд руб | D83: =CAPEX_нормы!$C$13*$D$41*INDEX(CAPEX_нормы!$E$13:$I$13,MATCH($D$16,CAPEX_нормы!$E$5:$I$5,0))*$D$28 -> 0 | E83: =$D83*CAPEX_нормы!J$13 -> 0 | F83: =$D83*CAPEX_нормы!K$13 -> 0 | G83: =$D83*CAPEX_нормы!L$13 -> 0 | H83: =$D83*CAPEX_нормы!M$13 -> 0 | I83: =$D83*CAPEX_нормы!N$13 -> 0 | J83: =$D83*CAPEX_нормы!O$13 -> 0 | K83: =$D83*CAPEX_нормы!P$13 -> 0 | L83: =$D83*CAPEX_нормы!Q$13 -> 0 | ... W83: =$D83*CAPEX_нормы!AB$13 -> 0 | X83: 0 | Y83: 0 | Z83: 0 | AA83: 0 | AB83: 0 | AC83: 0 | AD83: 0 | AE83: 0 | AF83: 0 | AG83: 0 | AH83: 0 | AI83: 0 | AJ83: 0 | AK83: 0 | AL83: 0 | AM83: 0 | AN83: 0 | AO83: 0 | AP83: 0 | AQ83: 0 | AR83: 0
B84: Пропановая холодильная установка | C84: млрд руб | D84: =CAPEX_нормы!$C$14*$D$41*INDEX(CAPEX_нормы!$E$14:$I$14,MATCH($D$16,CAPEX_нормы!$E$5:$I$5,0))*$D$28 -> 0 | E84: =$D84*CAPEX_нормы!J$14 -> 0 | F84: =$D84*CAPEX_нормы!K$14 -> 0 | G84: =$D84*CAPEX_нормы!L$14 -> 0 | H84: =$D84*CAPEX_нормы!M$14 -> 0 | I84: =$D84*CAPEX_нормы!N$14 -> 0 | J84: =$D84*CAPEX_нормы!O$14 -> 0 | K84: =$D84*CAPEX_нормы!P$14 -> 0 | L84: =$D84*CAPEX_нормы!Q$14 -> 0 | ... W84: =$D84*CAPEX_нормы!AB$14 -> 0 | X84: 0 | Y84: 0 | Z84: 0 | AA84: 0 | AB84: 0 | AC84: 0 | AD84: 0 | AE84: 0 | AF84: 0 | AG84: 0 | AH84: 0 | AI84: 0 | AJ84: 0 | AK84: 0 | AL84: 0 | AM84: 0 | AN84: 0 | AO84: 0 | AP84: 0 | AQ84: 0 | AR84: 0
B85: Криогенный блок извлечения этана | C85: млрд руб | D85: =CAPEX_нормы!$C$15*$D$41*INDEX(CAPEX_нормы!$E$15:$I$15,MATCH($D$16,CAPEX_нормы!$E$5:$I$5,0))*$D$28 -> 0 | E85: =$D85*CAPEX_нормы!J$15 -> 0 | F85: =$D85*CAPEX_нормы!K$15 -> 0 | G85: =$D85*CAPEX_нормы!L$15 -> 0 | H85: =$D85*CAPEX_нормы!M$15 -> 0 | I85: =$D85*CAPEX_нормы!N$15 -> 0 | J85: =$D85*CAPEX_нормы!O$15 -> 0 | K85: =$D85*CAPEX_нормы!P$15 -> 0 | L85: =$D85*CAPEX_нормы!Q$15 -> 0 | ... W85: =$D85*CAPEX_нормы!AB$15 -> 0 | X85: 0 | Y85: 0 | Z85: 0 | AA85: 0 | AB85: 0 | AC85: 0 | AD85: 0 | AE85: 0 | AF85: 0 | AG85: 0 | AH85: 0 | AI85: 0 | AJ85: 0 | AK85: 0 | AL85: 0 | AM85: 0 | AN85: 0 | AO85: 0 | AP85: 0 | AQ85: 0 | AR85: 0
B86: Энергоцентр (ЭСН), промбаза | C86: млрд руб | D86: =CAPEX_нормы!$C$16*$D$41*INDEX(CAPEX_нормы!$E$16:$I$16,MATCH($D$16,CAPEX_нормы!$E$5:$I$5,0))*$D$28 -> 10.772549 | E86: =$D86*CAPEX_нормы!J$16 -> 0 | F86: =$D86*CAPEX_нормы!K$16 -> 4.4885658 | G86: =$D86*CAPEX_нормы!L$16 -> 4.4885658 | H86: =$D86*CAPEX_нормы!M$16 -> 1.7954285 | I86: =$D86*CAPEX_нормы!N$16 -> 0 | J86: =$D86*CAPEX_нормы!O$16 -> 0 | K86: =$D86*CAPEX_нормы!P$16 -> 0 | L86: =$D86*CAPEX_нормы!Q$16 -> 0 | ... W86: =$D86*CAPEX_нормы!AB$16 -> 0 | X86: 0 | Y86: 0 | Z86: 0 | AA86: 0 | AB86: 0 | AC86: 0 | AD86: 0 | AE86: 0 | AF86: 0 | AG86: 0 | AH86: 0 | AI86: 0 | AJ86: 0 | AK86: 0 | AL86: 0 | AM86: 0 | AN86: 0 | AO86: 0 | AP86: 0 | AQ86: 0 | AR86: 0
B87: Вахтовый жилой комплекс у УКПГ | C87: млрд руб | D87: =$D$30*INDEX(CAPEX_нормы!$E$17:$I$17,MATCH($D$16,CAPEX_нормы!$E$5:$I$5,0))*$D$28 -> 4 | E87: =$D87*CAPEX_нормы!J$17 -> 0 | F87: =$D87*CAPEX_нормы!K$17 -> 1.5 | G87: =$D87*CAPEX_нормы!L$17 -> 1.5 | H87: =$D87*CAPEX_нормы!M$17 -> 1 | I87: =$D87*CAPEX_нормы!N$17 -> 0 | J87: =$D87*CAPEX_нормы!O$17 -> 0 | K87: =$D87*CAPEX_нормы!P$17 -> 0 | L87: =$D87*CAPEX_нормы!Q$17 -> 0 | ... W87: =$D87*CAPEX_нормы!AB$17 -> 0 | X87: 0 | Y87: 0 | Z87: 0 | AA87: 0 | AB87: 0 | AC87: 0 | AD87: 0 | AE87: 0 | AF87: 0 | AG87: 0 | AH87: 0 | AI87: 0 | AJ87: 0 | AK87: 0 | AL87: 0 | AM87: 0 | AN87: 0 | AO87: 0 | AP87: 0 | AQ87: 0 | AR87: 0
B88: Автодорога до Бованенково 120 км | C88: млрд руб | D88: =$D$31*INDEX(CAPEX_нормы!$E$18:$I$18,MATCH($D$16,CAPEX_нормы!$E$5:$I$5,0))*$D$28 -> 24 | E88: =$D88*CAPEX_нормы!J$18 -> 0 | F88: =$D88*CAPEX_нормы!K$18 -> 9.6 | G88: =$D88*CAPEX_нормы!L$18 -> 9.6 | H88: =$D88*CAPEX_нормы!M$18 -> 4.8 | I88: =$D88*CAPEX_нормы!N$18 -> 0 | J88: =$D88*CAPEX_нормы!O$18 -> 0 | K88: =$D88*CAPEX_нормы!P$18 -> 0 | L88: =$D88*CAPEX_нормы!Q$18 -> 0 | ... W88: =$D88*CAPEX_нормы!AB$18 -> 0 | X88: 0 | Y88: 0 | Z88: 0 | AA88: 0 | AB88: 0 | AC88: 0 | AD88: 0 | AE88: 0 | AF88: 0 | AG88: 0 | AH88: 0 | AI88: 0 | AJ88: 0 | AK88: 0 | AL88: 0 | AM88: 0 | AN88: 0 | AO88: 0 | AP88: 0 | AQ88: 0 | AR88: 0
B89: Газопровод 120 км до Бованенково | C89: млрд руб | D89: =CAPEX_нормы!$C$19*$D$41*INDEX(CAPEX_нормы!$E$19:$I$19,MATCH($D$16,CAPEX_нормы!$E$5:$I$5,0))*$D$28 -> 37.703923 | E89: =$D89*CAPEX_нормы!J$19 -> 0 | F89: =$D89*CAPEX_нормы!K$19 -> 10.772539 | G89: =$D89*CAPEX_нормы!L$19 -> 17.954231 | H89: =$D89*CAPEX_нормы!M$19 -> 8.9771155 | I89: =$D89*CAPEX_нормы!N$19 -> 0 | J89: =$D89*CAPEX_нормы!O$19 -> 0 | K89: =$D89*CAPEX_нормы!P$19 -> 0 | L89: =$D89*CAPEX_нормы!Q$19 -> 0 | ... W89: =$D89*CAPEX_нормы!AB$19 -> 0 | X89: 0 | Y89: 0 | Z89: 0 | AA89: 0 | AB89: 0 | AC89: 0 | AD89: 0 | AE89: 0 | AF89: 0 | AG89: 0 | AH89: 0 | AI89: 0 | AJ89: 0 | AK89: 0 | AL89: 0 | AM89: 0 | AN89: 0 | AO89: 0 | AP89: 0 | AQ89: 0 | AR89: 0
B90: Конденсатопровод 120 км | C90: млрд руб | D90: =CAPEX_нормы!$C$20*$D$41*INDEX(CAPEX_нормы!$E$20:$I$20,MATCH($D$16,CAPEX_нормы!$E$5:$I$5,0))*$D$28 -> 8.6180395 | E90: =$D90*CAPEX_нормы!J$20 -> 0 | F90: =$D90*CAPEX_нормы!K$20 -> 0 | G90: =$D90*CAPEX_нормы!L$20 -> 5.3862747 | H90: =$D90*CAPEX_нормы!M$20 -> 3.2317648 | I90: =$D90*CAPEX_нормы!N$20 -> 0 | J90: =$D90*CAPEX_нормы!O$20 -> 0 | K90: =$D90*CAPEX_нормы!P$20 -> 0 | L90: =$D90*CAPEX_нормы!Q$20 -> 0 | ... W90: =$D90*CAPEX_нормы!AB$20 -> 0 | X90: 0 | Y90: 0 | Z90: 0 | AA90: 0 | AB90: 0 | AC90: 0 | AD90: 0 | AE90: 0 | AF90: 0 | AG90: 0 | AH90: 0 | AI90: 0 | AJ90: 0 | AK90: 0 | AL90: 0 | AM90: 0 | AN90: 0 | AO90: 0 | AP90: 0 | AQ90: 0 | AR90: 0
B91: ДКС (2 очереди) | C91: млрд руб | D91: =CAPEX_нормы!$C$21*$D$41*INDEX(CAPEX_нормы!$E$21:$I$21,MATCH($D$16,CAPEX_нормы!$E$5:$I$5,0))*$D$28 -> 49.374185 | E91: =$D91*CAPEX_нормы!J$21 -> 0 | F91: =$D91*CAPEX_нормы!K$21 -> 0 | G91: =$D91*CAPEX_нормы!L$21 -> 0 | H91: =$D91*CAPEX_нормы!M$21 -> 0 | I91: =$D91*CAPEX_нормы!N$21 -> 0 | J91: =$D91*CAPEX_нормы!O$21 -> 0 | K91: =$D91*CAPEX_нормы!P$21 -> 0 | L91: =$D91*CAPEX_нормы!Q$21 -> 0 | ... W91: =$D91*CAPEX_нормы!AB$21 -> 17.954231 | X91: 0 | Y91: 0 | Z91: 0 | AA91: 0 | AB91: 0 | AC91: 0 | AD91: 0 | AE91: 0 | AF91: 0 | AG91: 0 | AH91: 0 | AI91: 0 | AJ91: 0 | AK91: 0 | AL91: 0 | AM91: 0 | AN91: 0 | AO91: 0 | AP91: 0 | AQ91: 0 | AR91: 0
B92: GTL-установка у ст. Бованенково + налив | C92: млрд руб | D92: =$D$32*$D$17*INDEX(CAPEX_нормы!$E$22:$I$22,MATCH($D$16,CAPEX_нормы!$E$5:$I$5,0))*$D$28 -> 0 | E92: =$D92*CAPEX_нормы!J$22 -> 0 | F92: =$D92*CAPEX_нормы!K$22 -> 0 | G92: =$D92*CAPEX_нормы!L$22 -> 0 | H92: =$D92*CAPEX_нормы!M$22 -> 0 | I92: =$D92*CAPEX_нормы!N$22 -> 0 | J92: =$D92*CAPEX_нормы!O$22 -> 0 | K92: =$D92*CAPEX_нормы!P$22 -> 0 | L92: =$D92*CAPEX_нормы!Q$22 -> 0 | ... W92: =$D92*CAPEX_нормы!AB$22 -> 0 | X92: 0 | Y92: 0 | Z92: 0 | AA92: 0 | AB92: 0 | AC92: 0 | AD92: 0 | AE92: 0 | AF92: 0 | AG92: 0 | AH92: 0 | AI92: 0 | AJ92: 0 | AK92: 0 | AL92: 0 | AM92: 0 | AN92: 0 | AO92: 0 | AP92: 0 | AQ92: 0 | AR92: 0
B93: CAPEX всего | C93: млрд руб | D93: =SUM(E93:AR93) -> 347.05583 | E93: =SUM(E76:E92) -> 15 | F93: =SUM(F76:F92) -> 76.898861 | G93: =SUM(G76:G92) -> 110.56137 | H93: =SUM(H76:H92) -> 78.078605 | I93: =SUM(I76:I92) -> 6.8571429 | J93: =SUM(J76:J92) -> 0 | K93: =SUM(K76:K92) -> 0 | L93: =SUM(L76:L92) -> 0 | ... AR93: =SUM(AR76:AR92) -> 0
B94: Накопленный CAPEX | C94: млрд руб | E94: =E93 -> 15 | F94: =E94+F93 -> 91.898861 | G94: =F94+G93 -> 202.46023 | H94: =G94+H93 -> 280.53884 | I94: =H94+I93 -> 287.39598 | J94: =I94+J93 -> 287.39598 | K94: =J94+K93 -> 287.39598 | L94: =K94+L93 -> 287.39598 | M94: =L94+M93 -> 287.39598 | ... AR94: =AQ94+AR93 -> 347.05583
B95: Операционные затраты, амортизация, налоги, млрд руб
B96: Признак добычи | C96: 0/1 | E96: =IF(E52>0,1,0) -> 0 | F96: =IF(F52>0,1,0) -> 0 | G96: =IF(G52>0,1,0) -> 0 | H96: =IF(H52>0,1,0) -> 0 | I96: =IF(I52>0,1,0) -> 1 | J96: =IF(J52>0,1,0) -> 1 | K96: =IF(K52>0,1,0) -> 1 | L96: =IF(L52>0,1,0) -> 1 | ... AR96: =IF(AR52>0,1,0) -> 1
B97: OPEX (пост. + перем. + СУГ + терминал + GTL + чужой ВЖК) | C97: млрд руб | D97: =SUM(E97:AR97) -> 225.79578 | E97: =E96*Исходные!$C$33*E94+E52*Исходные!$C$34/1000+E62*Исходные!$C$35/1000+(E61+E62)*Исходные!$C$36/1000+IF(E59>0,$D$43*Исходные!$C$41/1000,0)+E96*$D$33 -> 0 | F97: =F96*Исходные!$C$33*F94+F52*Исходные!$C$34/1000+F62*Исходные!$C$35/1000+(F61+F62)*Исходные!$C$36/1000+IF(F59>0,$D$43*Исходные!$C$41/1000,0)+F96*$D$33 -> 0 | G97: =G96*Исходные!$C$33*G94+G52*Исходные!$C$34/1000+G62*Исходные!$C$35/1000+(G61+G62)*Исходные!$C$36/1000+IF(G59>0,$D$43*Исходные!$C$41/1000,0)+G96*$D$33 -> 0 | H97: =H96*Исходные!$C$33*H94+H52*Исходные!$C$34/1000+H62*Исходные!$C$35/1000+(H61+H62)*Исходные!$C$36/1000+IF(H59>0,$D$43*Исходные!$C$41/1000,0)+H96*$D$33 -> 0 | I97: =I96*Исходные!$C$33*I94+I52*Исходные!$C$34/1000+I62*Исходные!$C$35/1000+(I61+I62)*Исходные!$C$36/1000+IF(I59>0,$D$43*Исходные!$C$41/1000,0)+I96*$D$33 -> 5.0321693 | J97: =J96*Исходные!$C$33*J94+J52*Исходные!$C$34/1000+J62*Исходные!$C$35/1000+(J61+J62)*Исходные!$C$36/1000+IF(J59>0,$D$43*Исходные!$C$41/1000,0)+J96*$D$33 -> 5.7533988 | K97: =K96*Исходные!$C$33*K94+K52*Исходные!$C$34/1000+K62*Исходные!$C$35/1000+(K61+K62)*Исходные!$C$36/1000+IF(K59>0,$D$43*Исходные!$C$41/1000,0)+K96*$D$33 -> 6.3303825 | L97: =L96*Исходные!$C$33*L94+L52*Исходные!$C$34/1000+L62*Исходные!$C$35/1000+(L61+L62)*Исходные!$C$36/1000+IF(L59>0,$D$43*Исходные!$C$41/1000,0)+L96*$D$33 -> 6.3303825 | ... AR97: =AR96*Исходные!$C$33*AR94+AR52*Исходные!$C$34/1000+AR62*Исходные!$C$35/1000+(AR61+AR62)*Исходные!$C$36/1000+IF(AR59>0,$D$43*Исходные!$C$41/1000,0)+AR96*$D$33 -> 5.5929116
B98: Ввод основных средств | C98: млрд руб | D98: =SUM(E98:AR98) -> 347.05583 | E98: 0 | F98: 0 | G98: 0 | H98: 0 | I98: =SUM(E93:H93) -> 280.53884 | J98: =I93 -> 6.8571429 | K98: =J93 -> 0 | L98: =K93 -> 0 | M98: =L93 -> 0 | N98: =M93 -> 0 | O98: =N93 -> 2.5714286 | P98: =O93 -> 16.037102 | Q98: =P93 -> 20.52566 | ... AR98: =AQ93 -> 0
B99: Амортизация | C99: млрд руб | D99: =SUM(E99:AR99) -> 347.05583 | E99: =SUM(OFFSET(E98,0,-MIN(Исходные!$C$32-1,E47),1,MIN(Исходные!$C$32,E47+1)))/Исходные!$C$32 -> 0 | F99: =SUM(OFFSET(F98,0,-MIN(Исходные!$C$32-1,F47),1,MIN(Исходные!$C$32,F47+1)))/Исходные!$C$32 -> 0 | G99: =SUM(OFFSET(G98,0,-MIN(Исходные!$C$32-1,G47),1,MIN(Исходные!$C$32,G47+1)))/Исходные!$C$32 -> 0 | H99: =SUM(OFFSET(H98,0,-MIN(Исходные!$C$32-1,H47),1,MIN(Исходные!$C$32,H47+1)))/Исходные!$C$32 -> 0 | I99: =SUM(OFFSET(I98,0,-MIN(Исходные!$C$32-1,I47),1,MIN(Исходные!$C$32,I47+1)))/Исходные!$C$32 -> 18.702589 | J99: =SUM(OFFSET(J98,0,-MIN(Исходные!$C$32-1,J47),1,MIN(Исходные!$C$32,J47+1)))/Исходные!$C$32 -> 19.159732 | K99: =SUM(OFFSET(K98,0,-MIN(Исходные!$C$32-1,K47),1,MIN(Исходные!$C$32,K47+1)))/Исходные!$C$32 -> 19.159732 | L99: =SUM(OFFSET(L98,0,-MIN(Исходные!$C$32-1,L47),1,MIN(Исходные!$C$32,L47+1)))/Исходные!$C$32 -> 19.159732 | ... AR99: =SUM(OFFSET(AR98,0,-MIN(Исходные!$C$32-1,AR47),1,MIN(Исходные!$C$32,AR47+1)))/Исходные!$C$32 -> 0
B100: Накопленная амортизация | C100: млрд руб | E100: =E99 -> 0 | F100: =E100+F99 -> 0 | G100: =F100+G99 -> 0 | H100: =G100+H99 -> 0 | I100: =H100+I99 -> 18.702589 | J100: =I100+J99 -> 37.862321 | K100: =J100+K99 -> 57.022053 | L100: =K100+L99 -> 76.181786 | M100: =L100+M99 -> 95.341518 | ... AR100: =AQ100+AR99 -> 347.05583
B101: Налог на имущество | C101: млрд руб | D101: =SUM(E101:AR101) -> 54.909972 | E101: =E96*Исходные!$C$31*(E94-E100) -> 0 | F101: =F96*Исходные!$C$31*(F94-F100) -> 0 | G101: =G96*Исходные!$C$31*(G94-G100) -> 0 | H101: =H96*Исходные!$C$31*(H94-H100) -> 0 | I101: =I96*Исходные!$C$31*(I94-I100) -> 5.9112546 | J101: =J96*Исходные!$C$31*(J94-J100) -> 5.4897405 | K101: =K96*Исходные!$C$31*(K94-K100) -> 5.0682264 | L101: =L96*Исходные!$C$31*(L94-L100) -> 4.6467123 | ... AR101: =AR96*Исходные!$C$31*(AR94-AR100) -> 0
B102: EBITDA | C102: млрд руб | D102: =SUM(E102:AR102) -> 1234.5918 | E102: =E73-E74-E97-E101 -> 0 | F102: =F73-F74-F97-F101 -> 0 | G102: =G73-G74-G97-G101 -> 0 | H102: =H73-H74-H97-H101 -> 0 | I102: =I73-I74-I97-I101 -> 14.114474 | J102: =J73-J74-J97-J101 -> 38.616663 | K102: =K73-K74-K97-K101 -> 58.046725 | L102: =L73-L74-L97-L101 -> 58.109849 | ... AR102: =AR73-AR74-AR97-AR101 -> 6.8345655
B103: Налог на прибыль | C103: млрд руб | D103: =SUM(E103:AR103) -> 223.03102 | E103: =MAX(0,E102-E99)*Исходные!$C$30 -> 0 | F103: =MAX(0,F102-F99)*Исходные!$C$30 -> 0 | G103: =MAX(0,G102-G99)*Исходные!$C$30 -> 0 | H103: =MAX(0,H102-H99)*Исходные!$C$30 -> 0 | I103: =MAX(0,I102-I99)*Исходные!$C$30 -> 0 | J103: =MAX(0,J102-J99)*Исходные!$C$30 -> 4.8642328 | K103: =MAX(0,K102-K99)*Исходные!$C$30 -> 9.7217482 | L103: =MAX(0,L102-L99)*Исходные!$C$30 -> 9.7375293 | ... AR103: =MAX(0,AR102-AR99)*Исходные!$C$30 -> 1.7086414
...

Sheet Расчёт_Б
B2: Расчёт: Б. ТДА + ГФУ (СУГ)
B3: Глубокое извлечение C3+, СУГ по ж/д. Денежный поток по годам, млрд руб. (реальные цены 2026 г.)
B5: ЧДД (NPV) при ставке варианта, млрд руб | C5: =SUM(E107:AR107) -> -9.3797347
B6: ВНД (IRR), реальная | C6: =IRR(E105:AR105,0.1) -> 0.096053345
B7: Дисконтированная окупаемость, год | C7: =IF(SUM(E109:AR109)=0,"нет",2067-SUM(E109:AR109)) -> нет
B8: Индекс доходности (PI) | C8: =1+C5/SUMPRODUCT(E93:AR93,E106:AR106) -> 0.96857102
B9: CAPEX всего, млрд руб | C9: =D93 -> 423.0023
B10: Фонд скважин, шт. | C10: =$D$42 -> 57.142857
B11: Проверка: Σ профиля − извлекаемые (должно быть ≈ 0), млрд м³ | C11: =D50-Исходные!$C$8 -> 0.0003531191
B13: Показатель | C13: Ед. | D13: Итого / знач. | E13: 2027 | F13: 2028 | G13: 2029 | H13: 2030 | I13: 2031 | J13: 2032 | K13: 2033 | L13: 2034 | M13: 2035 | N13: 2036 | O13: 2037 | P13: 2038 | Q13: 2039 | R13: 2040 | S13: 2041 | T13: 2042 | U13: 2043 | V13: 2044 | W13: 2045 | X13: 2046 | Y13: 2047 | Z13: 2048 | AA13: 2049 | AB13: 2050 | AC13: 2051 | AD13: 2052 | AE13: 2053 | AF13: 2054 | AG13: 2055 | AH13: 2056 | AI13: 2057 | AJ13: 2058 | AK13: 2059 | AL13: 2060 | AM13: 2061 | AN13: 2062 | AO13: 2063 | AP13: 2064 | AQ13: 2065 | AR13: 2066
B14: Параметры варианта (ссылки на «Сценарии» и «Исходные»)
B15: Технология (столбец баланса) | C15: код | D15: =Сценарии!$E$6 -> B
B16: Состав CAPEX | C16: код | D16: =Сценарии!$E$7 -> B
B17: GTL (1 — есть) | C17: 0/1 | D17: =Сценарии!$E$8 -> 0
B18: Полка добычи | C18: млрд м³/год | D18: =Сценарии!$E$9 -> 12
B19: Темп падения | C19: 1/год | D19: =Сценарии!$E$10 -> 0.071752
B20: Стоимость скважины | C20: млрд руб | D20: =Сценарии!$E$11 -> 1.5
B21: Дебит скважины | C21: млн м³/сут | D21: =Сценарии!$E$12 -> 0.75
B22: Кр (п-ов Ямал) в НДПИ | C22: 0/1 | D22: =Сценарии!$E$13 -> 1
B23: Цена ДТ GTL | C23: руб/т | D23: =Сценарии!$E$14 -> 56100
B24: Цена керосина GTL | C24: руб/т | D24: =Сценарии!$E$15 -> 64500
B25: Цена газа | C25: руб/1000 м³ | D25: =Сценарии!$E$16 -> 4705
B26: Brent | C26: $/барр. | D26: =Сценарии!$E$17 -> 65
B27: Ставка дисконтирования | C27: доля | D27: =Сценарии!$E$18 -> 0.1
B28: Множитель CAPEX | C28: x | D28: =Сценарии!$E$19 -> 1
B29: Множитель добычи | C29: x | D29: =Сценарии!$E$20 -> 1
B30: ВЖК у УКПГ | C30: млрд руб | D30: =Сценарии!$E$21 -> 4
B31: Автодорога | C31: млрд руб | D31: =Сценарии!$E$22 -> 24
B32: GTL + налив | C32: млрд руб | D32: =Сценарии!$E$23 -> 10.75
B33: Услуги чужого ВЖК | C33: млрд руб/год | D33: =Сценарии!$E$24 -> 0
B34: Выход конденсата | C34: кг/1000 м³ | D34: =INDEX(Баланс!$D$18:$G$18,MATCH($D$15,Баланс!$D$17:$G$17,0)) -> 32.941018
B35: Выход СУГ | C35: кг/1000 м³ | D35: =INDEX(Баланс!$D$19:$G$19,MATCH($D$15,Баланс!$D$17:$G$17,0)) -> 72.968324
B36: Выход этана | C36: кг/1000 м³ | D36: =INDEX(Баланс!$D$20:$G$20,MATCH($D$15,Баланс!$D$17:$G$17,0)) -> 0
B37: Товарный газ | C37: м³/1000 м³ | D37: =INDEX(Баланс!$D$21:$G$21,MATCH($D$15,Баланс!$D$17:$G$17,0)) -> 955.35768
B38: Теплота сгорания товарного газа | C38: МДж/м³ | D38: =INDEX(Баланс!$D$22:$G$22,MATCH($D$15,Баланс!$D$17:$G$17,0)) -> 34.707378
B39: Цена товарного газа с учётом теплоты | C39: руб/1000 м³ | D39: =$D$25*$D$38/Исходные!$C$12 -> 4937.1023
B40: Нетбэк конденсата на промысле | C40: руб/т | D40: =($D$26-Исходные!$C$16)*Исходные!$C$17*Исходные!$C$15-Исходные!$C$18 -> 37376
B41: Коэффициент масштаба объектов (полка/14)^0,7 | C41: x | D41: =($D$18/14)^0.7 -> 0.89771245
B42: Фонд эксплуатационных скважин | C42: шт. | D42: =100*$D$18/14*0.5/$D$21 -> 57.142857
B43: GTL: синтетические УВ | C43: млн т/год | D43: =(Исходные!$C$39+Исходные!$C$40)/Исходные!$C$38/1000 -> 0.076502732
B44: GTL: газ на установку | C44: млрд м³/год | D44: =$D$43/Исходные!$C$37 -> 0.18659203
B45: Добыча и продукция
B46: Год | E46: 2027 | F46: 2028 | G46: 2029 | H46: 2030 | I46: 2031 | J46: 2032 | K46: 2033 | L46: 2034 | M46: 2035 | N46: 2036 | O46: 2037 | P46: 2038 | Q46: 2039 | R46: 2040 | S46: 2041 | T46: 2042 | U46: 2043 | V46: 2044 | W46: 2045 | X46: 2046 | Y46: 2047 | Z46: 2048 | AA46: 2049 | AB46: 2050 | AC46: 2051 | AD46: 2052 | AE46: 2053 | AF46: 2054 | AG46: 2055 | AH46: 2056 | AI46: 2057 | AJ46: 2058 | AK46: 2059 | AL46: 2060 | AM46: 2061 | AN46: 2062 | AO46: 2063 | AP46: 2064 | AQ46: 2065 | AR46: 2066
B47: Номер года от начала (для дисконтирования) | E47: =E46-2027 -> 0 | F47: =F46-2027 -> 1 | G47: =G46-2027 -> 2 | H47: =H46-2027 -> 3 | I47: =I46-2027 -> 4 | J47: =J46-2027 -> 5 | K47: =K46-2027 -> 6 | L47: =L46-2027 -> 7 | ... AR47: =AR46-2027 -> 39
B48: Признак падения добычи | C48: 0/1 | E48: 0 | F48: =IF(F46<=Исходные!$C$9+1,0,IF(OR(E48=1,E51+$D$18>Исходные!$C$10*Исходные!$C$8),1,0)) -> 0 | G48: =IF(G46<=Исходные!$C$9+1,0,IF(OR(F48=1,F51+$D$18>Исходные!$C$10*Исходные!$C$8),1,0)) -> 0 | H48: =IF(H46<=Исходные!$C$9+1,0,IF(OR(G48=1,G51+$D$18>Исходные!$C$10*Исходные!$C$8),1,0)) -> 0 | I48: =IF(I46<=Исходные!$C$9+1,0,IF(OR(H48=1,H51+$D$18>Исходные!$C$10*Исходные!$C$8),1,0)) -> 0 | J48: =IF(J46<=Исходные!$C$9+1,0,IF(OR(I48=1,I51+$D$18>Исходные!$C$10*Исходные!$C$8),1,0)) -> 0 | K48: =IF(K46<=Исходные!$C$9+1,0,IF(OR(J48=1,J51+$D$18>Исходные!$C$10*Исходные!$C$8),1,0)) -> 0 | L48: =IF(L46<=Исходные!$C$9+1,0,IF(OR(K48=1,K51+$D$18>Исходные!$C$10*Исходные!$C$8),1,0)) -> 0 | M48: =IF(M46<=Исходные!$C$9+1,0,IF(OR(L48=1,L51+$D$18>Исходные!$C$10*Исходные!$C$8),1,0)) -> 0 | ... AR48: =IF(AR46<=Исходные!$C$9+1,0,IF(OR(AQ48=1,AQ51+$D$18>Исходные!$C$10*Исходные!$C$8),1,0)) -> 1
B49: Год падения, порядковый | E49: 0 | F49: =IF(F48=1,E49+1,0) -> 0 | G49: =IF(G48=1,F49+1,0) -> 0 | H49: =IF(H48=1,G49+1,0) -> 0 | I49: =IF(I48=1,H49+1,0) -> 0 | J49: =IF(J48=1,I49+1,0) -> 0 | K49: =IF(K48=1,J49+1,0) -> 0 | L49: =IF(L48=1,K49+1,0) -> 0 | M49: =IF(M48=1,L49+1,0) -> 0 | ... AR49: =IF(AR48=1,AQ49+1,0) -> 23
B50: Профиль добычи (до множителя) | C50: млрд м³ | D50: =SUM(E50:AR50) -> 275.20035 | E50: =IF(E46<Исходные!$C$9,0,IF(E46=Исходные!$C$9,$D$18*5/14,IF(E46=Исходные!$C$9+1,$D$18*10/14,IF(E48=1,$D$18*EXP(-$D$19*E49),$D$18)))) -> 0 | F50: =IF(F46<Исходные!$C$9,0,IF(F46=Исходные!$C$9,$D$18*5/14,IF(F46=Исходные!$C$9+1,$D$18*10/14,IF(F48=1,$D$18*EXP(-$D$19*F49),$D$18)))) -> 0 | G50: =IF(G46<Исходные!$C$9,0,IF(G46=Исходные!$C$9,$D$18*5/14,IF(G46=Исходные!$C$9+1,$D$18*10/14,IF(G48=1,$D$18*EXP(-$D$19*G49),$D$18)))) -> 0 | H50: =IF(H46<Исходные!$C$9,0,IF(H46=Исходные!$C$9,$D$18*5/14,IF(H46=Исходные!$C$9+1,$D$18*10/14,IF(H48=1,$D$18*EXP(-$D$19*H49),$D$18)))) -> 0 | I50: =IF(I46<Исходные!$C$9,0,IF(I46=Исходные!$C$9,$D$18*5/14,IF(I46=Исходные!$C$9+1,$D$18*10/14,IF(I48=1,$D$18*EXP(-$D$19*I49),$D$18)))) -> 4.2857143 | J50: =IF(J46<Исходные!$C$9,0,IF(J46=Исходные!$C$9,$D$18*5/14,IF(J46=Исходные!$C$9+1,$D$18*10/14,IF(J48=1,$D$18*EXP(-$D$19*J49),$D$18)))) -> 8.5714286 | K50: =IF(K46<Исходные!$C$9,0,IF(K46=Исходные!$C$9,$D$18*5/14,IF(K46=Исходные!$C$9+1,$D$18*10/14,IF(K48=1,$D$18*EXP(-$D$19*K49),$D$18)))) -> 12 | L50: =IF(L46<Исходные!$C$9,0,IF(L46=Исходные!$C$9,$D$18*5/14,IF(L46=Исходные!$C$9+1,$D$18*10/14,IF(L48=1,$D$18*EXP(-$D$19*L49),$D$18)))) -> 12 | ... AR50: =IF(AR46<Исходные!$C$9,0,IF(AR46=Исходные!$C$9,$D$18*5/14,IF(AR46=Исходные!$C$9+1,$D$18*10/14,IF(AR48=1,$D$18*EXP(-$D$19*AR49),$D$18)))) -> 2.3039168
B51: Накопленный профиль | C51: млрд м³ | E51: =E50 -> 0 | F51: =E51+F50 -> 0 | G51: =F51+G50 -> 0 | H51: =G51+H50 -> 0 | I51: =H51+I50 -> 4.2857143 | J51: =I51+J50 -> 12.857143 | K51: =J51+K50 -> 24.857143 | L51: =K51+L50 -> 36.857143 | M51: =L51+M50 -> 48.857143 | ... AR51: =AQ51+AR50 -> 275.20035
B52: Добыча сырого газа | C52: млрд м³ | D52: =SUM(E52:AR52) -> 275.20035 | E52: =E50*$D$29 -> 0 | F52: =F50*$D$29 -> 0 | G52: =G50*$D$29 -> 0 | H52: =H50*$D$29 -> 0 | I52: =I50*$D$29 -> 4.2857143 | J52: =J50*$D$29 -> 8.5714286 | K52: =K50*$D$29 -> 12 | L52: =L50*$D$29 -> 12 | ... AR52: =AR50*$D$29 -> 2.3039168
B53: Накопленная добыча | C53: млрд м³ | E53: =E52 -> 0 | F53: =E53+F52 -> 0 | G53: =F53+G52 -> 0 | H53: =G53+H52 -> 0 | I53: =H53+I52 -> 4.2857143 | J53: =I53+J52 -> 12.857143 | K53: =J53+K52 -> 24.857143 | L53: =K53+L52 -> 36.857143 | M53: =L53+M52 -> 48.857143 | ... AR53: =AQ53+AR52 -> 275.20035
B54: Выработанность > 1 % НГЗ (старт Кр) | C54: 0/1 | E54: =IF(E53/Исходные!$C$6>Исходные!$C$29,1,0) -> 0 | F54: =IF(OR(E54=1,F53/Исходные!$C$6>Исходные!$C$29),1,0) -> 0 | G54: =IF(OR(F54=1,G53/Исходные!$C$6>Исходные!$C$29),1,0) -> 0 | H54: =IF(OR(G54=1,H53/Исходные!$C$6>Исходные!$C$29),1,0) -> 0 | I54: =IF(OR(H54=1,I53/Исходные!$C$6>Исходные!$C$29),1,0) -> 1 | J54: =IF(OR(I54=1,J53/Исходные!$C$6>Исходные!$C$29),1,0) -> 1 | K54: =IF(OR(J54=1,K53/Исходные!$C$6>Исходные!$C$29),1,0) -> 1 | L54: =IF(OR(K54=1,L53/Исходные!$C$6>Исходные!$C$29),1,0) -> 1 | M54: =IF(OR(L54=1,M53/Исходные!$C$6>Исходные!$C$29),1,0) -> 1 | ... AR54: =IF(OR(AQ54=1,AR53/Исходные!$C$6>Исходные!$C$29),1,0) -> 1
B55: n для Кр (порядковый год) | E55: =1 -> 1 | F55: =IF(F54=1,IF(E54=1,E55+1,1),1) -> 1 | G55: =IF(G54=1,IF(F54=1,F55+1,1),1) -> 1 | H55: =IF(H54=1,IF(G54=1,G55+1,1),1) -> 1 | I55: =IF(I54=1,IF(H54=1,H55+1,1),1) -> 1 | J55: =IF(J54=1,IF(I54=1,I55+1,1),1) -> 2 | K55: =IF(K54=1,IF(J54=1,J55+1,1),1) -> 3 | L55: =IF(L54=1,IF(K54=1,K55+1,1),1) -> 4 | M55: =IF(M54=1,IF(L54=1,L55+1,1),1) -> 5 | ... AR55: =IF(AR54=1,IF(AQ54=1,AQ55+1,1),1) -> 36
B56: Коэффициент Кр | E56: =IF($D$22=0,1,IF(E55>Исходные!$C$28,1,MIN(1,Исходные!$C$26*E55+Исходные!$C$27))) -> 0.21 | F56: =IF($D$22=0,1,IF(F55>Исходные!$C$28,1,MIN(1,Исходные!$C$26*F55+Исходные!$C$27))) -> 0.21 | G56: =IF($D$22=0,1,IF(G55>Исходные!$C$28,1,MIN(1,Исходные!$C$26*G55+Исходные!$C$27))) -> 0.21 | H56: =IF($D$22=0,1,IF(H55>Исходные!$C$28,1,MIN(1,Исходные!$C$26*H55+Исходные!$C$27))) -> 0.21 | I56: =IF($D$22=0,1,IF(I55>Исходные!$C$28,1,MIN(1,Исходные!$C$26*I55+Исходные!$C$27))) -> 0.21 | J56: =IF($D$22=0,1,IF(J55>Исходные!$C$28,1,MIN(1,Исходные!$C$26*J55+Исходные!$C$27))) -> 0.276 | K56: =IF($D$22=0,1,IF(K55>Исходные!$C$28,1,MIN(1,Исходные!$C$26*K55+Исходные!$C$27))) -> 0.342 | L56: =IF($D$22=0,1,IF(L55>Исходные!$C$28,1,MIN(1,Исходные!$C$26*L55+Исходные!$C$27))) -> 0.408 | ... AR56: =IF($D$22=0,1,IF(AR55>Исходные!$C$28,1,MIN(1,Исходные!$C$26*AR55+Исходные!$C$27))) -> 1
B57: Собственные нужды | C57: доля | E57: =IF(E46>=2038,Исходные!$C$22,Исходные!$C$21) -> 0.02 | F57: =IF(F46>=2038,Исходные!$C$22,Исходные!$C$21) -> 0.02 | G57: =IF(G46>=2038,Исходные!$C$22,Исходные!$C$21) -> 0.02 | H57: =IF(H46>=2038,Исходные!$C$22,Исходные!$C$21) -> 0.02 | I57: =IF(I46>=2038,Исходные!$C$22,Исходные!$C$21) -> 0.02 | J57: =IF(J46>=2038,Исходные!$C$22,Исходные!$C$21) -> 0.02 | K57: =IF(K46>=2038,Исходные!$C$22,Исходные!$C$21) -> 0.02 | L57: =IF(L46>=2038,Исходные!$C$22,Исходные!$C$21) -> 0.02 | ... AR57: =IF(AR46>=2038,Исходные!$C$22,Исходные!$C$21) -> 0.035
B58: Газ на подготовку | C58: млрд м³ | D58: =SUM(E58:AR58) -> 266.6612 | E58: =E52*(1-E57) -> 0 | F58: =F52*(1-F57) -> 0 | G58: =G52*(1-G57) -> 0 | H58: =H52*(1-H57) -> 0 | I58: =I52*(1-I57) -> 4.2 | J58: =J52*(1-J57) -> 8.4 | K58: =K52*(1-K57) -> 11.76 | L58: =L52*(1-L57) -> 11.76 | ... AR58: =AR52*(1-AR57) -> 2.2232798
B59: Газ на GTL | C59: млрд м³ | D59: =SUM(E59:AR59) -> 0 | E59: =IF(AND($D$17=1,E46>=Исходные!$C$42,E52>0),$D$44,0) -> 0 | F59: =IF(AND($D$17=1,F46>=Исходные!$C$42,F52>0),$D$44,0) -> 0 | G59: =IF(AND($D$17=1,G46>=Исходные!$C$42,G52>0),$D$44,0) -> 0 | H59: =IF(AND($D$17=1,H46>=Исходные!$C$42,H52>0),$D$44,0) -> 0 | I59: =IF(AND($D$17=1,I46>=Исходные!$C$42,I52>0),$D$44,0) -> 0 | J59: =IF(AND($D$17=1,J46>=Исходные!$C$42,J52>0),$D$44,0) -> 0 | K59: =IF(AND($D$17=1,K46>=Исходные!$C$42,K52>0),$D$44,0) -> 0 | L59: =IF(AND($D$17=1,L46>=Исходные!$C$42,L52>0),$D$44,0) -> 0 | ... AR59: =IF(AND($D$17=1,AR46>=Исходные!$C$42,AR52>0),$D$44,0) -> 0
B60: Товарный газ в ЕСГ | C60: млрд м³ | D60: =SUM(E60:AR60) -> 254.75682 | E60: =E58*$D$37/1000-E59 -> 0 | F60: =F58*$D$37/1000-F59 -> 0 | G60: =G58*$D$37/1000-G59 -> 0 | H60: =H58*$D$37/1000-H59 -> 0 | I60: =I58*$D$37/1000-I59 -> 4.0125023 | J60: =J58*$D$37/1000-J59 -> 8.0250045 | K60: =K58*$D$37/1000-K59 -> 11.235006 | L60: =L58*$D$37/1000-L59 -> 11.235006 | ... AR60: =AR58*$D$37/1000-AR59 -> 2.1240274
B61: Стабильный конденсат | C61: млн т | D61: =SUM(E61:AR61) -> 8.7840914 | E61: =E58*$D$34/1000 -> 0 | F61: =F58*$D$34/1000 -> 0 | G61: =G58*$D$34/1000 -> 0 | H61: =H58*$D$34/1000 -> 0 | I61: =I58*$D$34/1000 -> 0.13835228 | J61: =J58*$D$34/1000 -> 0.27670455 | K61: =K58*$D$34/1000 -> 0.38738638 | L61: =L58*$D$34/1000 -> 0.38738638 | ... AR61: =AR58*$D$34/1000 -> 0.073237099
B62: СУГ | C62: млн т | D62: =SUM(E62:AR62) -> 19.457821 | E62: =E58*$D$35/1000 -> 0 | F62: =F58*$D$35/1000 -> 0 | G62: =G58*$D$35/1000 -> 0 | H62: =H58*$D$35/1000 -> 0 | I62: =I58*$D$35/1000 -> 0.30646696 | J62: =J58*$D$35/1000 -> 0.61293392 | K62: =K58*$D$35/1000 -> 0.85810749 | L62: =L58*$D$35/1000 -> 0.85810749 | ... AR62: =AR58*$D$35/1000 -> 0.162229
B63: Этан | C63: млн т | D63: =SUM(E63:AR63) -> 0 | E63: =E58*$D$36/1000 -> 0 | F63: =F58*$D$36/1000 -> 0 | G63: =G58*$D$36/1000 -> 0 | H63: =H58*$D$36/1000 -> 0 | I63: =I58*$D$36/1000 -> 0 | J63: =J58*$D$36/1000 -> 0 | K63: =K58*$D$36/1000 -> 0 | L63: =L58*$D$36/1000 -> 0 | ... AR63: =AR58*$D$36/1000 -> 0
B64: Синтетическое ДТ | C64: млн т | D64: =SUM(E64:AR64) -> 0 | E64: =IF(E59>0,Исходные!$C$39/1000,0) -> 0 | F64: =IF(F59>0,Исходные!$C$39/1000,0) -> 0 | G64: =IF(G59>0,Исходные!$C$39/1000,0) -> 0 | H64: =IF(H59>0,Исходные!$C$39/1000,0) -> 0 | I64: =IF(I59>0,Исходные!$C$39/1000,0) -> 0 | J64: =IF(J59>0,Исходные!$C$39/1000,0) -> 0 | K64: =IF(K59>0,Исходные!$C$39/1000,0) -> 0 | L64: =IF(L59>0,Исходные!$C$39/1000,0) -> 0 | ... AR64: =IF(AR59>0,Исходные!$C$39/1000,0) -> 0
B65: Синтетический авиакеросин | C65: млн т | D65: =SUM(E65:AR65) -> 0 | E65: =IF(E59>0,Исходные!$C$40/1000,0) -> 0 | F65: =IF(F59>0,Исходные!$C$40/1000,0) -> 0 | G65: =IF(G59>0,Исходные!$C$40/1000,0) -> 0 | H65: =IF(H59>0,Исходные!$C$40/1000,0) -> 0 | I65: =IF(I59>0,Исходные!$C$40/1000,0) -> 0 | J65: =IF(J59>0,Исходные!$C$40/1000,0) -> 0 | K65: =IF(K59>0,Исходные!$C$40/1000,0) -> 0 | L65: =IF(L59>0,Исходные!$C$40/1000,0) -> 0 | ... AR65: =IF(AR59>0,Исходные!$C$40/1000,0) -> 0
B66: Нафта GTL (сдаётся с конденсатом) | C66: млн т | D66: =SUM(E66:AR66) -> 0 | E66: =IF(E59>0,$D$43-E64-E65,0) -> 0 | F66: =IF(F59>0,$D$43-F64-F65,0) -> 0 | G66: =IF(G59>0,$D$43-G64-G65,0) -> 0 | H66: =IF(H59>0,$D$43-H64-H65,0) -> 0 | I66: =IF(I59>0,$D$43-I64-I65,0) -> 0 | J66: =IF(J59>0,$D$43-J64-J65,0) -> 0 | K66: =IF(K59>0,$D$43-K64-K65,0) -> 0 | L66: =IF(L59>0,$D$43-L64-L65,0) -> 0 | ... AR66: =IF(AR59>0,$D$43-AR64-AR65,0) -> 0
B67: Выручка, налоги, затраты, млрд руб
B68: Выручка: газ | C68: млрд руб | D68: =SUM(E68:AR68) -> 1257.7605 | E68: =E60*$D$39/1000 -> 0 | F68: =F60*$D$39/1000 -> 0 | G68: =G60*$D$39/1000 -> 0 | H68: =H60*$D$39/1000 -> 0 | I68: =I60*$D$39/1000 -> 19.810134 | J68: =J60*$D$39/1000 -> 39.620268 | K68: =K60*$D$39/1000 -> 55.468376 | L68: =L60*$D$39/1000 -> 55.468376 | ... AR68: =AR60*$D$39/1000 -> 10.486541
B69: Выручка: конденсат и нафта | C69: млрд руб | D69: =SUM(E69:AR69) -> 328.3142 | E69: =(E61+E66)*$D$40/1000 -> 0 | F69: =(F61+F66)*$D$40/1000 -> 0 | G69: =(G61+G66)*$D$40/1000 -> 0 | H69: =(H61+H66)*$D$40/1000 -> 0 | I69: =(I61+I66)*$D$40/1000 -> 5.1710547 | J69: =(J61+J66)*$D$40/1000 -> 10.342109 | K69: =(K61+K66)*$D$40/1000 -> 14.478953 | L69: =(L61+L66)*$D$40/1000 -> 14.478953 | ... AR69: =(AR61+AR66)*$D$40/1000 -> 2.7373098
B70: Выручка: СУГ и этан | C70: млрд руб | D70: =SUM(E70:AR70) -> 389.15641 | E70: =E62*Исходные!$C$19/1000+E63*Исходные!$C$20/1000 -> 0 | F70: =F62*Исходные!$C$19/1000+F63*Исходные!$C$20/1000 -> 0 | G70: =G62*Исходные!$C$19/1000+G63*Исходные!$C$20/1000 -> 0 | H70: =H62*Исходные!$C$19/1000+H63*Исходные!$C$20/1000 -> 0 | I70: =I62*Исходные!$C$19/1000+I63*Исходные!$C$20/1000 -> 6.1293392 | J70: =J62*Исходные!$C$19/1000+J63*Исходные!$C$20/1000 -> 12.258678 | K70: =K62*Исходные!$C$19/1000+K63*Исходные!$C$20/1000 -> 17.16215 | L70: =L62*Исходные!$C$19/1000+L63*Исходные!$C$20/1000 -> 17.16215 | ... AR70: =AR62*Исходные!$C$19/1000+AR63*Исходные!$C$20/1000 -> 3.2445799
B71: Выручка: ДТ GTL | C71: млрд руб | D71: =SUM(E71:AR71) -> 0 | E71: =E64*$D$23/1000 -> 0 | F71: =F64*$D$23/1000 -> 0 | G71: =G64*$D$23/1000 -> 0 | H71: =H64*$D$23/1000 -> 0 | I71: =I64*$D$23/1000 -> 0 | J71: =J64*$D$23/1000 -> 0 | K71: =K64*$D$23/1000 -> 0 | L71: =L64*$D$23/1000 -> 0 | ... AR71: =AR64*$D$23/1000 -> 0
B72: Выручка: керосин GTL | C72: млрд руб | D72: =SUM(E72:AR72) -> 0 | E72: =E65*$D$24/1000 -> 0 | F72: =F65*$D$24/1000 -> 0 | G72: =G65*$D$24/1000 -> 0 | H72: =H65*$D$24/1000 -> 0 | I72: =I65*$D$24/1000 -> 0 | J72: =J65*$D$24/1000 -> 0 | K72: =K65*$D$24/1000 -> 0 | L72: =L65*$D$24/1000 -> 0 | ... AR72: =AR65*$D$24/1000 -> 0
B73: Выручка всего | C73: млрд руб | D73: =SUM(E73:AR73) -> 1975.2311 | E73: =SUM(E68:E72) -> 0 | F73: =SUM(F68:F72) -> 0 | G73: =SUM(G68:G72) -> 0 | H73: =SUM(H68:H72) -> 0 | I73: =SUM(I68:I72) -> 31.110528 | J73: =SUM(J68:J72) -> 62.221056 | K73: =SUM(K68:K72) -> 87.109479 | L73: =SUM(L68:L72) -> 87.109479 | ... AR73: =SUM(AR68:AR72) -> 16.46843
B74: НДПИ (газ + жидкие УВ, с Кр) | C74: млрд руб | D74: =SUM(E74:AR74) -> 269.73584 | E74: =E52*$D$37/1000*(Исходные!$C$23+Исходные!$C$24*E56)/1000+Исходные!$C$25*E56*(E69+E70) -> 0 | F74: =F52*$D$37/1000*(Исходные!$C$23+Исходные!$C$24*F56)/1000+Исходные!$C$25*F56*(F69+F70) -> 0 | G74: =G52*$D$37/1000*(Исходные!$C$23+Исходные!$C$24*G56)/1000+Исходные!$C$25*G56*(G69+G70) -> 0 | H74: =H52*$D$37/1000*(Исходные!$C$23+Исходные!$C$24*H56)/1000+Исходные!$C$25*H56*(H69+H70) -> 0 | I74: =I52*$D$37/1000*(Исходные!$C$23+Исходные!$C$24*I56)/1000+Исходные!$C$25*I56*(I69+I70) -> 2.5935466 | J74: =J52*$D$37/1000*(Исходные!$C$23+Исходные!$C$24*J56)/1000+Исходные!$C$25*J56*(J69+J70) -> 5.5459558 | K74: =K52*$D$37/1000*(Исходные!$C$23+Исходные!$C$24*K56)/1000+Исходные!$C$25*K56*(K69+K70) -> 8.2667459 | L74: =L52*$D$37/1000*(Исходные!$C$23+Исходные!$C$24*L56)/1000+Исходные!$C$25*L56*(L69+L70) -> 8.7691536 | ... AR74: =AR52*$D$37/1000*(Исходные!$C$23+Исходные!$C$24*AR56)/1000+Исходные!$C$25*AR56*(AR69+AR70) -> 2.5348756
B75: Капитальные вложения, млрд руб
B76: Доразведка, 3D, ТЭО и проектная документация | C76: млрд руб | D76: =CAPEX_нормы!$C$6*INDEX(CAPEX_нормы!$E$6:$I$6,MATCH($D$16,CAPEX_нормы!$E$5:$I$5,0))*$D$28 -> 15 | E76: =$D76*CAPEX_нормы!J$6 -> 15 | F76: =$D76*CAPEX_нормы!K$6 -> 0 | G76: =$D76*CAPEX_нормы!L$6 -> 0 | H76: =$D76*CAPEX_нормы!M$6 -> 0 | I76: =$D76*CAPEX_нормы!N$6 -> 0 | J76: =$D76*CAPEX_нормы!O$6 -> 0 | K76: =$D76*CAPEX_нормы!P$6 -> 0 | L76: =$D76*CAPEX_нормы!Q$6 -> 0 | ... W76: =$D76*CAPEX_нормы!AB$6 -> 0 | X76: 0 | Y76: 0 | Z76: 0 | AA76: 0 | AB76: 0 | AC76: 0 | AD76: 0 | AE76: 0 | AF76: 0 | AG76: 0 | AH76: 0 | AI76: 0 | AJ76: 0 | AK76: 0 | AL76: 0 | AM76: 0 | AN76: 0 | AO76: 0 | AP76: 0 | AQ76: 0 | AR76: 0
B77: Эксплуатационные скважины | C77: млрд руб | D77: =$D$42*$D$20*INDEX(CAPEX_нормы!$E$7:$I$7,MATCH($D$16,CAPEX_нормы!$E$5:$I$5,0))*$D$28 -> 85.714286 | E77: =$D77*CAPEX_нормы!J$7 -> 0 | F77: =$D77*CAPEX_нормы!K$7 -> 17.142857 | G77: =$D77*CAPEX_нормы!L$7 -> 25.714286 | H77: =$D77*CAPEX_нормы!M$7 -> 25.714286 | I77: =$D77*CAPEX_нормы!N$7 -> 6.8571429 | J77: =$D77*CAPEX_нормы!O$7 -> 0 | K77: =$D77*CAPEX_нормы!P$7 -> 0 | L77: =$D77*CAPEX_нормы!Q$7 -> 0 | ... W77: =$D77*CAPEX_нормы!AB$7 -> 0 | X77: 0 | Y77: 0 | Z77: 0 | AA77: 0 | AB77: 0 | AC77: 0 | AD77: 0 | AE77: 0 | AF77: 0 | AG77: 0 | AH77: 0 | AI77: 0 | AJ77: 0 | AK77: 0 | AL77: 0 | AM77: 0 | AN77: 0 | AO77: 0 | AP77: 0 | AQ77: 0 | AR77: 0
B78: Кусты скважин и газосборная сеть | C78: млрд руб | D78: =CAPEX_нормы!$C$8*$D$41*INDEX(CAPEX_нормы!$E$8:$I$8,MATCH($D$16,CAPEX_нормы!$E$5:$I$5,0))*$D$28 -> 41.743629 | E78: =$D78*CAPEX_нормы!J$8 -> 0 | F78: =$D78*CAPEX_нормы!K$8 -> 12.523089 | G78: =$D78*CAPEX_нормы!L$8 -> 16.697452 | H78: =$D78*CAPEX_нормы!M$8 -> 12.523089 | I78: =$D78*CAPEX_нормы!N$8 -> 0 | J78: =$D78*CAPEX_нормы!O$8 -> 0 | K78: =$D78*CAPEX_нормы!P$8 -> 0 | L78: =$D78*CAPEX_нормы!Q$8 -> 0 | ... W78: =$D78*CAPEX_нормы!AB$8 -> 0 | X78: 0 | Y78: 0 | Z78: 0 | AA78: 0 | AB78: 0 | AC78: 0 | AD78: 0 | AE78: 0 | AF78: 0 | AG78: 0 | AH78: 0 | AI78: 0 | AJ78: 0 | AK78: 0 | AL78: 0 | AM78: 0 | AN78: 0 | AO78: 0 | AP78: 0 | AQ78: 0 | AR78: 0
B79: УКПГ: НТС, регенерация метанола, стабилизация | C79: млрд руб | D79: =CAPEX_нормы!$C$9*$D$41*INDEX(CAPEX_нормы!$E$9:$I$9,MATCH($D$16,CAPEX_нормы!$E$5:$I$5,0))*$D$28 -> 70.129296 | E79: =$D79*CAPEX_нормы!J$9 -> 0 | F79: =$D79*CAPEX_нормы!K$9 -> 20.871811 | G79: =$D79*CAPEX_нормы!L$9 -> 29.220564 | H79: =$D79*CAPEX_нормы!M$9 -> 20.036922 | I79: =$D79*CAPEX_нормы!N$9 -> 0 | J79: =$D79*CAPEX_нормы!O$9 -> 0 | K79: =$D79*CAPEX_нормы!P$9 -> 0 | L79: =$D79*CAPEX_нормы!Q$9 -> 0 | ... W79: =$D79*CAPEX_нормы!AB$9 -> 0 | X79: 0 | Y79: 0 | Z79: 0 | AA79: 0 | AB79: 0 | AC79: 0 | AD79: 0 | AE79: 0 | AF79: 0 | AG79: 0 | AH79: 0 | AI79: 0 | AJ79: 0 | AK79: 0 | AL79: 0 | AM79: 0 | AN79: 0 | AO79: 0 | AP79: 0 | AQ79: 0 | AR79: 0
B80: Турбодетандерные агрегаты (5 шт.) | C80: млрд руб | D80: =CAPEX_нормы!$C$10*$D$41*INDEX(CAPEX_нормы!$E$10:$I$10,MATCH($D$16,CAPEX_нормы!$E$5:$I$5,0))*$D$28 -> 0 | E80: =$D80*CAPEX_нормы!J$10 -> 0 | F80: =$D80*CAPEX_нормы!K$10 -> 0 | G80: =$D80*CAPEX_нормы!L$10 -> 0 | H80: =$D80*CAPEX_нормы!M$10 -> 0 | I80: =$D80*CAPEX_нормы!N$10 -> 0 | J80: =$D80*CAPEX_нормы!O$10 -> 0 | K80: =$D80*CAPEX_нормы!P$10 -> 0 | L80: =$D80*CAPEX_нормы!Q$10 -> 0 | ... W80: =$D80*CAPEX_нормы!AB$10 -> 0 | X80: 0 | Y80: 0 | Z80: 0 | AA80: 0 | AB80: 0 | AC80: 0 | AD80: 0 | AE80: 0 | AF80: 0 | AG80: 0 | AH80: 0 | AI80: 0 | AJ80: 0 | AK80: 0 | AL80: 0 | AM80: 0 | AN80: 0 | AO80: 0 | AP80: 0 | AQ80: 0 | AR80: 0
B81: ТДА + деэтанизация + ГФУ + парк СУГ | C81: млрд руб | D81: =CAPEX_нормы!$C$11*$D$41*INDEX(CAPEX_нормы!$E$11:$I$11,MATCH($D$16,CAPEX_нормы!$E$5:$I$5,0))*$D$28 -> 53.862747 | E81: =$D81*CAPEX_нормы!J$11 -> 0 | F81: =$D81*CAPEX_нормы!K$11 -> 0 | G81: =$D81*CAPEX_нормы!L$11 -> 22.442829 | H81: =$D81*CAPEX_нормы!M$11 -> 31.419918 | I81: =$D81*CAPEX_нормы!N$11 -> 0 | J81: =$D81*CAPEX_нормы!O$11 -> 0 | K81: =$D81*CAPEX_нормы!P$11 -> 0 | L81: =$D81*CAPEX_нормы!Q$11 -> 0 | ... W81: =$D81*CAPEX_нормы!AB$11 -> 0 | X81: 0 | Y81: 0 | Z81: 0 | AA81: 0 | AB81: 0 | AC81: 0 | AD81: 0 | AE81: 0 | AF81: 0 | AG81: 0 | AH81: 0 | AI81: 0 | AJ81: 0 | AK81: 0 | AL81: 0 | AM81: 0 | AN81: 0 | AO81: 0 | AP81: 0 | AQ81: 0 | AR81: 0
B82: Продуктопровод СУГ 120 км | C82: млрд руб | D82: =CAPEX_нормы!$C$12*$D$41*INDEX(CAPEX_нормы!$E$12:$I$12,MATCH($D$16,CAPEX_нормы!$E$5:$I$5,0))*$D$28 -> 8.6180395 | E82: =$D82*CAPEX_нормы!J$12 -> 0 | F82: =$D82*CAPEX_нормы!K$12 -> 0 | G82: =$D82*CAPEX_нормы!L$12 -> 4.4885594 | H82: =$D82*CAPEX_нормы!M$12 -> 4.1294801 | I82: =$D82*CAPEX_нормы!N$12 -> 0 | J82: =$D82*CAPEX_нормы!O$12 -> 0 | K82: =$D82*CAPEX_нормы!P$12 -> 0 | L82: =$D82*CAPEX_нормы!Q$12 -> 0 | ... W82: =$D82*CAPEX_нормы!AB$12 -> 0 | X82: 0 | Y82: 0 | Z82: 0 | AA82: 0 | AB82: 0 | AC82: 0 | AD82: 0 | AE82: 0 | AF82: 0 | AG82: 0 | AH82: 0 | AI82: 0 | AJ82: 0 | AK82: 0 | AL82: 0 | AM82: 0 | AN82: 0 | AO82: 0 | AP82: 0 | AQ82: 0 | AR82: 0
B83: Налив СУГ на ж/д | C83: млрд руб | D83: =CAPEX_нормы!$C$13*$D$41*INDEX(CAPEX_нормы!$E$13:$I$13,MATCH($D$16,CAPEX_нормы!$E$5:$I$5,0))*$D$28 -> 2.6931373 | E83: =$D83*CAPEX_нормы!J$13 -> 0 | F83: =$D83*CAPEX_нормы!K$13 -> 0 | G83: =$D83*CAPEX_нормы!L$13 -> 1.3465687 | H83: =$D83*CAPEX_нормы!M$13 -> 1.3465687 | I83: =$D83*CAPEX_нормы!N$13 -> 0 | J83: =$D83*CAPEX_нормы!O$13 -> 0 | K83: =$D83*CAPEX_нормы!P$13 -> 0 | L83: =$D83*CAPEX_нормы!Q$13 -> 0 | ... W83: =$D83*CAPEX_нормы!AB$13 -> 0 | X83: 0 | Y83: 0 | Z83: 0 | AA83: 0 | AB83: 0 | AC83: 0 | AD83: 0 | AE83: 0 | AF83: 0 | AG83: 0 | AH83: 0 | AI83: 0 | AJ83: 0 | AK83: 0 | AL83: 0 | AM83: 0 | AN83: 0 | AO83: 0 | AP83: 0 | AQ83: 0 | AR83: 0
B84: Пропановая холодильная установка | C84: млрд руб | D84: =CAPEX_нормы!$C$14*$D$41*INDEX(CAPEX_нормы!$E$14:$I$14,MATCH($D$16,CAPEX_нормы!$E$5:$I$5,0))*$D$28 -> 10.772549 | E84: =$D84*CAPEX_нормы!J$14 -> 0 | F84: =$D84*CAPEX_нормы!K$14 -> 0 | G84: =$D84*CAPEX_нормы!L$14 -> 0 | H84: =$D84*CAPEX_нормы!M$14 -> 0 | I84: =$D84*CAPEX_нормы!N$14 -> 0 | J84: =$D84*CAPEX_нормы!O$14 -> 0 | K84: =$D84*CAPEX_нормы!P$14 -> 0 | L84: =$D84*CAPEX_нормы!Q$14 -> 0 | ... W84: =$D84*CAPEX_нормы!AB$14 -> 0 | X84: 0 | Y84: 0 | Z84: 0 | AA84: 0 | AB84: 0 | AC84: 0 | AD84: 0 | AE84: 0 | AF84: 0 | AG84: 0 | AH84: 0 | AI84: 0 | AJ84: 0 | AK84: 0 | AL84: 0 | AM84: 0 | AN84: 0 | AO84: 0 | AP84: 0 | AQ84: 0 | AR84: 0
B85: Криогенный блок извлечения этана | C85: млрд руб | D85: =CAPEX_нормы!$C$15*$D$41*INDEX(CAPEX_нормы!$E$15:$I$15,MATCH($D$16,CAPEX_нормы!$E$5:$I$5,0))*$D$28 -> 0 | E85: =$D85*CAPEX_нормы!J$15 -> 0 | F85: =$D85*CAPEX_нормы!K$15 -> 0 | G85: =$D85*CAPEX_нормы!L$15 -> 0 | H85: =$D85*CAPEX_нормы!M$15 -> 0 | I85: =$D85*CAPEX_нормы!N$15 -> 0 | J85: =$D85*CAPEX_нормы!O$15 -> 0 | K85: =$D85*CAPEX_нормы!P$15 -> 0 | L85: =$D85*CAPEX_нормы!Q$15 -> 0 | ... W85: =$D85*CAPEX_нормы!AB$15 -> 0 | X85: 0 | Y85: 0 | Z85: 0 | AA85: 0 | AB85: 0 | AC85: 0 | AD85: 0 | AE85: 0 | AF85: 0 | AG85: 0 | AH85: 0 | AI85: 0 | AJ85: 0 | AK85: 0 | AL85: 0 | AM85: 0 | AN85: 0 | AO85: 0 | AP85: 0 | AQ85: 0 | AR85: 0
B86: Энергоцентр (ЭСН), промбаза | C86: млрд руб | D86: =CAPEX_нормы!$C$16*$D$41*INDEX(CAPEX_нормы!$E$16:$I$16,MATCH($D$16,CAPEX_нормы!$E$5:$I$5,0))*$D$28 -> 10.772549 | E86: =$D86*CAPEX_нормы!J$16 -> 0 | F86: =$D86*CAPEX_нормы!K$16 -> 4.4885658 | G86: =$D86*CAPEX_нормы!L$16 -> 4.4885658 | H86: =$D86*CAPEX_нормы!M$16 -> 1.7954285 | I86: =$D86*CAPEX_нормы!N$16 -> 0 | J86: =$D86*CAPEX_нормы!O$16 -> 0 | K86: =$D86*CAPEX_нормы!P$16 -> 0 | L86: =$D86*CAPEX_нормы!Q$16 -> 0 | ... W86: =$D86*CAPEX_нормы!AB$16 -> 0 | X86: 0 | Y86: 0 | Z86: 0 | AA86: 0 | AB86: 0 | AC86: 0 | AD86: 0 | AE86: 0 | AF86: 0 | AG86: 0 | AH86: 0 | AI86: 0 | AJ86: 0 | AK86: 0 | AL86: 0 | AM86: 0 | AN86: 0 | AO86: 0 | AP86: 0 | AQ86: 0 | AR86: 0
B87: Вахтовый жилой комплекс у УКПГ | C87: млрд руб | D87: =$D$30*INDEX(CAPEX_нормы!$E$17:$I$17,MATCH($D$16,CAPEX_нормы!$E$5:$I$5,0))*$D$28 -> 4 | E87: =$D87*CAPEX_нормы!J$17 -> 0 | F87: =$D87*CAPEX_нормы!K$17 -> 1.5 | G87: =$D87*CAPEX_нормы!L$17 -> 1.5 | H87: =$D87*CAPEX_нормы!M$17 -> 1 | I87: =$D87*CAPEX_нормы!N$17 -> 0 | J87: =$D87*CAPEX_нормы!O$17 -> 0 | K87: =$D87*CAPEX_нормы!P$17 -> 0 | L87: =$D87*CAPEX_нормы!Q$17 -> 0 | ... W87: =$D87*CAPEX_нормы!AB$17 -> 0 | X87: 0 | Y87: 0 | Z87: 0 | AA87: 0 | AB87: 0 | AC87: 0 | AD87: 0 | AE87: 0 | AF87: 0 | AG87: 0 | AH87: 0 | AI87: 0 | AJ87: 0 | AK87: 0 | AL87: 0 | AM87: 0 | AN87: 0 | AO87: 0 | AP87: 0 | AQ87: 0 | AR87: 0
B88: Автодорога до Бованенково 120 км | C88: млрд руб | D88: =$D$31*INDEX(CAPEX_нормы!$E$18:$I$18,MATCH($D$16,CAPEX_нормы!$E$5:$I$5,0))*$D$28 -> 24 | E88: =$D88*CAPEX_нормы!J$18 -> 0 | F88: =$D88*CAPEX_нормы!K$18 -> 9.6 | G88: =$D88*CAPEX_нормы!L$18 -> 9.6 | H88: =$D88*CAPEX_нормы!M$18 -> 4.8 | I88: =$D88*CAPEX_нормы!N$18 -> 0 | J88: =$D88*CAPEX_нормы!O$18 -> 0 | K88: =$D88*CAPEX_нормы!P$18 -> 0 | L88: =$D88*CAPEX_нормы!Q$18 -> 0 | ... W88: =$D88*CAPEX_нормы!AB$18 -> 0 | X88: 0 | Y88: 0 | Z88: 0 | AA88: 0 | AB88: 0 | AC88: 0 | AD88: 0 | AE88: 0 | AF88: 0 | AG88: 0 | AH88: 0 | AI88: 0 | AJ88: 0 | AK88: 0 | AL88: 0 | AM88: 0 | AN88: 0 | AO88: 0 | AP88: 0 | AQ88: 0 | AR88: 0
B89: Газопровод 120 км до Бованенково | C89: млрд руб | D89: =CAPEX_нормы!$C$19*$D$41*INDEX(CAPEX_нормы!$E$19:$I$19,MATCH($D$16,CAPEX_нормы!$E$5:$I$5,0))*$D$28 -> 37.703923 | E89: =$D89*CAPEX_нормы!J$19 -> 0 | F89: =$D89*CAPEX_нормы!K$19 -> 10.772539 | G89: =$D89*CAPEX_нормы!L$19 -> 17.954231 | H89: =$D89*CAPEX_нормы!M$19 -> 8.9771155 | I89: =$D89*CAPEX_нормы!N$19 -> 0 | J89: =$D89*CAPEX_нормы!O$19 -> 0 | K89: =$D89*CAPEX_нормы!P$19 -> 0 | L89: =$D89*CAPEX_нормы!Q$19 -> 0 | ... W89: =$D89*CAPEX_нормы!AB$19 -> 0 | X89: 0 | Y89: 0 | Z89: 0 | AA89: 0 | AB89: 0 | AC89: 0 | AD89: 0 | AE89: 0 | AF89: 0 | AG89: 0 | AH89: 0 | AI89: 0 | AJ89: 0 | AK89: 0 | AL89: 0 | AM89: 0 | AN89: 0 | AO89: 0 | AP89: 0 | AQ89: 0 | AR89: 0
B90: Конденсатопровод 120 км | C90: млрд руб | D90: =CAPEX_нормы!$C$20*$D$41*INDEX(CAPEX_нормы!$E$20:$I$20,MATCH($D$16,CAPEX_нормы!$E$5:$I$5,0))*$D$28 -> 8.6180395 | E90: =$D90*CAPEX_нормы!J$20 -> 0 | F90: =$D90*CAPEX_нормы!K$20 -> 0 | G90: =$D90*CAPEX_нормы!L$20 -> 5.3862747 | H90: =$D90*CAPEX_нормы!M$20 -> 3.2317648 | I90: =$D90*CAPEX_нормы!N$20 -> 0 | J90: =$D90*CAPEX_нормы!O$20 -> 0 | K90: =$D90*CAPEX_нормы!P$20 -> 0 | L90: =$D90*CAPEX_нормы!Q$20 -> 0 | ... W90: =$D90*CAPEX_нормы!AB$20 -> 0 | X90: 0 | Y90: 0 | Z90: 0 | AA90: 0 | AB90: 0 | AC90: 0 | AD90: 0 | AE90: 0 | AF90: 0 | AG90: 0 | AH90: 0 | AI90: 0 | AJ90: 0 | AK90: 0 | AL90: 0 | AM90: 0 | AN90: 0 | AO90: 0 | AP90: 0 | AQ90: 0 | AR90: 0
B91: ДКС (2 очереди) | C91: млрд руб | D91: =CAPEX_нормы!$C$21*$D$41*INDEX(CAPEX_нормы!$E$21:$I$21,MATCH($D$16,CAPEX_нормы!$E$5:$I$5,0))*$D$28 -> 49.374185 | E91: =$D91*CAPEX_нормы!J$21 -> 0 | F91: =$D91*CAPEX_нормы!K$21 -> 0 | G91: =$D91*CAPEX_нормы!L$21 -> 0 | H91: =$D91*CAPEX_нормы!M$21 -> 0 | I91: =$D91*CAPEX_нормы!N$21 -> 0 | J91: =$D91*CAPEX_нормы!O$21 -> 0 | K91: =$D91*CAPEX_нормы!P$21 -> 0 | L91: =$D91*CAPEX_нормы!Q$21 -> 0 | ... W91: =$D91*CAPEX_нормы!AB$21 -> 17.954231 | X91: 0 | Y91: 0 | Z91: 0 | AA91: 0 | AB91: 0 | AC91: 0 | AD91: 0 | AE91: 0 | AF91: 0 | AG91: 0 | AH91: 0 | AI91: 0 | AJ91: 0 | AK91: 0 | AL91: 0 | AM91: 0 | AN91: 0 | AO91: 0 | AP91: 0 | AQ91: 0 | AR91: 0
B92: GTL-установка у ст. Бованенково + налив | C92: млрд руб | D92: =$D$32*$D$17*INDEX(CAPEX_нормы!$E$22:$I$22,MATCH($D$16,CAPEX_нормы!$E$5:$I$5,0))*$D$28 -> 0 | E92: =$D92*CAPEX_нормы!J$22 -> 0 | F92: =$D92*CAPEX_нормы!K$22 -> 0 | G92: =$D92*CAPEX_нормы!L$22 -> 0 | H92: =$D92*CAPEX_нормы!M$22 -> 0 | I92: =$D92*CAPEX_нормы!N$22 -> 0 | J92: =$D92*CAPEX_нормы!O$22 -> 0 | K92: =$D92*CAPEX_нормы!P$22 -> 0 | L92: =$D92*CAPEX_нормы!Q$22 -> 0 | ... W92: =$D92*CAPEX_нормы!AB$22 -> 0 | X92: 0 | Y92: 0 | Z92: 0 | AA92: 0 | AB92: 0 | AC92: 0 | AD92: 0 | AE92: 0 | AF92: 0 | AG92: 0 | AH92: 0 | AI92: 0 | AJ92: 0 | AK92: 0 | AL92: 0 | AM92: 0 | AN92: 0 | AO92: 0 | AP92: 0 | AQ92: 0 | AR92: 0
B93: CAPEX всего | C93: млрд руб | D93: =SUM(E93:AR93) -> 423.0023 | E93: =SUM(E76:E92) -> 15 | F93: =SUM(F76:F92) -> 76.898861 | G93: =SUM(G76:G92) -> 138.83933 | H93: =SUM(H76:H92) -> 114.97457 | I93: =SUM(I76:I92) -> 6.8571429 | J93: =SUM(J76:J92) -> 0 | K93: =SUM(K76:K92) -> 0 | L93: =SUM(L76:L92) -> 0 | ... AR93: =SUM(AR76:AR92) -> 0
B94: Накопленный CAPEX | C94: млрд руб | E94: =E93 -> 15 | F94: =E94+F93 -> 91.898861 | G94: =F94+G93 -> 230.73819 | H94: =G94+H93 -> 345.71276 | I94: =H94+I93 -> 352.56991 | J94: =I94+J93 -> 352.56991 | K94: =J94+K93 -> 352.56991 | L94: =K94+L93 -> 352.56991 | M94: =L94+M93 -> 352.56991 | ... AR94: =AQ94+AR93 -> 423.0023
B95: Операционные затраты, амортизация, налоги, млрд руб
B96: Признак добычи | C96: 0/1 | E96: =IF(E52>0,1,0) -> 0 | F96: =IF(F52>0,1,0) -> 0 | G96: =IF(G52>0,1,0) -> 0 | H96: =IF(H52>0,1,0) -> 0 | I96: =IF(I52>0,1,0) -> 1 | J96: =IF(J52>0,1,0) -> 1 | K96: =IF(K52>0,1,0) -> 1 | L96: =IF(L52>0,1,0) -> 1 | ... AR96: =IF(AR52>0,1,0) -> 1
B97: OPEX (пост. + перем. + СУГ + терминал + GTL + чужой ВЖК) | C97: млрд руб | D97: =SUM(E97:AR97) -> 294.27861 | E97: =E96*Исходные!$C$33*E94+E52*Исходные!$C$34/1000+E62*Исходные!$C$35/1000+(E61+E62)*Исходные!$C$36/1000+IF(E59>0,$D$43*Исходные!$C$41/1000,0)+E96*$D$33 -> 0 | F97: =F96*Исходные!$C$33*F94+F52*Исходные!$C$34/1000+F62*Исходные!$C$35/1000+(F61+F62)*Исходные!$C$36/1000+IF(F59>0,$D$43*Исходные!$C$41/1000,0)+F96*$D$33 -> 0 | G97: =G96*Исходные!$C$33*G94+G52*Исходные!$C$34/1000+G62*Исходные!$C$35/1000+(G61+G62)*Исходные!$C$36/1000+IF(G59>0,$D$43*Исходные!$C$41/1000,0)+G96*$D$33 -> 0 | H97: =H96*Исходные!$C$33*H94+H52*Исходные!$C$34/1000+H62*Исходные!$C$35/1000+(H61+H62)*Исходные!$C$36/1000+IF(H59>0,$D$43*Исходные!$C$41/1000,0)+H96*$D$33 -> 0 | I97: =I96*Исходные!$C$33*I94+I52*Исходные!$C$34/1000+I62*Исходные!$C$35/1000+(I61+I62)*Исходные!$C$36/1000+IF(I59>0,$D$43*Исходные!$C$41/1000,0)+I96*$D$33 -> 6.4602823 | J97: =J96*Исходные!$C$33*J94+J52*Исходные!$C$34/1000+J62*Исходные!$C$35/1000+(J61+J62)*Исходные!$C$36/1000+IF(J59>0,$D$43*Исходные!$C$41/1000,0)+J96*$D$33 -> 7.632016 | K97: =K96*Исходные!$C$33*K94+K52*Исходные!$C$34/1000+K62*Исходные!$C$35/1000+(K61+K62)*Исходные!$C$36/1000+IF(K59>0,$D$43*Исходные!$C$41/1000,0)+K96*$D$33 -> 8.569403 | L97: =L96*Исходные!$C$33*L94+L52*Исходные!$C$34/1000+L62*Исходные!$C$35/1000+(L61+L62)*Исходные!$C$36/1000+IF(L59>0,$D$43*Исходные!$C$41/1000,0)+L96*$D$33 -> 8.569403 | ... AR97: =AR96*Исходные!$C$33*AR94+AR52*Исходные!$C$34/1000+AR62*Исходные!$C$35/1000+(AR61+AR62)*Исходные!$C$36/1000+IF(AR59>0,$D$43*Исходные!$C$41/1000,0)+AR96*$D$33 -> 6.9705841
B98: Ввод основных средств | C98: млрд руб | D98: =SUM(E98:AR98) -> 423.0023 | E98: 0 | F98: 0 | G98: 0 | H98: 0 | I98: =SUM(E93:H93) -> 345.71276 | J98: =I93 -> 6.8571429 | K98: =J93 -> 0 | L98: =K93 -> 0 | M98: =L93 -> 0 | N98: =M93 -> 0 | O98: =N93 -> 2.5714286 | P98: =O93 -> 16.037102 | Q98: =P93 -> 31.298209 | ... AR98: =AQ93 -> 0
B99: Амортизация | C99: млрд руб | D99: =SUM(E99:AR99) -> 423.0023 | E99: =SUM(OFFSET(E98,0,-MIN(Исходные!$C$32-1,E47),1,MIN(Исходные!$C$32,E47+1)))/Исходные!$C$32 -> 0 | F99: =SUM(OFFSET(F98,0,-MIN(Исходные!$C$32-1,F47),1,MIN(Исходные!$C$32,F47+1)))/Исходные!$C$32 -> 0 | G99: =SUM(OFFSET(G98,0,-MIN(Исходные!$C$32-1,G47),1,MIN(Исходные!$C$32,G47+1)))/Исходные!$C$32 -> 0 | H99: =SUM(OFFSET(H98,0,-MIN(Исходные!$C$32-1,H47),1,MIN(Исходные!$C$32,H47+1)))/Исходные!$C$32 -> 0 | I99: =SUM(OFFSET(I98,0,-MIN(Исходные!$C$32-1,I47),1,MIN(Исходные!$C$32,I47+1)))/Исходные!$C$32 -> 23.047517 | J99: =SUM(OFFSET(J98,0,-MIN(Исходные!$C$32-1,J47),1,MIN(Исходные!$C$32,J47+1)))/Исходные!$C$32 -> 23.50466 | K99: =SUM(OFFSET(K98,0,-MIN(Исходные!$C$32-1,K47),1,MIN(Исходные!$C$32,K47+1)))/Исходные!$C$32 -> 23.50466 | L99: =SUM(OFFSET(L98,0,-MIN(Исходные!$C$32-1,L47),1,MIN(Исходные!$C$32,L47+1)))/Исходные!$C$32 -> 23.50466 | ... AR99: =SUM(OFFSET(AR98,0,-MIN(Исходные!$C$32-1,AR47),1,MIN(Исходные!$C$32,AR47+1)))/Исходные!$C$32 -> 0
B100: Накопленная амортизация | C100: млрд руб | E100: =E99 -> 0 | F100: =E100+F99 -> 0 | G100: =F100+G99 -> 0 | H100: =G100+H99 -> 0 | I100: =H100+I99 -> 23.047517 | J100: =I100+J99 -> 46.552178 | K100: =J100+K99 -> 70.056838 | L100: =K100+L99 -> 93.561499 | M100: =L100+M99 -> 117.06616 | ... AR100: =AQ100+AR99 -> 423.0023
B101: Налог на имущество | C101: млрд руб | D101: =SUM(E101:AR101) -> 66.842725 | E101: =E96*Исходные!$C$31*(E94-E100) -> 0 | F101: =F96*Исходные!$C$31*(F94-F100) -> 0 | G101: =G96*Исходные!$C$31*(G94-G100) -> 0 | H101: =H96*Исходные!$C$31*(H94-H100) -> 0 | I101: =I96*Исходные!$C$31*(I94-I100) -> 7.2494925 | J101: =J96*Исходные!$C$31*(J94-J100) -> 6.73239 | K101: =K96*Исходные!$C$31*(K94-K100) -> 6.2152875 | L101: =L96*Исходные!$C$31*(L94-L100) -> 5.6981849 | ... AR101: =AR96*Исходные!$C$31*(AR94-AR100) -> 0
B102: EBITDA | C102: млрд руб | D102: =SUM(E102:AR102) -> 1344.3739 | E102: =E73-E74-E97-E101 -> 0 | F102: =F73-F74-F97-F101 -> 0 | G102: =G73-G74-G97-G101 -> 0 | H102: =H73-H74-H97-H101 -> 0 | I102: =I73-I74-I97-I101 -> 14.807207 | J102: =J73-J74-J97-J101 -> 42.310694 | K102: =K73-K74-K97-K101 -> 64.058042 | L102: =L73-L74-L97-L101 -> 64.072737 | ... AR102: =AR73-AR74-AR97-AR101 -> 6.9629706
B103: Налог на прибыль | C103: млрд руб | D103: =SUM(E103:AR103) -> 232.40299 | E103: =MAX(0,E102-E99)*Исходные!$C$30 -> 0 | F103: =MAX(0,F102-F99)*Исходные!$C$30 -> 0 | G103: =MAX(0,G102-G99)*Исходные!$C$30 -> 0 | H103: =MAX(0,H102-H99)*Исходные!$C$30 -> 0 | I103: =MAX(0,I102-I99)*Исходные!$C$30 -> 0 | J103: =MAX(0,J102-J99)*Исходные!$C$30 -> 4.7015085 | K103: =MAX(0,K102-K99)*Исходные!$C$30 -> 10.138345 | L103: =MAX(0,L102-L99)*Исходные!$C$30 -> 10.142019 | ... AR103: =MAX(0,AR102-AR99)*Исходные!$C$30 -> 1.7407426
...

Sheet Расчёт_В
B2: Расчёт: В. Б + этан
B3: Криогенное извлечение этана, потребителя нет. Денежный поток по годам, млрд руб. (реальные цены 2026 г.)
B5: ЧДД (NPV) при ставке варианта, млрд руб | C5: =SUM(E107:AR107) -> -75.259733
B6: ВНД (IRR), реальная | C6: =IRR(E105:AR105,0.1) -> 0.071124893
B7: Дисконтированная окупаемость, год | C7: =IF(SUM(E109:AR109)=0,"нет",2067-SUM(E109:AR109)) -> нет
B8: Индекс доходности (PI) | C8: =1+C5/SUMPRODUCT(E93:AR93,E106:AR106) -> 0.78210017
B9: CAPEX всего, млрд руб | C9: =D93 -> 485.84218
B10: Фонд скважин, шт. | C10: =$D$42 -> 57.142857
B11: Проверка: Σ профиля − извлекаемые (должно быть ≈ 0), млрд м³ | C11: =D50-Исходные!$C$8 -> 0.0003531191
B13: Показатель | C13: Ед. | D13: Итого / знач. | E13: 2027 | F13: 2028 | G13: 2029 | H13: 2030 | I13: 2031 | J13: 2032 | K13: 2033 | L13: 2034 | M13: 2035 | N13: 2036 | O13: 2037 | P13: 2038 | Q13: 2039 | R13: 2040 | S13: 2041 | T13: 2042 | U13: 2043 | V13: 2044 | W13: 2045 | X13: 2046 | Y13: 2047 | Z13: 2048 | AA13: 2049 | AB13: 2050 | AC13: 2051 | AD13: 2052 | AE13: 2053 | AF13: 2054 | AG13: 2055 | AH13: 2056 | AI13: 2057 | AJ13: 2058 | AK13: 2059 | AL13: 2060 | AM13: 2061 | AN13: 2062 | AO13: 2063 | AP13: 2064 | AQ13: 2065 | AR13: 2066
B14: Параметры варианта (ссылки на «Сценарии» и «Исходные»)
B15: Технология (столбец баланса) | C15: код | D15: =Сценарии!$F$6 -> C
B16: Состав CAPEX | C16: код | D16: =Сценарии!$F$7 -> C
B17: GTL (1 — есть) | C17: 0/1 | D17: =Сценарии!$F$8 -> 0
B18: Полка добычи | C18: млрд м³/год | D18: =Сценарии!$F$9 -> 12
B19: Темп падения | C19: 1/год | D19: =Сценарии!$F$10 -> 0.071752
B20: Стоимость скважины | C20: млрд руб | D20: =Сценарии!$F$11 -> 1.5
B21: Дебит скважины | C21: млн м³/сут | D21: =Сценарии!$F$12 -> 0.75
B22: Кр (п-ов Ямал) в НДПИ | C22: 0/1 | D22: =Сценарии!$F$13 -> 1
B23: Цена ДТ GTL | C23: руб/т | D23: =Сценарии!$F$14 -> 56100
B24: Цена керосина GTL | C24: руб/т | D24: =Сценарии!$F$15 -> 64500
B25: Цена газа | C25: руб/1000 м³ | D25: =Сценарии!$F$16 -> 4705
B26: Brent | C26: $/барр. | D26: =Сценарии!$F$17 -> 65
B27: Ставка дисконтирования | C27: доля | D27: =Сценарии!$F$18 -> 0.1
B28: Множитель CAPEX | C28: x | D28: =Сценарии!$F$19 -> 1
B29: Множитель добычи | C29: x | D29: =Сценарии!$F$20 -> 1
B30: ВЖК у УКПГ | C30: млрд руб | D30: =Сценарии!$F$21 -> 4
B31: Автодорога | C31: млрд руб | D31: =Сценарии!$F$22 -> 24
B32: GTL + налив | C32: млрд руб | D32: =Сценарии!$F$23 -> 10.75
B33: Услуги чужого ВЖК | C33: млрд руб/год | D33: =Сценарии!$F$24 -> 0
B34: Выход конденсата | C34: кг/1000 м³ | D34: =INDEX(Баланс!$D$18:$G$18,MATCH($D$15,Баланс!$D$17:$G$17,0)) -> 33.107387
B35: Выход СУГ | C35: кг/1000 м³ | D35: =INDEX(Баланс!$D$19:$G$19,MATCH($D$15,Баланс!$D$17:$G$17,0)) -> 77.853527
B36: Выход этана | C36: кг/1000 м³ | D36: =INDEX(Баланс!$D$20:$G$20,MATCH($D$15,Баланс!$D$17:$G$17,0)) -> 58.467219
B37: Товарный газ | C37: м³/1000 м³ | D37: =INDEX(Баланс!$D$21:$G$21,MATCH($D$15,Баланс!$D$17:$G$17,0)) -> 905.94297
B38: Теплота сгорания товарного газа | C38: МДж/м³ | D38: =INDEX(Баланс!$D$22:$G$22,MATCH($D$15,Баланс!$D$17:$G$17,0)) -> 33.272649
B39: Цена товарного газа с учётом теплоты | C39: руб/1000 м³ | D39: =$D$25*$D$38/Исходные!$C$12 -> 4733.0131
B40: Нетбэк конденсата на промысле | C40: руб/т | D40: =($D$26-Исходные!$C$16)*Исходные!$C$17*Исходные!$C$15-Исходные!$C$18 -> 37376
B41: Коэффициент масштаба объектов (полка/14)^0,7 | C41: x | D41: =($D$18/14)^0.7 -> 0.89771245
B42: Фонд эксплуатационных скважин | C42: шт. | D42: =100*$D$18/14*0.5/$D$21 -> 57.142857
B43: GTL: синтетические УВ | C43: млн т/год | D43: =(Исходные!$C$39+Исходные!$C$40)/Исходные!$C$38/1000 -> 0.076502732
B44: GTL: газ на установку | C44: млрд м³/год | D44: =$D$43/Исходные!$C$37 -> 0.18659203
B45: Добыча и продукция
B46: Год | E46: 2027 | F46: 2028 | G46: 2029 | H46: 2030 | I46: 2031 | J46: 2032 | K46: 2033 | L46: 2034 | M46: 2035 | N46: 2036 | O46: 2037 | P46: 2038 | Q46: 2039 | R46: 2040 | S46: 2041 | T46: 2042 | U46: 2043 | V46: 2044 | W46: 2045 | X46: 2046 | Y46: 2047 | Z46: 2048 | AA46: 2049 | AB46: 2050 | AC46: 2051 | AD46: 2052 | AE46: 2053 | AF46: 2054 | AG46: 2055 | AH46: 2056 | AI46: 2057 | AJ46: 2058 | AK46: 2059 | AL46: 2060 | AM46: 2061 | AN46: 2062 | AO46: 2063 | AP46: 2064 | AQ46: 2065 | AR46: 2066
B47: Номер года от начала (для дисконтирования) | E47: =E46-2027 -> 0 | F47: =F46-2027 -> 1 | G47: =G46-2027 -> 2 | H47: =H46-2027 -> 3 | I47: =I46-2027 -> 4 | J47: =J46-2027 -> 5 | K47: =K46-2027 -> 6 | L47: =L46-2027 -> 7 | ... AR47: =AR46-2027 -> 39
B48: Признак падения добычи | C48: 0/1 | E48: 0 | F48: =IF(F46<=Исходные!$C$9+1,0,IF(OR(E48=1,E51+$D$18>Исходные!$C$10*Исходные!$C$8),1,0)) -> 0 | G48: =IF(G46<=Исходные!$C$9+1,0,IF(OR(F48=1,F51+$D$18>Исходные!$C$10*Исходные!$C$8),1,0)) -> 0 | H48: =IF(H46<=Исходные!$C$9+1,0,IF(OR(G48=1,G51+$D$18>Исходные!$C$10*Исходные!$C$8),1,0)) -> 0 | I48: =IF(I46<=Исходные!$C$9+1,0,IF(OR(H48=1,H51+$D$18>Исходные!$C$10*Исходные!$C$8),1,0)) -> 0 | J48: =IF(J46<=Исходные!$C$9+1,0,IF(OR(I48=1,I51+$D$18>Исходные!$C$10*Исходные!$C$8),1,0)) -> 0 | K48: =IF(K46<=Исходные!$C$9+1,0,IF(OR(J48=1,J51+$D$18>Исходные!$C$10*Исходные!$C$8),1,0)) -> 0 | L48: =IF(L46<=Исходные!$C$9+1,0,IF(OR(K48=1,K51+$D$18>Исходные!$C$10*Исходные!$C$8),1,0)) -> 0 | M48: =IF(M46<=Исходные!$C$9+1,0,IF(OR(L48=1,L51+$D$18>Исходные!$C$10*Исходные!$C$8),1,0)) -> 0 | ... AR48: =IF(AR46<=Исходные!$C$9+1,0,IF(OR(AQ48=1,AQ51+$D$18>Исходные!$C$10*Исходные!$C$8),1,0)) -> 1
B49: Год падения, порядковый | E49: 0 | F49: =IF(F48=1,E49+1,0) -> 0 | G49: =IF(G48=1,F49+1,0) -> 0 | H49: =IF(H48=1,G49+1,0) -> 0 | I49: =IF(I48=1,H49+1,0) -> 0 | J49: =IF(J48=1,I49+1,0) -> 0 | K49: =IF(K48=1,J49+1,0) -> 0 | L49: =IF(L48=1,K49+1,0) -> 0 | M49: =IF(M48=1,L49+1,0) -> 0 | ... AR49: =IF(AR48=1,AQ49+1,0) -> 23
B50: Профиль добычи (до множителя) | C50: млрд м³ | D50: =SUM(E50:AR50) -> 275.20035 | E50: =IF(E46<Исходные!$C$9,0,IF(E46=Исходные!$C$9,$D$18*5/14,IF(E46=Исходные!$C$9+1,$D$18*10/14,IF(E48=1,$D$18*EXP(-$D$19*E49),$D$18)))) -> 0 | F50: =IF(F46<Исходные!$C$9,0,IF(F46=Исходные!$C$9,$D$18*5/14,IF(F46=Исходные!$C$9+1,$D$18*10/14,IF(F48=1,$D$18*EXP(-$D$19*F49),$D$18)))) -> 0 | G50: =IF(G46<Исходные!$C$9,0,IF(G46=Исходные!$C$9,$D$18*5/14,IF(G46=Исходные!$C$9+1,$D$18*10/14,IF(G48=1,$D$18*EXP(-$D$19*G49),$D$18)))) -> 0 | H50: =IF(H46<Исходные!$C$9,0,IF(H46=Исходные!$C$9,$D$18*5/14,IF(H46=Исходные!$C$9+1,$D$18*10/14,IF(H48=1,$D$18*EXP(-$D$19*H49),$D$18)))) -> 0 | I50: =IF(I46<Исходные!$C$9,0,IF(I46=Исходные!$C$9,$D$18*5/14,IF(I46=Исходные!$C$9+1,$D$18*10/14,IF(I48=1,$D$18*EXP(-$D$19*I49),$D$18)))) -> 4.2857143 | J50: =IF(J46<Исходные!$C$9,0,IF(J46=Исходные!$C$9,$D$18*5/14,IF(J46=Исходные!$C$9+1,$D$18*10/14,IF(J48=1,$D$18*EXP(-$D$19*J49),$D$18)))) -> 8.5714286 | K50: =IF(K46<Исходные!$C$9,0,IF(K46=Исходные!$C$9,$D$18*5/14,IF(K46=Исходные!$C$9+1,$D$18*10/14,IF(K48=1,$D$18*EXP(-$D$19*K49),$D$18)))) -> 12 | L50: =IF(L46<Исходные!$C$9,0,IF(L46=Исходные!$C$9,$D$18*5/14,IF(L46=Исходные!$C$9+1,$D$18*10/14,IF(L48=1,$D$18*EXP(-$D$19*L49),$D$18)))) -> 12 | ... AR50: =IF(AR46<Исходные!$C$9,0,IF(AR46=Исходные!$C$9,$D$18*5/14,IF(AR46=Исходные!$C$9+1,$D$18*10/14,IF(AR48=1,$D$18*EXP(-$D$19*AR49),$D$18)))) -> 2.3039168
B51: Накопленный профиль | C51: млрд м³ | E51: =E50 -> 0 | F51: =E51+F50 -> 0 | G51: =F51+G50 -> 0 | H51: =G51+H50 -> 0 | I51: =H51+I50 -> 4.2857143 | J51: =I51+J50 -> 12.857143 | K51: =J51+K50 -> 24.857143 | L51: =K51+L50 -> 36.857143 | M51: =L51+M50 -> 48.857143 | ... AR51: =AQ51+AR50 -> 275.20035
B52: Добыча сырого газа | C52: млрд м³ | D52: =SUM(E52:AR52) -> 275.20035 | E52: =E50*$D$29 -> 0 | F52: =F50*$D$29 -> 0 | G52: =G50*$D$29 -> 0 | H52: =H50*$D$29 -> 0 | I52: =I50*$D$29 -> 4.2857143 | J52: =J50*$D$29 -> 8.5714286 | K52: =K50*$D$29 -> 12 | L52: =L50*$D$29 -> 12 | ... AR52: =AR50*$D$29 -> 2.3039168
B53: Накопленная добыча | C53: млрд м³ | E53: =E52 -> 0 | F53: =E53+F52 -> 0 | G53: =F53+G52 -> 0 | H53: =G53+H52 -> 0 | I53: =H53+I52 -> 4.2857143 | J53: =I53+J52 -> 12.857143 | K53: =J53+K52 -> 24.857143 | L53: =K53+L52 -> 36.857143 | M53: =L53+M52 -> 48.857143 | ... AR53: =AQ53+AR52 -> 275.20035
B54: Выработанность > 1 % НГЗ (старт Кр) | C54: 0/1 | E54: =IF(E53/Исходные!$C$6>Исходные!$C$29,1,0) -> 0 | F54: =IF(OR(E54=1,F53/Исходные!$C$6>Исходные!$C$29),1,0) -> 0 | G54: =IF(OR(F54=1,G53/Исходные!$C$6>Исходные!$C$29),1,0) -> 0 | H54: =IF(OR(G54=1,H53/Исходные!$C$6>Исходные!$C$29),1,0) -> 0 | I54: =IF(OR(H54=1,I53/Исходные!$C$6>Исходные!$C$29),1,0) -> 1 | J54: =IF(OR(I54=1,J53/Исходные!$C$6>Исходные!$C$29),1,0) -> 1 | K54: =IF(OR(J54=1,K53/Исходные!$C$6>Исходные!$C$29),1,0) -> 1 | L54: =IF(OR(K54=1,L53/Исходные!$C$6>Исходные!$C$29),1,0) -> 1 | M54: =IF(OR(L54=1,M53/Исходные!$C$6>Исходные!$C$29),1,0) -> 1 | ... AR54: =IF(OR(AQ54=1,AR53/Исходные!$C$6>Исходные!$C$29),1,0) -> 1
B55: n для Кр (порядковый год) | E55: =1 -> 1 | F55: =IF(F54=1,IF(E54=1,E55+1,1),1) -> 1 | G55: =IF(G54=1,IF(F54=1,F55+1,1),1) -> 1 | H55: =IF(H54=1,IF(G54=1,G55+1,1),1) -> 1 | I55: =IF(I54=1,IF(H54=1,H55+1,1),1) -> 1 | J55: =IF(J54=1,IF(I54=1,I55+1,1),1) -> 2 | K55: =IF(K54=1,IF(J54=1,J55+1,1),1) -> 3 | L55: =IF(L54=1,IF(K54=1,K55+1,1),1) -> 4 | M55: =IF(M54=1,IF(L54=1,L55+1,1),1) -> 5 | ... AR55: =IF(AR54=1,IF(AQ54=1,AQ55+1,1),1) -> 36
B56: Коэффициент Кр | E56: =IF($D$22=0,1,IF(E55>Исходные!$C$28,1,MIN(1,Исходные!$C$26*E55+Исходные!$C$27))) -> 0.21 | F56: =IF($D$22=0,1,IF(F55>Исходные!$C$28,1,MIN(1,Исходные!$C$26*F55+Исходные!$C$27))) -> 0.21 | G56: =IF($D$22=0,1,IF(G55>Исходные!$C$28,1,MIN(1,Исходные!$C$26*G55+Исходные!$C$27))) -> 0.21 | H56: =IF($D$22=0,1,IF(H55>Исходные!$C$28,1,MIN(1,Исходные!$C$26*H55+Исходные!$C$27))) -> 0.21 | I56: =IF($D$22=0,1,IF(I55>Исходные!$C$28,1,MIN(1,Исходные!$C$26*I55+Исходные!$C$27))) -> 0.21 | J56: =IF($D$22=0,1,IF(J55>Исходные!$C$28,1,MIN(1,Исходные!$C$26*J55+Исходные!$C$27))) -> 0.276 | K56: =IF($D$22=0,1,IF(K55>Исходные!$C$28,1,MIN(1,Исходные!$C$26*K55+Исходные!$C$27))) -> 0.342 | L56: =IF($D$22=0,1,IF(L55>Исходные!$C$28,1,MIN(1,Исходные!$C$26*L55+Исходные!$C$27))) -> 0.408 | ... AR56: =IF($D$22=0,1,IF(AR55>Исходные!$C$28,1,MIN(1,Исходные!$C$26*AR55+Исходные!$C$27))) -> 1
B57: Собственные нужды | C57: доля | E57: =IF(E46>=2038,Исходные!$C$22,Исходные!$C$21) -> 0.02 | F57: =IF(F46>=2038,Исходные!$C$22,Исходные!$C$21) -> 0.02 | G57: =IF(G46>=2038,Исходные!$C$22,Исходные!$C$21) -> 0.02 | H57: =IF(H46>=2038,Исходные!$C$22,Исходные!$C$21) -> 0.02 | I57: =IF(I46>=2038,Исходные!$C$22,Исходные!$C$21) -> 0.02 | J57: =IF(J46>=2038,Исходные!$C$22,Исходные!$C$21) -> 0.02 | K57: =IF(K46>=2038,Исходные!$C$22,Исходные!$C$21) -> 0.02 | L57: =IF(L46>=2038,Исходные!$C$22,Исходные!$C$21) -> 0.02 | ... AR57: =IF(AR46>=2038,Исходные!$C$22,Исходные!$C$21) -> 0.035
B58: Газ на подготовку | C58: млрд м³ | D58: =SUM(E58:AR58) -> 266.6612 | E58: =E52*(1-E57) -> 0 | F58: =F52*(1-F57) -> 0 | G58: =G52*(1-G57) -> 0 | H58: =H52*(1-H57) -> 0 | I58: =I52*(1-I57) -> 4.2 | J58: =J52*(1-J57) -> 8.4 | K58: =K52*(1-K57) -> 11.76 | L58: =L52*(1-L57) -> 11.76 | ... AR58: =AR52*(1-AR57) -> 2.2232798
B59: Газ на GTL | C59: млрд м³ | D59: =SUM(E59:AR59) -> 0 | E59: =IF(AND($D$17=1,E46>=Исходные!$C$42,E52>0),$D$44,0) -> 0 | F59: =IF(AND($D$17=1,F46>=Исходные!$C$42,F52>0),$D$44,0) -> 0 | G59: =IF(AND($D$17=1,G46>=Исходные!$C$42,G52>0),$D$44,0) -> 0 | H59: =IF(AND($D$17=1,H46>=Исходные!$C$42,H52>0),$D$44,0) -> 0 | I59: =IF(AND($D$17=1,I46>=Исходные!$C$42,I52>0),$D$44,0) -> 0 | J59: =IF(AND($D$17=1,J46>=Исходные!$C$42,J52>0),$D$44,0) -> 0 | K59: =IF(AND($D$17=1,K46>=Исходные!$C$42,K52>0),$D$44,0) -> 0 | L59: =IF(AND($D$17=1,L46>=Исходные!$C$42,L52>0),$D$44,0) -> 0 | ... AR59: =IF(AND($D$17=1,AR46>=Исходные!$C$42,AR52>0),$D$44,0) -> 0
B60: Товарный газ в ЕСГ | C60: млрд м³ | D60: =SUM(E60:AR60) -> 241.57984 | E60: =E58*$D$37/1000-E59 -> 0 | F60: =F58*$D$37/1000-F59 -> 0 | G60: =G58*$D$37/1000-G59 -> 0 | H60: =H58*$D$37/1000-H59 -> 0 | I60: =I58*$D$37/1000-I59 -> 3.8049605 | J60: =J58*$D$37/1000-J59 -> 7.609921 | K60: =K58*$D$37/1000-K59 -> 10.653889 | L60: =L58*$D$37/1000-L59 -> 10.653889 | ... AR60: =AR58*$D$37/1000-AR59 -> 2.0141647
B61: Стабильный конденсат | C61: млн т | D61: =SUM(E61:AR61) -> 8.8284555 | E61: =E58*$D$34/1000 -> 0 | F61: =F58*$D$34/1000 -> 0 | G61: =G58*$D$34/1000 -> 0 | H61: =H58*$D$34/1000 -> 0 | I61: =I58*$D$34/1000 -> 0.13905103 | J61: =J58*$D$34/1000 -> 0.27810205 | K61: =K58*$D$34/1000 -> 0.38934287 | L61: =L58*$D$34/1000 -> 0.38934287 | ... AR61: =AR58*$D$34/1000 -> 0.073606984
B62: СУГ | C62: млн т | D62: =SUM(E62:AR62) -> 20.760515 | E62: =E58*$D$35/1000 -> 0 | F62: =F58*$D$35/1000 -> 0 | G62: =G58*$D$35/1000 -> 0 | H62: =H58*$D$35/1000 -> 0 | I62: =I58*$D$35/1000 -> 0.32698481 | J62: =J58*$D$35/1000 -> 0.65396962 | K62: =K58*$D$35/1000 -> 0.91555747 | L62: =L58*$D$35/1000 -> 0.91555747 | ... AR62: =AR58*$D$35/1000 -> 0.17309017
B63: Этан | C63: млн т | D63: =SUM(E63:AR63) -> 15.590939 | E63: =E58*$D$36/1000 -> 0 | F63: =F58*$D$36/1000 -> 0 | G63: =G58*$D$36/1000 -> 0 | H63: =H58*$D$36/1000 -> 0 | I63: =I58*$D$36/1000 -> 0.24556232 | J63: =J58*$D$36/1000 -> 0.49112464 | K63: =K58*$D$36/1000 -> 0.6875745 | L63: =L58*$D$36/1000 -> 0.6875745 | ... AR63: =AR58*$D$36/1000 -> 0.12998899
B64: Синтетическое ДТ | C64: млн т | D64: =SUM(E64:AR64) -> 0 | E64: =IF(E59>0,Исходные!$C$39/1000,0) -> 0 | F64: =IF(F59>0,Исходные!$C$39/1000,0) -> 0 | G64: =IF(G59>0,Исходные!$C$39/1000,0) -> 0 | H64: =IF(H59>0,Исходные!$C$39/1000,0) -> 0 | I64: =IF(I59>0,Исходные!$C$39/1000,0) -> 0 | J64: =IF(J59>0,Исходные!$C$39/1000,0) -> 0 | K64: =IF(K59>0,Исходные!$C$39/1000,0) -> 0 | L64: =IF(L59>0,Исходные!$C$39/1000,0) -> 0 | ... AR64: =IF(AR59>0,Исходные!$C$39/1000,0) -> 0
B65: Синтетический авиакеросин | C65: млн т | D65: =SUM(E65:AR65) -> 0 | E65: =IF(E59>0,Исходные!$C$40/1000,0) -> 0 | F65: =IF(F59>0,Исходные!$C$40/1000,0) -> 0 | G65: =IF(G59>0,Исходные!$C$40/1000,0) -> 0 | H65: =IF(H59>0,Исходные!$C$40/1000,0) -> 0 | I65: =IF(I59>0,Исходные!$C$40/1000,0) -> 0 | J65: =IF(J59>0,Исходные!$C$40/1000,0) -> 0 | K65: =IF(K59>0,Исходные!$C$40/1000,0) -> 0 | L65: =IF(L59>0,Исходные!$C$40/1000,0) -> 0 | ... AR65: =IF(AR59>0,Исходные!$C$40/1000,0) -> 0
B66: Нафта GTL (сдаётся с конденсатом) | C66: млн т | D66: =SUM(E66:AR66) -> 0 | E66: =IF(E59>0,$D$43-E64-E65,0) -> 0 | F66: =IF(F59>0,$D$43-F64-F65,0) -> 0 | G66: =IF(G59>0,$D$43-G64-G65,0) -> 0 | H66: =IF(H59>0,$D$43-H64-H65,0) -> 0 | I66: =IF(I59>0,$D$43-I64-I65,0) -> 0 | J66: =IF(J59>0,$D$43-J64-J65,0) -> 0 | K66: =IF(K59>0,$D$43-K64-K65,0) -> 0 | L66: =IF(L59>0,$D$43-L64-L65,0) -> 0 | ... AR66: =IF(AR59>0,$D$43-AR64-AR65,0) -> 0
B67: Выручка, налоги, затраты, млрд руб
B68: Выручка: газ | C68: млрд руб | D68: =SUM(E68:AR68) -> 1143.4005 | E68: =E60*$D$39/1000 -> 0 | F68: =F60*$D$39/1000 -> 0 | G68: =G60*$D$39/1000 -> 0 | H68: =H60*$D$39/1000 -> 0 | I68: =I60*$D$39/1000 -> 18.008928 | J68: =J60*$D$39/1000 -> 36.017855 | K68: =K60*$D$39/1000 -> 50.424998 | L68: =L60*$D$39/1000 -> 50.424998 | ... AR68: =AR60*$D$39/1000 -> 9.5330677
B69: Выручка: конденсат и нафта | C69: млрд руб | D69: =SUM(E69:AR69) -> 329.97235 | E69: =(E61+E66)*$D$40/1000 -> 0 | F69: =(F61+F66)*$D$40/1000 -> 0 | G69: =(G61+G66)*$D$40/1000 -> 0 | H69: =(H61+H66)*$D$40/1000 -> 0 | I69: =(I61+I66)*$D$40/1000 -> 5.1971712 | J69: =(J61+J66)*$D$40/1000 -> 10.394342 | K69: =(K61+K66)*$D$40/1000 -> 14.552079 | L69: =(L61+L66)*$D$40/1000 -> 14.552079 | ... AR69: =(AR61+AR66)*$D$40/1000 -> 2.7511346
B70: Выручка: СУГ и этан | C70: млрд руб | D70: =SUM(E70:AR70) -> 415.21029 | E70: =E62*Исходные!$C$19/1000+E63*Исходные!$C$20/1000 -> 0 | F70: =F62*Исходные!$C$19/1000+F63*Исходные!$C$20/1000 -> 0 | G70: =G62*Исходные!$C$19/1000+G63*Исходные!$C$20/1000 -> 0 | H70: =H62*Исходные!$C$19/1000+H63*Исходные!$C$20/1000 -> 0 | I70: =I62*Исходные!$C$19/1000+I63*Исходные!$C$20/1000 -> 6.5396962 | J70: =J62*Исходные!$C$19/1000+J63*Исходные!$C$20/1000 -> 13.079392 | K70: =K62*Исходные!$C$19/1000+K63*Исходные!$C$20/1000 -> 18.311149 | L70: =L62*Исходные!$C$19/1000+L63*Исходные!$C$20/1000 -> 18.311149 | ... AR70: =AR62*Исходные!$C$19/1000+AR63*Исходные!$C$20/1000 -> 3.4618034
B71: Выручка: ДТ GTL | C71: млрд руб | D71: =SUM(E71:AR71) -> 0 | E71: =E64*$D$23/1000 -> 0 | F71: =F64*$D$23/1000 -> 0 | G71: =G64*$D$23/1000 -> 0 | H71: =H64*$D$23/1000 -> 0 | I71: =I64*$D$23/1000 -> 0 | J71: =J64*$D$23/1000 -> 0 | K71: =K64*$D$23/1000 -> 0 | L71: =L64*$D$23/1000 -> 0 | ... AR71: =AR64*$D$23/1000 -> 0
B72: Выручка: керосин GTL | C72: млрд руб | D72: =SUM(E72:AR72) -> 0 | E72: =E65*$D$24/1000 -> 0 | F72: =F65*$D$24/1000 -> 0 | G72: =G65*$D$24/1000 -> 0 | H72: =H65*$D$24/1000 -> 0 | I72: =I65*$D$24/1000 -> 0 | J72: =J65*$D$24/1000 -> 0 | K72: =K65*$D$24/1000 -> 0 | L72: =L65*$D$24/1000 -> 0 | ... AR72: =AR65*$D$24/1000 -> 0
B73: Выручка всего | C73: млрд руб | D73: =SUM(E73:AR73) -> 1888.5832 | E73: =SUM(E68:E72) -> 0 | F73: =SUM(F68:F72) -> 0 | G73: =SUM(G68:G72) -> 0 | H73: =SUM(H68:H72) -> 0 | I73: =SUM(I68:I72) -> 29.745795 | J73: =SUM(J68:J72) -> 59.49159 | K73: =SUM(K68:K72) -> 83.288226 | L73: =SUM(L68:L72) -> 83.288226 | ... AR73: =SUM(AR68:AR72) -> 15.746006
B74: НДПИ (газ + жидкие УВ, с Кр) | C74: млрд руб | D74: =SUM(E74:AR74) -> 263.62312 | E74: =E52*$D$37/1000*(Исходные!$C$23+Исходные!$C$24*E56)/1000+Исходные!$C$25*E56*(E69+E70) -> 0 | F74: =F52*$D$37/1000*(Исходные!$C$23+Исходные!$C$24*F56)/1000+Исходные!$C$25*F56*(F69+F70) -> 0 | G74: =G52*$D$37/1000*(Исходные!$C$23+Исходные!$C$24*G56)/1000+Исходные!$C$25*G56*(G69+G70) -> 0 | H74: =H52*$D$37/1000*(Исходные!$C$23+Исходные!$C$24*H56)/1000+Исходные!$C$25*H56*(H69+H70) -> 0 | I74: =I52*$D$37/1000*(Исходные!$C$23+Исходные!$C$24*I56)/1000+Исходные!$C$25*I56*(I69+I70) -> 2.4915592 | J74: =J52*$D$37/1000*(Исходные!$C$23+Исходные!$C$24*J56)/1000+Исходные!$C$25*J56*(J69+J70) -> 5.3436346 | K74: =K52*$D$37/1000*(Исходные!$C$23+Исходные!$C$24*K56)/1000+Исходные!$C$25*K56*(K69+K70) -> 7.9858111 | L74: =L52*$D$37/1000*(Исходные!$C$23+Исходные!$C$24*L56)/1000+Исходные!$C$25*L56*(L69+L70) -> 8.4905337 | ... AR74: =AR52*$D$37/1000*(Исходные!$C$23+Исходные!$C$24*AR56)/1000+Исходные!$C$25*AR56*(AR69+AR70) -> 2.4848304
B75: Капитальные вложения, млрд руб
B76: Доразведка, 3D, ТЭО и проектная документация | C76: млрд руб | D76: =CAPEX_нормы!$C$6*INDEX(CAPEX_нормы!$E$6:$I$6,MATCH($D$16,CAPEX_нормы!$E$5:$I$5,0))*$D$28 -> 15 | E76: =$D76*CAPEX_нормы!J$6 -> 15 | F76: =$D76*CAPEX_нормы!K$6 -> 0 | G76: =$D76*CAPEX_нормы!L$6 -> 0 | H76: =$D76*CAPEX_нормы!M$6 -> 0 | I76: =$D76*CAPEX_нормы!N$6 -> 0 | J76: =$D76*CAPEX_нормы!O$6 -> 0 | K76: =$D76*CAPEX_нормы!P$6 -> 0 | L76: =$D76*CAPEX_нормы!Q$6 -> 0 | ... W76: =$D76*CAPEX_нормы!AB$6 -> 0 | X76: 0 | Y76: 0 | Z76: 0 | AA76: 0 | AB76: 0 | AC76: 0 | AD76: 0 | AE76: 0 | AF76: 0 | AG76: 0 | AH76: 0 | AI76: 0 | AJ76: 0 | AK76: 0 | AL76: 0 | AM76: 0 | AN76: 0 | AO76: 0 | AP76: 0 | AQ76: 0 | AR76: 0
B77: Эксплуатационные скважины | C77: млрд руб | D77: =$D$42*$D$20*INDEX(CAPEX_нормы!$E$7:$I$7,MATCH($D$16,CAPEX_нормы!$E$5:$I$5,0))*$D$28 -> 85.714286 | E77: =$D77*CAPEX_нормы!J$7 -> 0 | F77: =$D77*CAPEX_нормы!K$7 -> 17.142857 | G77: =$D77*CAPEX_нормы!L$7 -> 25.714286 | H77: =$D77*CAPEX_нормы!M$7 -> 25.714286 | I77: =$D77*CAPEX_нормы!N$7 -> 6.8571429 | J77: =$D77*CAPEX_нормы!O$7 -> 0 | K77: =$D77*CAPEX_нормы!P$7 -> 0 | L77: =$D77*CAPEX_нормы!Q$7 -> 0 | ... W77: =$D77*CAPEX_нормы!AB$7 -> 0 | X77: 0 | Y77: 0 | Z77: 0 | AA77: 0 | AB77: 0 | AC77: 0 | AD77: 0 | AE77: 0 | AF77: 0 | AG77: 0 | AH77: 0 | AI77: 0 | AJ77: 0 | AK77: 0 | AL77: 0 | AM77: 0 | AN77: 0 | AO77: 0 | AP77: 0 | AQ77: 0 | AR77: 0
B78: Кусты скважин и газосборная сеть | C78: млрд руб | D78: =CAPEX_нормы!$C$8*$D$41*INDEX(CAPEX_нормы!$E$8:$I$8,MATCH($D$16,CAPEX_нормы!$E$5:$I$5,0))*$D$28 -> 41.743629 | E78: =$D78*CAPEX_нормы!J$8 -> 0 | F78: =$D78*CAPEX_нормы!K$8 -> 12.523089 | G78: =$D78*CAPEX_нормы!L$8 -> 16.697452 | H78: =$D78*CAPEX_нормы!M$8 -> 12.523089 | I78: =$D78*CAPEX_нормы!N$8 -> 0 | J78: =$D78*CAPEX_нормы!O$8 -> 0 | K78: =$D78*CAPEX_нормы!P$8 -> 0 | L78: =$D78*CAPEX_нормы!Q$8 -> 0 | ... W78: =$D78*CAPEX_нормы!AB$8 -> 0 | X78: 0 | Y78: 0 | Z78: 0 | AA78: 0 | AB78: 0 | AC78: 0 | AD78: 0 | AE78: 0 | AF78: 0 | AG78: 0 | AH78: 0 | AI78: 0 | AJ78: 0 | AK78: 0 | AL78: 0 | AM78: 0 | AN78: 0 | AO78: 0 | AP78: 0 | AQ78: 0 | AR78: 0
B79: УКПГ: НТС, регенерация метанола, стабилизация | C79: млрд руб | D79: =CAPEX_нормы!$C$9*$D$41*INDEX(CAPEX_нормы!$E$9:$I$9,MATCH($D$16,CAPEX_нормы!$E$5:$I$5,0))*$D$28 -> 70.129296 | E79: =$D79*CAPEX_нормы!J$9 -> 0 | F79: =$D79*CAPEX_нормы!K$9 -> 20.871811 | G79: =$D79*CAPEX_нормы!L$9 -> 29.220564 | H79: =$D79*CAPEX_нормы!M$9 -> 20.036922 | I79: =$D79*CAPEX_нормы!N$9 -> 0 | J79: =$D79*CAPEX_нормы!O$9 -> 0 | K79: =$D79*CAPEX_нормы!P$9 -> 0 | L79: =$D79*CAPEX_нормы!Q$9 -> 0 | ... W79: =$D79*CAPEX_нормы!AB$9 -> 0 | X79: 0 | Y79: 0 | Z79: 0 | AA79: 0 | AB79: 0 | AC79: 0 | AD79: 0 | AE79: 0 | AF79: 0 | AG79: 0 | AH79: 0 | AI79: 0 | AJ79: 0 | AK79: 0 | AL79: 0 | AM79: 0 | AN79: 0 | AO79: 0 | AP79: 0 | AQ79: 0 | AR79: 0
B80: Турбодетандерные агрегаты (5 шт.) | C80: млрд руб | D80: =CAPEX_нормы!$C$10*$D$41*INDEX(CAPEX_нормы!$E$10:$I$10,MATCH($D$16,CAPEX_нормы!$E$5:$I$5,0))*$D$28 -> 0 | E80: =$D80*CAPEX_нормы!J$10 -> 0 | F80: =$D80*CAPEX_нормы!K$10 -> 0 | G80: =$D80*CAPEX_нормы!L$10 -> 0 | H80: =$D80*CAPEX_нормы!M$10 -> 0 | I80: =$D80*CAPEX_нормы!N$10 -> 0 | J80: =$D80*CAPEX_нормы!O$10 -> 0 | K80: =$D80*CAPEX_нормы!P$10 -> 0 | L80: =$D80*CAPEX_нормы!Q$10 -> 0 | ... W80: =$D80*CAPEX_нормы!AB$10 -> 0 | X80: 0 | Y80: 0 | Z80: 0 | AA80: 0 | AB80: 0 | AC80: 0 | AD80: 0 | AE80: 0 | AF80: 0 | AG80: 0 | AH80: 0 | AI80: 0 | AJ80: 0 | AK80: 0 | AL80: 0 | AM80: 0 | AN80: 0 | AO80: 0 | AP80: 0 | AQ80: 0 | AR80: 0
B81: ТДА + деэтанизация + ГФУ + парк СУГ | C81: млрд руб | D81: =CAPEX_нормы!$C$11*$D$41*INDEX(CAPEX_нормы!$E$11:$I$11,MATCH($D$16,CAPEX_нормы!$E$5:$I$5,0))*$D$28 -> 53.862747 | E81: =$D81*CAPEX_нормы!J$11 -> 0 | F81: =$D81*CAPEX_нормы!K$11 -> 0 | G81: =$D81*CAPEX_нормы!L$11 -> 22.442829 | H81: =$D81*CAPEX_нормы!M$11 -> 31.419918 | I81: =$D81*CAPEX_нормы!N$11 -> 0 | J81: =$D81*CAPEX_нормы!O$11 -> 0 | K81: =$D81*CAPEX_нормы!P$11 -> 0 | L81: =$D81*CAPEX_нормы!Q$11 -> 0 | ... W81: =$D81*CAPEX_нормы!AB$11 -> 0 | X81: 0 | Y81: 0 | Z81: 0 | AA81: 0 | AB81: 0 | AC81: 0 | AD81: 0 | AE81: 0 | AF81: 0 | AG81: 0 | AH81: 0 | AI81: 0 | AJ81: 0 | AK81: 0 | AL81: 0 | AM81: 0 | AN81: 0 | AO81: 0 | AP81: 0 | AQ81: 0 | AR81: 0
B82: Продуктопровод СУГ 120 км | C82: млрд руб | D82: =CAPEX_нормы!$C$12*$D$41*INDEX(CAPEX_нормы!$E$12:$I$12,MATCH($D$16,CAPEX_нормы!$E$5:$I$5,0))*$D$28 -> 8.6180395 | E82: =$D82*CAPEX_нормы!J$12 -> 0 | F82: =$D82*CAPEX_нормы!K$12 -> 0 | G82: =$D82*CAPEX_нормы!L$12 -> 4.4885594 | H82: =$D82*CAPEX_нормы!M$12 -> 4.1294801 | I82: =$D82*CAPEX_нормы!N$12 -> 0 | J82: =$D82*CAPEX_нормы!O$12 -> 0 | K82: =$D82*CAPEX_нормы!P$12 -> 0 | L82: =$D82*CAPEX_нормы!Q$12 -> 0 | ... W82: =$D82*CAPEX_нормы!AB$12 -> 0 | X82: 0 | Y82: 0 | Z82: 0 | AA82: 0 | AB82: 0 | AC82: 0 | AD82: 0 | AE82: 0 | AF82: 0 | AG82: 0 | AH82: 0 | AI82: 0 | AJ82: 0 | AK82: 0 | AL82: 0 | AM82: 0 | AN82: 0 | AO82: 0 | AP82: 0 | AQ82: 0 | AR82: 0
B83: Налив СУГ на ж/д | C83: млрд руб | D83: =CAPEX_нормы!$C$13*$D$41*INDEX(CAPEX_нормы!$E$13:$I$13,MATCH($D$16,CAPEX_нормы!$E$5:$I$5,0))*$D$28 -> 2.6931373 | E83: =$D83*CAPEX_нормы!J$13 -> 0 | F83: =$D83*CAPEX_нормы!K$13 -> 0 | G83: =$D83*CAPEX_нормы!L$13 -> 1.3465687 | H83: =$D83*CAPEX_нормы!M$13 -> 1.3465687 | I83: =$D83*CAPEX_нормы!N$13 -> 0 | J83: =$D83*CAPEX_нормы!O$13 -> 0 | K83: =$D83*CAPEX_нормы!P$13 -> 0 | L83: =$D83*CAPEX_нормы!Q$13 -> 0 | ... W83: =$D83*CAPEX_нормы!AB$13 -> 0 | X83: 0 | Y83: 0 | Z83: 0 | AA83: 0 | AB83: 0 | AC83: 0 | AD83: 0 | AE83: 0 | AF83: 0 | AG83: 0 | AH83: 0 | AI83: 0 | AJ83: 0 | AK83: 0 | AL83: 0 | AM83: 0 | AN83: 0 | AO83: 0 | AP83: 0 | AQ83: 0 | AR83: 0
B84: Пропановая холодильная установка | C84: млрд руб | D84: =CAPEX_нормы!$C$14*$D$41*INDEX(CAPEX_нормы!$E$14:$I$14,MATCH($D$16,CAPEX_нормы!$E$5:$I$5,0))*$D$28 -> 10.772549 | E84: =$D84*CAPEX_нормы!J$14 -> 0 | F84: =$D84*CAPEX_нормы!K$14 -> 0 | G84: =$D84*CAPEX_нормы!L$14 -> 0 | H84: =$D84*CAPEX_нормы!M$14 -> 0 | I84: =$D84*CAPEX_нормы!N$14 -> 0 | J84: =$D84*CAPEX_нормы!O$14 -> 0 | K84: =$D84*CAPEX_нормы!P$14 -> 0 | L84: =$D84*CAPEX_нормы!Q$14 -> 0 | ... W84: =$D84*CAPEX_нормы!AB$14 -> 0 | X84: 0 | Y84: 0 | Z84: 0 | AA84: 0 | AB84: 0 | AC84: 0 | AD84: 0 | AE84: 0 | AF84: 0 | AG84: 0 | AH84: 0 | AI84: 0 | AJ84: 0 | AK84: 0 | AL84: 0 | AM84: 0 | AN84: 0 | AO84: 0 | AP84: 0 | AQ84: 0 | AR84: 0
B85: Криогенный блок извлечения этана | C85: млрд руб | D85: =CAPEX_нормы!$C$15*$D$41*INDEX(CAPEX_нормы!$E$15:$I$15,MATCH($D$16,CAPEX_нормы!$E$5:$I$5,0))*$D$28 -> 62.839871 | E85: =$D85*CAPEX_нормы!J$15 -> 0 | F85: =$D85*CAPEX_нормы!K$15 -> 0 | G85: =$D85*CAPEX_нормы!L$15 -> 26.931347 | H85: =$D85*CAPEX_нормы!M$15 -> 35.908525 | I85: =$D85*CAPEX_нормы!N$15 -> 0 | J85: =$D85*CAPEX_нормы!O$15 -> 0 | K85: =$D85*CAPEX_нормы!P$15 -> 0 | L85: =$D85*CAPEX_нормы!Q$15 -> 0 | ... W85: =$D85*CAPEX_нормы!AB$15 -> 0 | X85: 0 | Y85: 0 | Z85: 0 | AA85: 0 | AB85: 0 | AC85: 0 | AD85: 0 | AE85: 0 | AF85: 0 | AG85: 0 | AH85: 0 | AI85: 0 | AJ85: 0 | AK85: 0 | AL85: 0 | AM85: 0 | AN85: 0 | AO85: 0 | AP85: 0 | AQ85: 0 | AR85: 0
B86: Энергоцентр (ЭСН), промбаза | C86: млрд руб | D86: =CAPEX_нормы!$C$16*$D$41*INDEX(CAPEX_нормы!$E$16:$I$16,MATCH($D$16,CAPEX_нормы!$E$5:$I$5,0))*$D$28 -> 10.772549 | E86: =$D86*CAPEX_нормы!J$16 -> 0 | F86: =$D86*CAPEX_нормы!K$16 -> 4.4885658 | G86: =$D86*CAPEX_нормы!L$16 -> 4.4885658 | H86: =$D86*CAPEX_нормы!M$16 -> 1.7954285 | I86: =$D86*CAPEX_нормы!N$16 -> 0 | J86: =$D86*CAPEX_нормы!O$16 -> 0 | K86: =$D86*CAPEX_нормы!P$16 -> 0 | L86: =$D86*CAPEX_нормы!Q$16 -> 0 | ... W86: =$D86*CAPEX_нормы!AB$16 -> 0 | X86: 0 | Y86: 0 | Z86: 0 | AA86: 0 | AB86: 0 | AC86: 0 | AD86: 0 | AE86: 0 | AF86: 0 | AG86: 0 | AH86: 0 | AI86: 0 | AJ86: 0 | AK86: 0 | AL86: 0 | AM86: 0 | AN86: 0 | AO86: 0 | AP86: 0 | AQ86: 0 | AR86: 0
B87: Вахтовый жилой комплекс у УКПГ | C87: млрд руб | D87: =$D$30*INDEX(CAPEX_нормы!$E$17:$I$17,MATCH($D$16,CAPEX_нормы!$E$5:$I$5,0))*$D$28 -> 4 | E87: =$D87*CAPEX_нормы!J$17 -> 0 | F87: =$D87*CAPEX_нормы!K$17 -> 1.5 | G87: =$D87*CAPEX_нормы!L$17 -> 1.5 | H87: =$D87*CAPEX_нормы!M$17 -> 1 | I87: =$D87*CAPEX_нормы!N$17 -> 0 | J87: =$D87*CAPEX_нормы!O$17 -> 0 | K87: =$D87*CAPEX_нормы!P$17 -> 0 | L87: =$D87*CAPEX_нормы!Q$17 -> 0 | ... W87: =$D87*CAPEX_нормы!AB$17 -> 0 | X87: 0 | Y87: 0 | Z87: 0 | AA87: 0 | AB87: 0 | AC87: 0 | AD87: 0 | AE87: 0 | AF87: 0 | AG87: 0 | AH87: 0 | AI87: 0 | AJ87: 0 | AK87: 0 | AL87: 0 | AM87: 0 | AN87: 0 | AO87: 0 | AP87: 0 | AQ87: 0 | AR87: 0
B88: Автодорога до Бованенково 120 км | C88: млрд руб | D88: =$D$31*INDEX(CAPEX_нормы!$E$18:$I$18,MATCH($D$16,CAPEX_нормы!$E$5:$I$5,0))*$D$28 -> 24 | E88: =$D88*CAPEX_нормы!J$18 -> 0 | F88: =$D88*CAPEX_нормы!K$18 -> 9.6 | G88: =$D88*CAPEX_нормы!L$18 -> 9.6 | H88: =$D88*CAPEX_нормы!M$18 -> 4.8 | I88: =$D88*CAPEX_нормы!N$18 -> 0 | J88: =$D88*CAPEX_нормы!O$18 -> 0 | K88: =$D88*CAPEX_нормы!P$18 -> 0 | L88: =$D88*CAPEX_нормы!Q$18 -> 0 | ... W88: =$D88*CAPEX_нормы!AB$18 -> 0 | X88: 0 | Y88: 0 | Z88: 0 | AA88: 0 | AB88: 0 | AC88: 0 | AD88: 0 | AE88: 0 | AF88: 0 | AG88: 0 | AH88: 0 | AI88: 0 | AJ88: 0 | AK88: 0 | AL88: 0 | AM88: 0 | AN88: 0 | AO88: 0 | AP88: 0 | AQ88: 0 | AR88: 0
B89: Газопровод 120 км до Бованенково | C89: млрд руб | D89: =CAPEX_нормы!$C$19*$D$41*INDEX(CAPEX_нормы!$E$19:$I$19,MATCH($D$16,CAPEX_нормы!$E$5:$I$5,0))*$D$28 -> 37.703923 | E89: =$D89*CAPEX_нормы!J$19 -> 0 | F89: =$D89*CAPEX_нормы!K$19 -> 10.772539 | G89: =$D89*CAPEX_нормы!L$19 -> 17.954231 | H89: =$D89*CAPEX_нормы!M$19 -> 8.9771155 | I89: =$D89*CAPEX_нормы!N$19 -> 0 | J89: =$D89*CAPEX_нормы!O$19 -> 0 | K89: =$D89*CAPEX_нормы!P$19 -> 0 | L89: =$D89*CAPEX_нормы!Q$19 -> 0 | ... W89: =$D89*CAPEX_нормы!AB$19 -> 0 | X89: 0 | Y89: 0 | Z89: 0 | AA89: 0 | AB89: 0 | AC89: 0 | AD89: 0 | AE89: 0 | AF89: 0 | AG89: 0 | AH89: 0 | AI89: 0 | AJ89: 0 | AK89: 0 | AL89: 0 | AM89: 0 | AN89: 0 | AO89: 0 | AP89: 0 | AQ89: 0 | AR89: 0
B90: Конденсатопровод 120 км | C90: млрд руб | D90: =CAPEX_нормы!$C$20*$D$41*INDEX(CAPEX_нормы!$E$20:$I$20,MATCH($D$16,CAPEX_нормы!$E$5:$I$5,0))*$D$28 -> 8.6180395 | E90: =$D90*CAPEX_нормы!J$20 -> 0 | F90: =$D90*CAPEX_нормы!K$20 -> 0 | G90: =$D90*CAPEX_нормы!L$20 -> 5.3862747 | H90: =$D90*CAPEX_нормы!M$20 -> 3.2317648 | I90: =$D90*CAPEX_нормы!N$20 -> 0 | J90: =$D90*CAPEX_нормы!O$20 -> 0 | K90: =$D90*CAPEX_нормы!P$20 -> 0 | L90: =$D90*CAPEX_нормы!Q$20 -> 0 | ... W90: =$D90*CAPEX_нормы!AB$20 -> 0 | X90: 0 | Y90: 0 | Z90: 0 | AA90: 0 | AB90: 0 | AC90: 0 | AD90: 0 | AE90: 0 | AF90: 0 | AG90: 0 | AH90: 0 | AI90: 0 | AJ90: 0 | AK90: 0 | AL90: 0 | AM90: 0 | AN90: 0 | AO90: 0 | AP90: 0 | AQ90: 0 | AR90: 0
B91: ДКС (2 очереди) | C91: млрд руб | D91: =CAPEX_нормы!$C$21*$D$41*INDEX(CAPEX_нормы!$E$21:$I$21,MATCH($D$16,CAPEX_нормы!$E$5:$I$5,0))*$D$28 -> 49.374185 | E91: =$D91*CAPEX_нормы!J$21 -> 0 | F91: =$D91*CAPEX_нормы!K$21 -> 0 | G91: =$D91*CAPEX_нормы!L$21 -> 0 | H91: =$D91*CAPEX_нормы!M$21 -> 0 | I91: =$D91*CAPEX_нормы!N$21 -> 0 | J91: =$D91*CAPEX_нормы!O$21 -> 0 | K91: =$D91*CAPEX_нормы!P$21 -> 0 | L91: =$D91*CAPEX_нормы!Q$21 -> 0 | ... W91: =$D91*CAPEX_нормы!AB$21 -> 17.954231 | X91: 0 | Y91: 0 | Z91: 0 | AA91: 0 | AB91: 0 | AC91: 0 | AD91: 0 | AE91: 0 | AF91: 0 | AG91: 0 | AH91: 0 | AI91: 0 | AJ91: 0 | AK91: 0 | AL91: 0 | AM91: 0 | AN91: 0 | AO91: 0 | AP91: 0 | AQ91: 0 | AR91: 0
B92: GTL-установка у ст. Бованенково + налив | C92: млрд руб | D92: =$D$32*$D$17*INDEX(CAPEX_нормы!$E$22:$I$22,MATCH($D$16,CAPEX_нормы!$E$5:$I$5,0))*$D$28 -> 0 | E92: =$D92*CAPEX_нормы!J$22 -> 0 | F92: =$D92*CAPEX_нормы!K$22 -> 0 | G92: =$D92*CAPEX_нормы!L$22 -> 0 | H92: =$D92*CAPEX_нормы!M$22 -> 0 | I92: =$D92*CAPEX_нормы!N$22 -> 0 | J92: =$D92*CAPEX_нормы!O$22 -> 0 | K92: =$D92*CAPEX_нормы!P$22 -> 0 | L92: =$D92*CAPEX_нормы!Q$22 -> 0 | ... W92: =$D92*CAPEX_нормы!AB$22 -> 0 | X92: 0 | Y92: 0 | Z92: 0 | AA92: 0 | AB92: 0 | AC92: 0 | AD92: 0 | AE92: 0 | AF92: 0 | AG92: 0 | AH92: 0 | AI92: 0 | AJ92: 0 | AK92: 0 | AL92: 0 | AM92: 0 | AN92: 0 | AO92: 0 | AP92: 0 | AQ92: 0 | AR92: 0
B93: CAPEX всего | C93: млрд руб | D93: =SUM(E93:AR93) -> 485.84218 | E93: =SUM(E76:E92) -> 15 | F93: =SUM(F76:F92) -> 76.898861 | G93: =SUM(G76:G92) -> 165.77068 | H93: =SUM(H76:H92) -> 150.8831 | I93: =SUM(I76:I92) -> 6.8571429 | J93: =SUM(J76:J92) -> 0 | K93: =SUM(K76:K92) -> 0 | L93: =SUM(L76:L92) -> 0 | ... AR93: =SUM(AR76:AR92) -> 0
B94: Накопленный CAPEX | C94: млрд руб | E94: =E93 -> 15 | F94: =E94+F93 -> 91.898861 | G94: =F94+G93 -> 257.66954 | H94: =G94+H93 -> 408.55263 | I94: =H94+I93 -> 415.40978 | J94: =I94+J93 -> 415.40978 | K94: =J94+K93 -> 415.40978 | L94: =K94+L93 -> 415.40978 | M94: =L94+M93 -> 415.40978 | ... AR94: =AQ94+AR93 -> 485.84218
B95: Операционные затраты, амортизация, налоги, млрд руб
B96: Признак добычи | C96: 0/1 | E96: =IF(E52>0,1,0) -> 0 | F96: =IF(F52>0,1,0) -> 0 | G96: =IF(G52>0,1,0) -> 0 | H96: =IF(H52>0,1,0) -> 0 | I96: =IF(I52>0,1,0) -> 1 | J96: =IF(J52>0,1,0) -> 1 | K96: =IF(K52>0,1,0) -> 1 | L96: =IF(L52>0,1,0) -> 1 | ... AR96: =IF(AR52>0,1,0) -> 1
B97: OPEX (пост. + перем. + СУГ + терминал + GTL + чужой ВЖК) | C97: млрд руб | D97: =SUM(E97:AR97) -> 330.18836 | E97: =E96*Исходные!$C$33*E94+E52*Исходные!$C$34/1000+E62*Исходные!$C$35/1000+(E61+E62)*Исходные!$C$36/1000+IF(E59>0,$D$43*Исходные!$C$41/1000,0)+E96*$D$33 -> 0 | F97: =F96*Исходные!$C$33*F94+F52*Исходные!$C$34/1000+F62*Исходные!$C$35/1000+(F61+F62)*Исходные!$C$36/1000+IF(F59>0,$D$43*Исходные!$C$41/1000,0)+F96*$D$33 -> 0 | G97: =G96*Исходные!$C$33*G94+G52*Исходные!$C$34/1000+G62*Исходные!$C$35/1000+(G61+G62)*Исходные!$C$36/1000+IF(G59>0,$D$43*Исходные!$C$41/1000,0)+G96*$D$33 -> 0 | H97: =H96*Исходные!$C$33*H94+H52*Исходные!$C$34/1000+H62*Исходные!$C$35/1000+(H61+H62)*Исходные!$C$36/1000+IF(H59>0,$D$43*Исходные!$C$41/1000,0)+H96*$D$33 -> 0 | I97: =I96*Исходные!$C$33*I94+I52*Исходные!$C$34/1000+I62*Исходные!$C$35/1000+(I61+I62)*Исходные!$C$36/1000+IF(I59>0,$D$43*Исходные!$C$41/1000,0)+I96*$D$33 -> 7.4340065 | J97: =J96*Исходные!$C$33*J94+J52*Исходные!$C$34/1000+J62*Исходные!$C$35/1000+(J61+J62)*Исходные!$C$36/1000+IF(J59>0,$D$43*Исходные!$C$41/1000,0)+J96*$D$33 -> 8.6368664 | K97: =K96*Исходные!$C$33*K94+K52*Исходные!$C$34/1000+K62*Исходные!$C$35/1000+(K61+K62)*Исходные!$C$36/1000+IF(K59>0,$D$43*Исходные!$C$41/1000,0)+K96*$D$33 -> 9.5991543 | L97: =L96*Исходные!$C$33*L94+L52*Исходные!$C$34/1000+L62*Исходные!$C$35/1000+(L61+L62)*Исходные!$C$36/1000+IF(L59>0,$D$43*Исходные!$C$41/1000,0)+L96*$D$33 -> 9.5991543 | ... AR97: =AR96*Исходные!$C$33*AR94+AR52*Исходные!$C$34/1000+AR62*Исходные!$C$35/1000+(AR61+AR62)*Исходные!$C$36/1000+IF(AR59>0,$D$43*Исходные!$C$41/1000,0)+AR96*$D$33 -> 7.9296589
B98: Ввод основных средств | C98: млрд руб | D98: =SUM(E98:AR98) -> 485.84218 | E98: 0 | F98: 0 | G98: 0 | H98: 0 | I98: =SUM(E93:H93) -> 408.55263 | J98: =I93 -> 6.8571429 | K98: =J93 -> 0 | L98: =K93 -> 0 | M98: =L93 -> 0 | N98: =M93 -> 0 | O98: =N93 -> 2.5714286 | P98: =O93 -> 16.037102 | Q98: =P93 -> 31.298209 | ... AR98: =AQ93 -> 0
B99: Амортизация | C99: млрд руб | D99: =SUM(E99:AR99) -> 485.84218 | E99: =SUM(OFFSET(E98,0,-MIN(Исходные!$C$32-1,E47),1,MIN(Исходные!$C$32,E47+1)))/Исходные!$C$32 -> 0 | F99: =SUM(OFFSET(F98,0,-MIN(Исходные!$C$32-1,F47),1,MIN(Исходные!$C$32,F47+1)))/Исходные!$C$32 -> 0 | G99: =SUM(OFFSET(G98,0,-MIN(Исходные!$C$32-1,G47),1,MIN(Исходные!$C$32,G47+1)))/Исходные!$C$32 -> 0 | H99: =SUM(OFFSET(H98,0,-MIN(Исходные!$C$32-1,H47),1,MIN(Исходные!$C$32,H47+1)))/Исходные!$C$32 -> 0 | I99: =SUM(OFFSET(I98,0,-MIN(Исходные!$C$32-1,I47),1,MIN(Исходные!$C$32,I47+1)))/Исходные!$C$32 -> 27.236842 | J99: =SUM(OFFSET(J98,0,-MIN(Исходные!$C$32-1,J47),1,MIN(Исходные!$C$32,J47+1)))/Исходные!$C$32 -> 27.693985 | K99: =SUM(OFFSET(K98,0,-MIN(Исходные!$C$32-1,K47),1,MIN(Исходные!$C$32,K47+1)))/Исходные!$C$32 -> 27.693985 | L99: =SUM(OFFSET(L98,0,-MIN(Исходные!$C$32-1,L47),1,MIN(Исходные!$C$32,L47+1)))/Исходные!$C$32 -> 27.693985 | ... AR99: =SUM(OFFSET(AR98,0,-MIN(Исходные!$C$32-1,AR47),1,MIN(Исходные!$C$32,AR47+1)))/Исходные!$C$32 -> 0
B100: Накопленная амортизация | C100: млрд руб | E100: =E99 -> 0 | F100: =E100+F99 -> 0 | G100: =F100+G99 -> 0 | H100: =G100+H99 -> 0 | I100: =H100+I99 -> 27.236842 | J100: =I100+J99 -> 54.930827 | K100: =J100+K99 -> 82.624812 | L100: =K100+L99 -> 110.3188 | M100: =L100+M99 -> 138.01278 | ... AR100: =AQ100+AR99 -> 485.84218
B101: Налог на имущество | C101: млрд руб | D101: =SUM(E101:AR101) -> 76.520065 | E101: =E96*Исходные!$C$31*(E94-E100) -> 0 | F101: =F96*Исходные!$C$31*(F94-F100) -> 0 | G101: =G96*Исходные!$C$31*(G94-G100) -> 0 | H101: =H96*Исходные!$C$31*(H94-H100) -> 0 | I101: =I96*Исходные!$C$31*(I94-I100) -> 8.5398046 | J101: =J96*Исходные!$C$31*(J94-J100) -> 7.9305369 | K101: =K96*Исходные!$C$31*(K94-K100) -> 7.3212692 | L101: =L96*Исходные!$C$31*(L94-L100) -> 6.7120015 | ... AR101: =AR96*Исходные!$C$31*(AR94-AR100) -> 0
B102: EBITDA | C102: млрд руб | D102: =SUM(E102:AR102) -> 1218.2516 | E102: =E73-E74-E97-E101 -> 0 | F102: =F73-F74-F97-F101 -> 0 | G102: =G73-G74-G97-G101 -> 0 | H102: =H73-H74-H97-H101 -> 0 | I102: =I73-I74-I97-I101 -> 11.280425 | J102: =J73-J74-J97-J101 -> 37.580552 | K102: =K73-K74-K97-K101 -> 58.381992 | L102: =L73-L74-L97-L101 -> 58.486537 | ... AR102: =AR73-AR74-AR97-AR101 -> 5.3315165
B103: Налог на прибыль | C103: млрд руб | D103: =SUM(E103:AR103) -> 187.09147 | E103: =MAX(0,E102-E99)*Исходные!$C$30 -> 0 | F103: =MAX(0,F102-F99)*Исходные!$C$30 -> 0 | G103: =MAX(0,G102-G99)*Исходные!$C$30 -> 0 | H103: =MAX(0,H102-H99)*Исходные!$C$30 -> 0 | I103: =MAX(0,I102-I99)*Исходные!$C$30 -> 0 | J103: =MAX(0,J102-J99)*Исходные!$C$30 -> 2.4716418 | K103: =MAX(0,K102-K99)*Исходные!$C$30 -> 7.6720017 | L103: =MAX(0,L102-L99)*Исходные!$C$30 -> 7.6981379 | ... AR103: =MAX(0,AR102-AR99)*Исходные!$C$30 -> 1.3328791
...

Sheet Расчёт_Г
B2: Расчёт: Г. НТС на ТДА, без GTL
B3: Наша технология подготовки без GTL. Денежный поток по годам, млрд руб. (реальные цены 2026 г.)
B5: ЧДД (NPV) при ставке варианта, млрд руб | C5: =SUM(E107:AR107) -> 16.893083
B6: ВНД (IRR), реальная | C6: =IRR(E105:AR105,0.1) -> 0.10816471
B7: Дисконтированная окупаемость, год | C7: =IF(SUM(E109:AR109)=0,"нет",2067-SUM(E109:AR109)) -> 2049
B8: Индекс доходности (PI) | C8: =1+C5/SUMPRODUCT(E93:AR93,E106:AR106) -> 1.0677063
B9: CAPEX всего, млрд руб | C9: =D93 -> 351.54439
B10: Фонд скважин, шт. | C10: =$D$42 -> 57.142857
B11: Проверка: Σ профиля − извлекаемые (должно быть ≈ 0), млрд м³ | C11: =D50-Исходные!$C$8 -> 0.0003531191
B13: Показатель | C13: Ед. | D13: Итого / знач. | E13: 2027 | F13: 2028 | G13: 2029 | H13: 2030 | I13: 2031 | J13: 2032 | K13: 2033 | L13: 2034 | M13: 2035 | N13: 2036 | O13: 2037 | P13: 2038 | Q13: 2039 | R13: 2040 | S13: 2041 | T13: 2042 | U13: 2043 | V13: 2044 | W13: 2045 | X13: 2046 | Y13: 2047 | Z13: 2048 | AA13: 2049 | AB13: 2050 | AC13: 2051 | AD13: 2052 | AE13: 2053 | AF13: 2054 | AG13: 2055 | AH13: 2056 | AI13: 2057 | AJ13: 2058 | AK13: 2059 | AL13: 2060 | AM13: 2061 | AN13: 2062 | AO13: 2063 | AP13: 2064 | AQ13: 2065 | AR13: 2066
B14: Параметры варианта (ссылки на «Сценарии» и «Исходные»)
B15: Технология (столбец баланса) | C15: код | D15: =Сценарии!$G$6 -> T
B16: Состав CAPEX | C16: код | D16: =Сценарии!$G$7 -> T0
B17: GTL (1 — есть) | C17: 0/1 | D17: =Сценарии!$G$8 -> 0
B18: Полка добычи | C18: млрд м³/год | D18: =Сценарии!$G$9 -> 12
B19: Темп падения | C19: 1/год | D19: =Сценарии!$G$10 -> 0.071752
B20: Стоимость скважины | C20: млрд руб | D20: =Сценарии!$G$11 -> 1.5
B21: Дебит скважины | C21: млн м³/сут | D21: =Сценарии!$G$12 -> 0.75
B22: Кр (п-ов Ямал) в НДПИ | C22: 0/1 | D22: =Сценарии!$G$13 -> 1
B23: Цена ДТ GTL | C23: руб/т | D23: =Сценарии!$G$14 -> 56100
B24: Цена керосина GTL | C24: руб/т | D24: =Сценарии!$G$15 -> 64500
B25: Цена газа | C25: руб/1000 м³ | D25: =Сценарии!$G$16 -> 4705
B26: Brent | C26: $/барр. | D26: =Сценарии!$G$17 -> 65
B27: Ставка дисконтирования | C27: доля | D27: =Сценарии!$G$18 -> 0.1
B28: Множитель CAPEX | C28: x | D28: =Сценарии!$G$19 -> 1
B29: Множитель добычи | C29: x | D29: =Сценарии!$G$20 -> 1
B30: ВЖК у УКПГ | C30: млрд руб | D30: =Сценарии!$G$21 -> 4
B31: Автодорога | C31: млрд руб | D31: =Сценарии!$G$22 -> 24
B32: GTL + налив | C32: млрд руб | D32: =Сценарии!$G$23 -> 10.75
B33: Услуги чужого ВЖК | C33: млрд руб/год | D33: =Сценарии!$G$24 -> 0
B34: Выход конденсата | C34: кг/1000 м³ | D34: =INDEX(Баланс!$D$18:$G$18,MATCH($D$15,Баланс!$D$17:$G$17,0)) -> 41.334488
B35: Выход СУГ | C35: кг/1000 м³ | D35: =INDEX(Баланс!$D$19:$G$19,MATCH($D$15,Баланс!$D$17:$G$17,0)) -> 0
B36: Выход этана | C36: кг/1000 м³ | D36: =INDEX(Баланс!$D$20:$G$20,MATCH($D$15,Баланс!$D$17:$G$17,0)) -> 0
B37: Товарный газ | C37: м³/1000 м³ | D37: =INDEX(Баланс!$D$21:$G$21,MATCH($D$15,Баланс!$D$17:$G$17,0)) -> 988.42921
B38: Теплота сгорания товарного газа | C38: МДж/м³ | D38: =INDEX(Баланс!$D$22:$G$22,MATCH($D$15,Баланс!$D$17:$G$17,0)) -> 36.565304
B39: Цена товарного газа с учётом теплоты | C39: руб/1000 м³ | D39: =$D$25*$D$38/Исходные!$C$12 -> 5201.3911
B40: Нетбэк конденсата на промысле | C40: руб/т | D40: =($D$26-Исходные!$C$16)*Исходные!$C$17*Исходные!$C$15-Исходные!$C$18 -> 37376
B41: Коэффициент масштаба объектов (полка/14)^0,7 | C41: x | D41: =($D$18/14)^0.7 -> 0.89771245
B42: Фонд эксплуатационных скважин | C42: шт. | D42: =100*$D$18/14*0.5/$D$21 -> 57.142857
B43: GTL: синтетические УВ | C43: млн т/год | D43: =(Исходные!$C$39+Исходные!$C$40)/Исходные!$C$38/1000 -> 0.076502732
B44: GTL: газ на установку | C44: млрд м³/год | D44: =$D$43/Исходные!$C$37 -> 0.18659203
B45: Добыча и продукция
B46: Год | E46: 2027 | F46: 2028 | G46: 2029 | H46: 2030 | I46: 2031 | J46: 2032 | K46: 2033 | L46: 2034 | M46: 2035 | N46: 2036 | O46: 2037 | P46: 2038 | Q46: 2039 | R46: 2040 | S46: 2041 | T46: 2042 | U46: 2043 | V46: 2044 | W46: 2045 | X46: 2046 | Y46: 2047 | Z46: 2048 | AA46: 2049 | AB46: 2050 | AC46: 2051 | AD46: 2052 | AE46: 2053 | AF46: 2054 | AG46: 2055 | AH46: 2056 | AI46: 2057 | AJ46: 2058 | AK46: 2059 | AL46: 2060 | AM46: 2061 | AN46: 2062 | AO46: 2063 | AP46: 2064 | AQ46: 2065 | AR46: 2066
B47: Номер года от начала (для дисконтирования) | E47: =E46-2027 -> 0 | F47: =F46-2027 -> 1 | G47: =G46-2027 -> 2 | H47: =H46-2027 -> 3 | I47: =I46-2027 -> 4 | J47: =J46-2027 -> 5 | K47: =K46-2027 -> 6 | L47: =L46-2027 -> 7 | ... AR47: =AR46-2027 -> 39
B48: Признак падения добычи | C48: 0/1 | E48: 0 | F48: =IF(F46<=Исходные!$C$9+1,0,IF(OR(E48=1,E51+$D$18>Исходные!$C$10*Исходные!$C$8),1,0)) -> 0 | G48: =IF(G46<=Исходные!$C$9+1,0,IF(OR(F48=1,F51+$D$18>Исходные!$C$10*Исходные!$C$8),1,0)) -> 0 | H48: =IF(H46<=Исходные!$C$9+1,0,IF(OR(G48=1,G51+$D$18>Исходные!$C$10*Исходные!$C$8),1,0)) -> 0 | I48: =IF(I46<=Исходные!$C$9+1,0,IF(OR(H48=1,H51+$D$18>Исходные!$C$10*Исходные!$C$8),1,0)) -> 0 | J48: =IF(J46<=Исходные!$C$9+1,0,IF(OR(I48=1,I51+$D$18>Исходные!$C$10*Исходные!$C$8),1,0)) -> 0 | K48: =IF(K46<=Исходные!$C$9+1,0,IF(OR(J48=1,J51+$D$18>Исходные!$C$10*Исходные!$C$8),1,0)) -> 0 | L48: =IF(L46<=Исходные!$C$9+1,0,IF(OR(K48=1,K51+$D$18>Исходные!$C$10*Исходные!$C$8),1,0)) -> 0 | M48: =IF(M46<=Исходные!$C$9+1,0,IF(OR(L48=1,L51+$D$18>Исходные!$C$10*Исходные!$C$8),1,0)) -> 0 | ... AR48: =IF(AR46<=Исходные!$C$9+1,0,IF(OR(AQ48=1,AQ51+$D$18>Исходные!$C$10*Исходные!$C$8),1,0)) -> 1
B49: Год падения, порядковый | E49: 0 | F49: =IF(F48=1,E49+1,0) -> 0 | G49: =IF(G48=1,F49+1,0) -> 0 | H49: =IF(H48=1,G49+1,0) -> 0 | I49: =IF(I48=1,H49+1,0) -> 0 | J49: =IF(J48=1,I49+1,0) -> 0 | K49: =IF(K48=1,J49+1,0) -> 0 | L49: =IF(L48=1,K49+1,0) -> 0 | M49: =IF(M48=1,L49+1,0) -> 0 | ... AR49: =IF(AR48=1,AQ49+1,0) -> 23
B50: Профиль добычи (до множителя) | C50: млрд м³ | D50: =SUM(E50:AR50) -> 275.20035 | E50: =IF(E46<Исходные!$C$9,0,IF(E46=Исходные!$C$9,$D$18*5/14,IF(E46=Исходные!$C$9+1,$D$18*10/14,IF(E48=1,$D$18*EXP(-$D$19*E49),$D$18)))) -> 0 | F50: =IF(F46<Исходные!$C$9,0,IF(F46=Исходные!$C$9,$D$18*5/14,IF(F46=Исходные!$C$9+1,$D$18*10/14,IF(F48=1,$D$18*EXP(-$D$19*F49),$D$18)))) -> 0 | G50: =IF(G46<Исходные!$C$9,0,IF(G46=Исходные!$C$9,$D$18*5/14,IF(G46=Исходные!$C$9+1,$D$18*10/14,IF(G48=1,$D$18*EXP(-$D$19*G49),$D$18)))) -> 0 | H50: =IF(H46<Исходные!$C$9,0,IF(H46=Исходные!$C$9,$D$18*5/14,IF(H46=Исходные!$C$9+1,$D$18*10/14,IF(H48=1,$D$18*EXP(-$D$19*H49),$D$18)))) -> 0 | I50: =IF(I46<Исходные!$C$9,0,IF(I46=Исходные!$C$9,$D$18*5/14,IF(I46=Исходные!$C$9+1,$D$18*10/14,IF(I48=1,$D$18*EXP(-$D$19*I49),$D$18)))) -> 4.2857143 | J50: =IF(J46<Исходные!$C$9,0,IF(J46=Исходные!$C$9,$D$18*5/14,IF(J46=Исходные!$C$9+1,$D$18*10/14,IF(J48=1,$D$18*EXP(-$D$19*J49),$D$18)))) -> 8.5714286 | K50: =IF(K46<Исходные!$C$9,0,IF(K46=Исходные!$C$9,$D$18*5/14,IF(K46=Исходные!$C$9+1,$D$18*10/14,IF(K48=1,$D$18*EXP(-$D$19*K49),$D$18)))) -> 12 | L50: =IF(L46<Исходные!$C$9,0,IF(L46=Исходные!$C$9,$D$18*5/14,IF(L46=Исходные!$C$9+1,$D$18*10/14,IF(L48=1,$D$18*EXP(-$D$19*L49),$D$18)))) -> 12 | ... AR50: =IF(AR46<Исходные!$C$9,0,IF(AR46=Исходные!$C$9,$D$18*5/14,IF(AR46=Исходные!$C$9+1,$D$18*10/14,IF(AR48=1,$D$18*EXP(-$D$19*AR49),$D$18)))) -> 2.3039168
B51: Накопленный профиль | C51: млрд м³ | E51: =E50 -> 0 | F51: =E51+F50 -> 0 | G51: =F51+G50 -> 0 | H51: =G51+H50 -> 0 | I51: =H51+I50 -> 4.2857143 | J51: =I51+J50 -> 12.857143 | K51: =J51+K50 -> 24.857143 | L51: =K51+L50 -> 36.857143 | M51: =L51+M50 -> 48.857143 | ... AR51: =AQ51+AR50 -> 275.20035
B52: Добыча сырого газа | C52: млрд м³ | D52: =SUM(E52:AR52) -> 275.20035 | E52: =E50*$D$29 -> 0 | F52: =F50*$D$29 -> 0 | G52: =G50*$D$29 -> 0 | H52: =H50*$D$29 -> 0 | I52: =I50*$D$29 -> 4.2857143 | J52: =J50*$D$29 -> 8.5714286 | K52: =K50*$D$29 -> 12 | L52: =L50*$D$29 -> 12 | ... AR52: =AR50*$D$29 -> 2.3039168
B53: Накопленная добыча | C53: млрд м³ | E53: =E52 -> 0 | F53: =E53+F52 -> 0 | G53: =F53+G52 -> 0 | H53: =G53+H52 -> 0 | I53: =H53+I52 -> 4.2857143 | J53: =I53+J52 -> 12.857143 | K53: =J53+K52 -> 24.857143 | L53: =K53+L52 -> 36.857143 | M53: =L53+M52 -> 48.857143 | ... AR53: =AQ53+AR52 -> 275.20035
B54: Выработанность > 1 % НГЗ (старт Кр) | C54: 0/1 | E54: =IF(E53/Исходные!$C$6>Исходные!$C$29,1,0) -> 0 | F54: =IF(OR(E54=1,F53/Исходные!$C$6>Исходные!$C$29),1,0) -> 0 | G54: =IF(OR(F54=1,G53/Исходные!$C$6>Исходные!$C$29),1,0) -> 0 | H54: =IF(OR(G54=1,H53/Исходные!$C$6>Исходные!$C$29),1,0) -> 0 | I54: =IF(OR(H54=1,I53/Исходные!$C$6>Исходные!$C$29),1,0) -> 1 | J54: =IF(OR(I54=1,J53/Исходные!$C$6>Исходные!$C$29),1,0) -> 1 | K54: =IF(OR(J54=1,K53/Исходные!$C$6>Исходные!$C$29),1,0) -> 1 | L54: =IF(OR(K54=1,L53/Исходные!$C$6>Исходные!$C$29),1,0) -> 1 | M54: =IF(OR(L54=1,M53/Исходные!$C$6>Исходные!$C$29),1,0) -> 1 | ... AR54: =IF(OR(AQ54=1,AR53/Исходные!$C$6>Исходные!$C$29),1,0) -> 1
B55: n для Кр (порядковый год) | E55: =1 -> 1 | F55: =IF(F54=1,IF(E54=1,E55+1,1),1) -> 1 | G55: =IF(G54=1,IF(F54=1,F55+1,1),1) -> 1 | H55: =IF(H54=1,IF(G54=1,G55+1,1),1) -> 1 | I55: =IF(I54=1,IF(H54=1,H55+1,1),1) -> 1 | J55: =IF(J54=1,IF(I54=1,I55+1,1),1) -> 2 | K55: =IF(K54=1,IF(J54=1,J55+1,1),1) -> 3 | L55: =IF(L54=1,IF(K54=1,K55+1,1),1) -> 4 | M55: =IF(M54=1,IF(L54=1,L55+1,1),1) -> 5 | ... AR55: =IF(AR54=1,IF(AQ54=1,AQ55+1,1),1) -> 36
B56: Коэффициент Кр | E56: =IF($D$22=0,1,IF(E55>Исходные!$C$28,1,MIN(1,Исходные!$C$26*E55+Исходные!$C$27))) -> 0.21 | F56: =IF($D$22=0,1,IF(F55>Исходные!$C$28,1,MIN(1,Исходные!$C$26*F55+Исходные!$C$27))) -> 0.21 | G56: =IF($D$22=0,1,IF(G55>Исходные!$C$28,1,MIN(1,Исходные!$C$26*G55+Исходные!$C$27))) -> 0.21 | H56: =IF($D$22=0,1,IF(H55>Исходные!$C$28,1,MIN(1,Исходные!$C$26*H55+Исходные!$C$27))) -> 0.21 | I56: =IF($D$22=0,1,IF(I55>Исходные!$C$28,1,MIN(1,Исходные!$C$26*I55+Исходные!$C$27))) -> 0.21 | J56: =IF($D$22=0,1,IF(J55>Исходные!$C$28,1,MIN(1,Исходные!$C$26*J55+Исходные!$C$27))) -> 0.276 | K56: =IF($D$22=0,1,IF(K55>Исходные!$C$28,1,MIN(1,Исходные!$C$26*K55+Исходные!$C$27))) -> 0.342 | L56: =IF($D$22=0,1,IF(L55>Исходные!$C$28,1,MIN(1,Исходные!$C$26*L55+Исходные!$C$27))) -> 0.408 | ... AR56: =IF($D$22=0,1,IF(AR55>Исходные!$C$28,1,MIN(1,Исходные!$C$26*AR55+Исходные!$C$27))) -> 1
B57: Собственные нужды | C57: доля | E57: =IF(E46>=2038,Исходные!$C$22,Исходные!$C$21) -> 0.02 | F57: =IF(F46>=2038,Исходные!$C$22,Исходные!$C$21) -> 0.02 | G57: =IF(G46>=2038,Исходные!$C$22,Исходные!$C$21) -> 0.02 | H57: =IF(H46>=2038,Исходные!$C$22,Исходные!$C$21) -> 0.02 | I57: =IF(I46>=2038,Исходные!$C$22,Исходные!$C$21) -> 0.02 | J57: =IF(J46>=2038,Исходные!$C$22,Исходные!$C$21) -> 0.02 | K57: =IF(K46>=2038,Исходные!$C$22,Исходные!$C$21) -> 0.02 | L57: =IF(L46>=2038,Исходные!$C$22,Исходные!$C$21) -> 0.02 | ... AR57: =IF(AR46>=2038,Исходные!$C$22,Исходные!$C$21) -> 0.035
B58: Газ на подготовку | C58: млрд м³ | D58: =SUM(E58:AR58) -> 266.6612 | E58: =E52*(1-E57) -> 0 | F58: =F52*(1-F57) -> 0 | G58: =G52*(1-G57) -> 0 | H58: =H52*(1-H57) -> 0 | I58: =I52*(1-I57) -> 4.2 | J58: =J52*(1-J57) -> 8.4 | K58: =K52*(1-K57) -> 11.76 | L58: =L52*(1-L57) -> 11.76 | ... AR58: =AR52*(1-AR57) -> 2.2232798
B59: Газ на GTL | C59: млрд м³ | D59: =SUM(E59:AR59) -> 0 | E59: =IF(AND($D$17=1,E46>=Исходные!$C$42,E52>0),$D$44,0) -> 0 | F59: =IF(AND($D$17=1,F46>=Исходные!$C$42,F52>0),$D$44,0) -> 0 | G59: =IF(AND($D$17=1,G46>=Исходные!$C$42,G52>0),$D$44,0) -> 0 | H59: =IF(AND($D$17=1,H46>=Исходные!$C$42,H52>0),$D$44,0) -> 0 | I59: =IF(AND($D$17=1,I46>=Исходные!$C$42,I52>0),$D$44,0) -> 0 | J59: =IF(AND($D$17=1,J46>=Исходные!$C$42,J52>0),$D$44,0) -> 0 | K59: =IF(AND($D$17=1,K46>=Исходные!$C$42,K52>0),$D$44,0) -> 0 | L59: =IF(AND($D$17=1,L46>=Исходные!$C$42,L52>0),$D$44,0) -> 0 | ... AR59: =IF(AND($D$17=1,AR46>=Исходные!$C$42,AR52>0),$D$44,0) -> 0
B60: Товарный газ в ЕСГ | C60: млрд м³ | D60: =SUM(E60:AR60) -> 263.57572 | E60: =E58*$D$37/1000-E59 -> 0 | F60: =F58*$D$37/1000-F59 -> 0 | G60: =G58*$D$37/1000-G59 -> 0 | H60: =H58*$D$37/1000-H59 -> 0 | I60: =I58*$D$37/1000-I59 -> 4.1514027 | J60: =J58*$D$37/1000-J59 -> 8.3028054 | K60: =K58*$D$37/1000-K59 -> 11.623928 | L60: =L58*$D$37/1000-L59 -> 11.623928 | ... AR60: =AR58*$D$37/1000-AR59 -> 2.1975547
B61: Стабильный конденсат | C61: млн т | D61: =SUM(E61:AR61) -> 11.022304 | E61: =E58*$D$34/1000 -> 0 | F61: =F58*$D$34/1000 -> 0 | G61: =G58*$D$34/1000 -> 0 | H61: =H58*$D$34/1000 -> 0 | I61: =I58*$D$34/1000 -> 0.17360485 | J61: =J58*$D$34/1000 -> 0.3472097 | K61: =K58*$D$34/1000 -> 0.48609358 | L61: =L58*$D$34/1000 -> 0.48609358 | ... AR61: =AR58*$D$34/1000 -> 0.091898131
B62: СУГ | C62: млн т | D62: =SUM(E62:AR62) -> 0 | E62: =E58*$D$35/1000 -> 0 | F62: =F58*$D$35/1000 -> 0 | G62: =G58*$D$35/1000 -> 0 | H62: =H58*$D$35/1000 -> 0 | I62: =I58*$D$35/1000 -> 0 | J62: =J58*$D$35/1000 -> 0 | K62: =K58*$D$35/1000 -> 0 | L62: =L58*$D$35/1000 -> 0 | ... AR62: =AR58*$D$35/1000 -> 0
B63: Этан | C63: млн т | D63: =SUM(E63:AR63) -> 0 | E63: =E58*$D$36/1000 -> 0 | F63: =F58*$D$36/1000 -> 0 | G63: =G58*$D$36/1000 -> 0 | H63: =H58*$D$36/1000 -> 0 | I63: =I58*$D$36/1000 -> 0 | J63: =J58*$D$36/1000 -> 0 | K63: =K58*$D$36/1000 -> 0 | L63: =L58*$D$36/1000 -> 0 | ... AR63: =AR58*$D$36/1000 -> 0
B64: Синтетическое ДТ | C64: млн т | D64: =SUM(E64:AR64) -> 0 | E64: =IF(E59>0,Исходные!$C$39/1000,0) -> 0 | F64: =IF(F59>0,Исходные!$C$39/1000,0) -> 0 | G64: =IF(G59>0,Исходные!$C$39/1000,0) -> 0 | H64: =IF(H59>0,Исходные!$C$39/1000,0) -> 0 | I64: =IF(I59>0,Исходные!$C$39/1000,0) -> 0 | J64: =IF(J59>0,Исходные!$C$39/1000,0) -> 0 | K64: =IF(K59>0,Исходные!$C$39/1000,0) -> 0 | L64: =IF(L59>0,Исходные!$C$39/1000,0) -> 0 | ... AR64: =IF(AR59>0,Исходные!$C$39/1000,0) -> 0
B65: Синтетический авиакеросин | C65: млн т | D65: =SUM(E65:AR65) -> 0 | E65: =IF(E59>0,Исходные!$C$40/1000,0) -> 0 | F65: =IF(F59>0,Исходные!$C$40/1000,0) -> 0 | G65: =IF(G59>0,Исходные!$C$40/1000,0) -> 0 | H65: =IF(H59>0,Исходные!$C$40/1000,0) -> 0 | I65: =IF(I59>0,Исходные!$C$40/1000,0) -> 0 | J65: =IF(J59>0,Исходные!$C$40/1000,0) -> 0 | K65: =IF(K59>0,Исходные!$C$40/1000,0) -> 0 | L65: =IF(L59>0,Исходные!$C$40/1000,0) -> 0 | ... AR65: =IF(AR59>0,Исходные!$C$40/1000,0) -> 0
B66: Нафта GTL (сдаётся с конденсатом) | C66: млн т | D66: =SUM(E66:AR66) -> 0 | E66: =IF(E59>0,$D$43-E64-E65,0) -> 0 | F66: =IF(F59>0,$D$43-F64-F65,0) -> 0 | G66: =IF(G59>0,$D$43-G64-G65,0) -> 0 | H66: =IF(H59>0,$D$43-H64-H65,0) -> 0 | I66: =IF(I59>0,$D$43-I64-I65,0) -> 0 | J66: =IF(J59>0,$D$43-J64-J65,0) -> 0 | K66: =IF(K59>0,$D$43-K64-K65,0) -> 0 | L66: =IF(L59>0,$D$43-L64-L65,0) -> 0 | ... AR66: =IF(AR59>0,$D$43-AR64-AR65,0) -> 0
B67: Выручка, налоги, затраты, млрд руб
B68: Выручка: газ | C68: млрд руб | D68: =SUM(E68:AR68) -> 1370.9604 | E68: =E60*$D$39/1000 -> 0 | F68: =F60*$D$39/1000 -> 0 | G68: =G60*$D$39/1000 -> 0 | H68: =H60*$D$39/1000 -> 0 | I68: =I60*$D$39/1000 -> 21.593069 | J68: =J60*$D$39/1000 -> 43.186138 | K68: =K60*$D$39/1000 -> 60.460593 | L68: =L60*$D$39/1000 -> 60.460593 | ... AR68: =AR60*$D$39/1000 -> 11.430341
B69: Выручка: конденсат и нафта | C69: млрд руб | D69: =SUM(E69:AR69) -> 411.96964 | E69: =(E61+E66)*$D$40/1000 -> 0 | F69: =(F61+F66)*$D$40/1000 -> 0 | G69: =(G61+G66)*$D$40/1000 -> 0 | H69: =(H61+H66)*$D$40/1000 -> 0 | I69: =(I61+I66)*$D$40/1000 -> 6.4886549 | J69: =(J61+J66)*$D$40/1000 -> 12.97731 | K69: =(K61+K66)*$D$40/1000 -> 18.168234 | L69: =(L61+L66)*$D$40/1000 -> 18.168234 | ... AR69: =(AR61+AR66)*$D$40/1000 -> 3.4347846
B70: Выручка: СУГ и этан | C70: млрд руб | D70: =SUM(E70:AR70) -> 0 | E70: =E62*Исходные!$C$19/1000+E63*Исходные!$C$20/1000 -> 0 | F70: =F62*Исходные!$C$19/1000+F63*Исходные!$C$20/1000 -> 0 | G70: =G62*Исходные!$C$19/1000+G63*Исходные!$C$20/1000 -> 0 | H70: =H62*Исходные!$C$19/1000+H63*Исходные!$C$20/1000 -> 0 | I70: =I62*Исходные!$C$19/1000+I63*Исходные!$C$20/1000 -> 0 | J70: =J62*Исходные!$C$19/1000+J63*Исходные!$C$20/1000 -> 0 | K70: =K62*Исходные!$C$19/1000+K63*Исходные!$C$20/1000 -> 0 | L70: =L62*Исходные!$C$19/1000+L63*Исходные!$C$20/1000 -> 0 | ... AR70: =AR62*Исходные!$C$19/1000+AR63*Исходные!$C$20/1000 -> 0
B71: Выручка: ДТ GTL | C71: млрд руб | D71: =SUM(E71:AR71) -> 0 | E71: =E64*$D$23/1000 -> 0 | F71: =F64*$D$23/1000 -> 0 | G71: =G64*$D$23/1000 -> 0 | H71: =H64*$D$23/1000 -> 0 | I71: =I64*$D$23/1000 -> 0 | J71: =J64*$D$23/1000 -> 0 | K71: =K64*$D$23/1000 -> 0 | L71: =L64*$D$23/1000 -> 0 | ... AR71: =AR64*$D$23/1000 -> 0
B72: Выручка: керосин GTL | C72: млрд руб | D72: =SUM(E72:AR72) -> 0 | E72: =E65*$D$24/1000 -> 0 | F72: =F65*$D$24/1000 -> 0 | G72: =G65*$D$24/1000 -> 0 | H72: =H65*$D$24/1000 -> 0 | I72: =I65*$D$24/1000 -> 0 | J72: =J65*$D$24/1000 -> 0 | K72: =K65*$D$24/1000 -> 0 | L72: =L65*$D$24/1000 -> 0 | ... AR72: =AR65*$D$24/1000 -> 0
B73: Выручка всего | C73: млрд руб | D73: =SUM(E73:AR73) -> 1782.93 | E73: =SUM(E68:E72) -> 0 | F73: =SUM(F68:F72) -> 0 | G73: =SUM(G68:G72) -> 0 | H73: =SUM(H68:H72) -> 0 | I73: =SUM(I68:I72) -> 28.081724 | J73: =SUM(J68:J72) -> 56.163448 | K73: =SUM(K68:K72) -> 78.628827 | L73: =SUM(L68:L72) -> 78.628827 | ... AR73: =SUM(AR68:AR72) -> 14.865126
B74: НДПИ (газ + жидкие УВ, с Кр) | C74: млрд руб | D74: =SUM(E74:AR74) -> 239.12514 | E74: =E52*$D$37/1000*(Исходные!$C$23+Исходные!$C$24*E56)/1000+Исходные!$C$25*E56*(E69+E70) -> 0 | F74: =F52*$D$37/1000*(Исходные!$C$23+Исходные!$C$24*F56)/1000+Исходные!$C$25*F56*(F69+F70) -> 0 | G74: =G52*$D$37/1000*(Исходные!$C$23+Исходные!$C$24*G56)/1000+Исходные!$C$25*G56*(G69+G70) -> 0 | H74: =H52*$D$37/1000*(Исходные!$C$23+Исходные!$C$24*H56)/1000+Исходные!$C$25*H56*(H69+H70) -> 0 | I74: =I52*$D$37/1000*(Исходные!$C$23+Исходные!$C$24*I56)/1000+Исходные!$C$25*I56*(I69+I70) -> 2.5194351 | J74: =J52*$D$37/1000*(Исходные!$C$23+Исходные!$C$24*J56)/1000+Исходные!$C$25*J56*(J69+J70) -> 5.3071376 | K74: =K52*$D$37/1000*(Исходные!$C$23+Исходные!$C$24*K56)/1000+Исходные!$C$25*K56*(K69+K70) -> 7.8055672 | L74: =L52*$D$37/1000*(Исходные!$C$23+Исходные!$C$24*L56)/1000+Исходные!$C$25*L56*(L69+L70) -> 8.1811417 | ... AR74: =AR52*$D$37/1000*(Исходные!$C$23+Исходные!$C$24*AR56)/1000+Исходные!$C$25*AR56*(AR69+AR70) -> 2.2094982
B75: Капитальные вложения, млрд руб
B76: Доразведка, 3D, ТЭО и проектная документация | C76: млрд руб | D76: =CAPEX_нормы!$C$6*INDEX(CAPEX_нормы!$E$6:$I$6,MATCH($D$16,CAPEX_нормы!$E$5:$I$5,0))*$D$28 -> 15 | E76: =$D76*CAPEX_нормы!J$6 -> 15 | F76: =$D76*CAPEX_нормы!K$6 -> 0 | G76: =$D76*CAPEX_нормы!L$6 -> 0 | H76: =$D76*CAPEX_нормы!M$6 -> 0 | I76: =$D76*CAPEX_нормы!N$6 -> 0 | J76: =$D76*CAPEX_нормы!O$6 -> 0 | K76: =$D76*CAPEX_нормы!P$6 -> 0 | L76: =$D76*CAPEX_нормы!Q$6 -> 0 | ... W76: =$D76*CAPEX_нормы!AB$6 -> 0 | X76: 0 | Y76: 0 | Z76: 0 | AA76: 0 | AB76: 0 | AC76: 0 | AD76: 0 | AE76: 0 | AF76: 0 | AG76: 0 | AH76: 0 | AI76: 0 | AJ76: 0 | AK76: 0 | AL76: 0 | AM76: 0 | AN76: 0 | AO76: 0 | AP76: 0 | AQ76: 0 | AR76: 0
B77: Эксплуатационные скважины | C77: млрд руб | D77: =$D$42*$D$20*INDEX(CAPEX_нормы!$E$7:$I$7,MATCH($D$16,CAPEX_нормы!$E$5:$I$5,0))*$D$28 -> 85.714286 | E77: =$D77*CAPEX_нормы!J$7 -> 0 | F77: =$D77*CAPEX_нормы!K$7 -> 17.142857 | G77: =$D77*CAPEX_нормы!L$7 -> 25.714286 | H77: =$D77*CAPEX_нормы!M$7 -> 25.714286 | I77: =$D77*CAPEX_нормы!N$7 -> 6.8571429 | J77: =$D77*CAPEX_нормы!O$7 -> 0 | K77: =$D77*CAPEX_нормы!P$7 -> 0 | L77: =$D77*CAPEX_нормы!Q$7 -> 0 | ... W77: =$D77*CAPEX_нормы!AB$7 -> 0 | X77: 0 | Y77: 0 | Z77: 0 | AA77: 0 | AB77: 0 | AC77: 0 | AD77: 0 | AE77: 0 | AF77: 0 | AG77: 0 | AH77: 0 | AI77: 0 | AJ77: 0 | AK77: 0 | AL77: 0 | AM77: 0 | AN77: 0 | AO77: 0 | AP77: 0 | AQ77: 0 | AR77: 0
B78: Кусты скважин и газосборная сеть | C78: млрд руб | D78: =CAPEX_нормы!$C$8*$D$41*INDEX(CAPEX_нормы!$E$8:$I$8,MATCH($D$16,CAPEX_нормы!$E$5:$I$5,0))*$D$28 -> 41.743629 | E78: =$D78*CAPEX_нормы!J$8 -> 0 | F78: =$D78*CAPEX_нормы!K$8 -> 12.523089 | G78: =$D78*CAPEX_нормы!L$8 -> 16.697452 | H78: =$D78*CAPEX_нормы!M$8 -> 12.523089 | I78: =$D78*CAPEX_нормы!N$8 -> 0 | J78: =$D78*CAPEX_нормы!O$8 -> 0 | K78: =$D78*CAPEX_нормы!P$8 -> 0 | L78: =$D78*CAPEX_нормы!Q$8 -> 0 | ... W78: =$D78*CAPEX_нормы!AB$8 -> 0 | X78: 0 | Y78: 0 | Z78: 0 | AA78: 0 | AB78: 0 | AC78: 0 | AD78: 0 | AE78: 0 | AF78: 0 | AG78: 0 | AH78: 0 | AI78: 0 | AJ78: 0 | AK78: 0 | AL78: 0 | AM78: 0 | AN78: 0 | AO78: 0 | AP78: 0 | AQ78: 0 | AR78: 0
B79: УКПГ: НТС, регенерация метанола, стабилизация | C79: млрд руб | D79: =CAPEX_нормы!$C$9*$D$41*INDEX(CAPEX_нормы!$E$9:$I$9,MATCH($D$16,CAPEX_нормы!$E$5:$I$5,0))*$D$28 -> 70.129296 | E79: =$D79*CAPEX_нормы!J$9 -> 0 | F79: =$D79*CAPEX_нормы!K$9 -> 20.871811 | G79: =$D79*CAPEX_нормы!L$9 -> 29.220564 | H79: =$D79*CAPEX_нормы!M$9 -> 20.036922 | I79: =$D79*CAPEX_нормы!N$9 -> 0 | J79: =$D79*CAPEX_нормы!O$9 -> 0 | K79: =$D79*CAPEX_нормы!P$9 -> 0 | L79: =$D79*CAPEX_нормы!Q$9 -> 0 | ... W79: =$D79*CAPEX_нормы!AB$9 -> 0 | X79: 0 | Y79: 0 | Z79: 0 | AA79: 0 | AB79: 0 | AC79: 0 | AD79: 0 | AE79: 0 | AF79: 0 | AG79: 0 | AH79: 0 | AI79: 0 | AJ79: 0 | AK79: 0 | AL79: 0 | AM79: 0 | AN79: 0 | AO79: 0 | AP79: 0 | AQ79: 0 | AR79: 0
B80: Турбодетандерные агрегаты (5 шт.) | C80: млрд руб | D80: =CAPEX_нормы!$C$10*$D$41*INDEX(CAPEX_нормы!$E$10:$I$10,MATCH($D$16,CAPEX_нормы!$E$5:$I$5,0))*$D$28 -> 4.4885622 | E80: =$D80*CAPEX_нормы!J$10 -> 0 | F80: =$D80*CAPEX_нормы!K$10 -> 0 | G80: =$D80*CAPEX_нормы!L$10 -> 2.2442811 | H80: =$D80*CAPEX_нормы!M$10 -> 2.2442811 | I80: =$D80*CAPEX_нормы!N$10 -> 0 | J80: =$D80*CAPEX_нормы!O$10 -> 0 | K80: =$D80*CAPEX_нормы!P$10 -> 0 | L80: =$D80*CAPEX_нормы!Q$10 -> 0 | ... W80: =$D80*CAPEX_нормы!AB$10 -> 0 | X80: 0 | Y80: 0 | Z80: 0 | AA80: 0 | AB80: 0 | AC80: 0 | AD80: 0 | AE80: 0 | AF80: 0 | AG80: 0 | AH80: 0 | AI80: 0 | AJ80: 0 | AK80: 0 | AL80: 0 | AM80: 0 | AN80: 0 | AO80: 0 | AP80: 0 | AQ80: 0 | AR80: 0
B81: ТДА + деэтанизация + ГФУ + парк СУГ | C81: млрд руб | D81: =CAPEX_нормы!$C$11*$D$41*INDEX(CAPEX_нормы!$E$11:$I$11,MATCH($D$16,CAPEX_нормы!$E$5:$I$5,0))*$D$28 -> 0 | E81: =$D81*CAPEX_нормы!J$11 -> 0 | F81: =$D81*CAPEX_нормы!K$11 -> 0 | G81: =$D81*CAPEX_нормы!L$11 -> 0 | H81: =$D81*CAPEX_нормы!M$11 -> 0 | I81: =$D81*CAPEX_нормы!N$11 -> 0 | J81: =$D81*CAPEX_нормы!O$11 -> 0 | K81: =$D81*CAPEX_нормы!P$11 -> 0 | L81: =$D81*CAPEX_нормы!Q$11 -> 0 | ... W81: =$D81*CAPEX_нормы!AB$11 -> 0 | X81: 0 | Y81: 0 | Z81: 0 | AA81: 0 | AB81: 0 | AC81: 0 | AD81: 0 | AE81: 0 | AF81: 0 | AG81: 0 | AH81: 0 | AI81: 0 | AJ81: 0 | AK81: 0 | AL81: 0 | AM81: 0 | AN81: 0 | AO81: 0 | AP81: 0 | AQ81: 0 | AR81: 0
B82: Продуктопровод СУГ 120 км | C82: млрд руб | D82: =CAPEX_нормы!$C$12*$D$41*INDEX(CAPEX_нормы!$E$12:$I$12,MATCH($D$16,CAPEX_нормы!$E$5:$I$5,0))*$D$28 -> 0 | E82: =$D82*CAPEX_нормы!J$12 -> 0 | F82: =$D82*CAPEX_нормы!K$12 -> 0 | G82: =$D82*CAPEX_нормы!L$12 -> 0 | H82: =$D82*CAPEX_нормы!M$12 -> 0 | I82: =$D82*CAPEX_нормы!N$12 -> 0 | J82: =$D82*CAPEX_нормы!O$12 -> 0 | K82: =$D82*CAPEX_нормы!P$12 -> 0 | L82: =$D82*CAPEX_нормы!Q$12 -> 0 | ... W82: =$D82*CAPEX_нормы!AB$12 -> 0 | X82: 0 | Y82: 0 | Z82: 0 | AA82: 0 | AB82: 0 | AC82: 0 | AD82: 0 | AE82: 0 | AF82: 0 | AG82: 0 | AH82: 0 | AI82: 0 | AJ82: 0 | AK82: 0 | AL82: 0 | AM82: 0 | AN82: 0 | AO82: 0 | AP82: 0 | AQ82: 0 | AR82: 0
B83: Налив СУГ на ж/д | C83: млрд руб | D83: =CAPEX_нормы!$C$13*$D$41*INDEX(CAPEX_нормы!$E$13:$I$13,MATCH($D$16,CAPEX_нормы!$E$5:$I$5,0))*$D$28 -> 0 | E83: =$D83*CAPEX_нормы!J$13 -> 0 | F83: =$D83*CAPEX_нормы!K$13 -> 0 | G83: =$D83*CAPEX_нормы!L$13 -> 0 | H83: =$D83*CAPEX_нормы!M$13 -> 0 | I83: =$D83*CAPEX_нормы!N$13 -> 0 | J83: =$D83*CAPEX_нормы!O$13 -> 0 | K83: =$D83*CAPEX_нормы!P$13 -> 0 | L83: =$D83*CAPEX_нормы!Q$13 -> 0 | ... W83: =$D83*CAPEX_нормы!AB$13 -> 0 | X83: 0 | Y83: 0 | Z83: 0 | AA83: 0 | AB83: 0 | AC83: 0 | AD83: 0 | AE83: 0 | AF83: 0 | AG83: 0 | AH83: 0 | AI83: 0 | AJ83: 0 | AK83: 0 | AL83: 0 | AM83: 0 | AN83: 0 | AO83: 0 | AP83: 0 | AQ83: 0 | AR83: 0
B84: Пропановая холодильная установка | C84: млрд руб | D84: =CAPEX_нормы!$C$14*$D$41*INDEX(CAPEX_нормы!$E$14:$I$14,MATCH($D$16,CAPEX_нормы!$E$5:$I$5,0))*$D$28 -> 0 | E84: =$D84*CAPEX_нормы!J$14 -> 0 | F84: =$D84*CAPEX_нормы!K$14 -> 0 | G84: =$D84*CAPEX_нормы!L$14 -> 0 | H84: =$D84*CAPEX_нормы!M$14 -> 0 | I84: =$D84*CAPEX_нормы!N$14 -> 0 | J84: =$D84*CAPEX_нормы!O$14 -> 0 | K84: =$D84*CAPEX_нормы!P$14 -> 0 | L84: =$D84*CAPEX_нормы!Q$14 -> 0 | ... W84: =$D84*CAPEX_нормы!AB$14 -> 0 | X84: 0 | Y84: 0 | Z84: 0 | AA84: 0 | AB84: 0 | AC84: 0 | AD84: 0 | AE84: 0 | AF84: 0 | AG84: 0 | AH84: 0 | AI84: 0 | AJ84: 0 | AK84: 0 | AL84: 0 | AM84: 0 | AN84: 0 | AO84: 0 | AP84: 0 | AQ84: 0 | AR84: 0
B85: Криогенный блок извлечения этана | C85: млрд руб | D85: =CAPEX_нормы!$C$15*$D$41*INDEX(CAPEX_нормы!$E$15:$I$15,MATCH($D$16,CAPEX_нормы!$E$5:$I$5,0))*$D$28 -> 0 | E85: =$D85*CAPEX_нормы!J$15 -> 0 | F85: =$D85*CAPEX_нормы!K$15 -> 0 | G85: =$D85*CAPEX_нормы!L$15 -> 0 | H85: =$D85*CAPEX_нормы!M$15 -> 0 | I85: =$D85*CAPEX_нормы!N$15 -> 0 | J85: =$D85*CAPEX_нормы!O$15 -> 0 | K85: =$D85*CAPEX_нормы!P$15 -> 0 | L85: =$D85*CAPEX_нормы!Q$15 -> 0 | ... W85: =$D85*CAPEX_нормы!AB$15 -> 0 | X85: 0 | Y85: 0 | Z85: 0 | AA85: 0 | AB85: 0 | AC85: 0 | AD85: 0 | AE85: 0 | AF85: 0 | AG85: 0 | AH85: 0 | AI85: 0 | AJ85: 0 | AK85: 0 | AL85: 0 | AM85: 0 | AN85: 0 | AO85: 0 | AP85: 0 | AQ85: 0 | AR85: 0
B86: Энергоцентр (ЭСН), промбаза | C86: млрд руб | D86: =CAPEX_нормы!$C$16*$D$41*INDEX(CAPEX_нормы!$E$16:$I$16,MATCH($D$16,CAPEX_нормы!$E$5:$I$5,0))*$D$28 -> 10.772549 | E86: =$D86*CAPEX_нормы!J$16 -> 0 | F86: =$D86*CAPEX_нормы!K$16 -> 4.4885658 | G86: =$D86*CAPEX_нормы!L$16 -> 4.4885658 | H86: =$D86*CAPEX_нормы!M$16 -> 1.7954285 | I86: =$D86*CAPEX_нормы!N$16 -> 0 | J86: =$D86*CAPEX_нормы!O$16 -> 0 | K86: =$D86*CAPEX_нормы!P$16 -> 0 | L86: =$D86*CAPEX_нормы!Q$16 -> 0 | ... W86: =$D86*CAPEX_нормы!AB$16 -> 0 | X86: 0 | Y86: 0 | Z86: 0 | AA86: 0 | AB86: 0 | AC86: 0 | AD86: 0 | AE86: 0 | AF86: 0 | AG86: 0 | AH86: 0 | AI86: 0 | AJ86: 0 | AK86: 0 | AL86: 0 | AM86: 0 | AN86: 0 | AO86: 0 | AP86: 0 | AQ86: 0 | AR86: 0
B87: Вахтовый жилой комплекс у УКПГ | C87: млрд руб | D87: =$D$30*INDEX(CAPEX_нормы!$E$17:$I$17,MATCH($D$16,CAPEX_нормы!$E$5:$I$5,0))*$D$28 -> 4 | E87: =$D87*CAPEX_нормы!J$17 -> 0 | F87: =$D87*CAPEX_нормы!K$17 -> 1.5 | G87: =$D87*CAPEX_нормы!L$17 -> 1.5 | H87: =$D87*CAPEX_нормы!M$17 -> 1 | I87: =$D87*CAPEX_нормы!N$17 -> 0 | J87: =$D87*CAPEX_нормы!O$17 -> 0 | K87: =$D87*CAPEX_нормы!P$17 -> 0 | L87: =$D87*CAPEX_нормы!Q$17 -> 0 | ... W87: =$D87*CAPEX_нормы!AB$17 -> 0 | X87: 0 | Y87: 0 | Z87: 0 | AA87: 0 | AB87: 0 | AC87: 0 | AD87: 0 | AE87: 0 | AF87: 0 | AG87: 0 | AH87: 0 | AI87: 0 | AJ87: 0 | AK87: 0 | AL87: 0 | AM87: 0 | AN87: 0 | AO87: 0 | AP87: 0 | AQ87: 0 | AR87: 0
B88: Автодорога до Бованенково 120 км | C88: млрд руб | D88: =$D$31*INDEX(CAPEX_нормы!$E$18:$I$18,MATCH($D$16,CAPEX_нормы!$E$5:$I$5,0))*$D$28 -> 24 | E88: =$D88*CAPEX_нормы!J$18 -> 0 | F88: =$D88*CAPEX_нормы!K$18 -> 9.6 | G88: =$D88*CAPEX_нормы!L$18 -> 9.6 | H88: =$D88*CAPEX_нормы!M$18 -> 4.8 | I88: =$D88*CAPEX_нормы!N$18 -> 0 | J88: =$D88*CAPEX_нормы!O$18 -> 0 | K88: =$D88*CAPEX_нормы!P$18 -> 0 | L88: =$D88*CAPEX_нормы!Q$18 -> 0 | ... W88: =$D88*CAPEX_нормы!AB$18 -> 0 | X88: 0 | Y88: 0 | Z88: 0 | AA88: 0 | AB88: 0 | AC88: 0 | AD88: 0 | AE88: 0 | AF88: 0 | AG88: 0 | AH88: 0 | AI88: 0 | AJ88: 0 | AK88: 0 | AL88: 0 | AM88: 0 | AN88: 0 | AO88: 0 | AP88: 0 | AQ88: 0 | AR88: 0
B89: Газопровод 120 км до Бованенково | C89: млрд руб | D89: =CAPEX_нормы!$C$19*$D$41*INDEX(CAPEX_нормы!$E$19:$I$19,MATCH($D$16,CAPEX_нормы!$E$5:$I$5,0))*$D$28 -> 37.703923 | E89: =$D89*CAPEX_нормы!J$19 -> 0 | F89: =$D89*CAPEX_нормы!K$19 -> 10.772539 | G89: =$D89*CAPEX_нормы!L$19 -> 17.954231 | H89: =$D89*CAPEX_нормы!M$19 -> 8.9771155 | I89: =$D89*CAPEX_нормы!N$19 -> 0 | J89: =$D89*CAPEX_нормы!O$19 -> 0 | K89: =$D89*CAPEX_нормы!P$19 -> 0 | L89: =$D89*CAPEX_нормы!Q$19 -> 0 | ... W89: =$D89*CAPEX_нормы!AB$19 -> 0 | X89: 0 | Y89: 0 | Z89: 0 | AA89: 0 | AB89: 0 | AC89: 0 | AD89: 0 | AE89: 0 | AF89: 0 | AG89: 0 | AH89: 0 | AI89: 0 | AJ89: 0 | AK89: 0 | AL89: 0 | AM89: 0 | AN89: 0 | AO89: 0 | AP89: 0 | AQ89: 0 | AR89: 0
B90: Конденсатопровод 120 км | C90: млрд руб | D90: =CAPEX_нормы!$C$20*$D$41*INDEX(CAPEX_нормы!$E$20:$I$20,MATCH($D$16,CAPEX_нормы!$E$5:$I$5,0))*$D$28 -> 8.6180395 | E90: =$D90*CAPEX_нормы!J$20 -> 0 | F90: =$D90*CAPEX_нормы!K$20 -> 0 | G90: =$D90*CAPEX_нормы!L$20 -> 5.3862747 | H90: =$D90*CAPEX_нормы!M$20 -> 3.2317648 | I90: =$D90*CAPEX_нормы!N$20 -> 0 | J90: =$D90*CAPEX_нормы!O$20 -> 0 | K90: =$D90*CAPEX_нормы!P$20 -> 0 | L90: =$D90*CAPEX_нормы!Q$20 -> 0 | ... W90: =$D90*CAPEX_нормы!AB$20 -> 0 | X90: 0 | Y90: 0 | Z90: 0 | AA90: 0 | AB90: 0 | AC90: 0 | AD90: 0 | AE90: 0 | AF90: 0 | AG90: 0 | AH90: 0 | AI90: 0 | AJ90: 0 | AK90: 0 | AL90: 0 | AM90: 0 | AN90: 0 | AO90: 0 | AP90: 0 | AQ90: 0 | AR90: 0
B91: ДКС (2 очереди) | C91: млрд руб | D91: =CAPEX_нормы!$C$21*$D$41*INDEX(CAPEX_нормы!$E$21:$I$21,MATCH($D$16,CAPEX_нормы!$E$5:$I$5,0))*$D$28 -> 49.374185 | E91: =$D91*CAPEX_нормы!J$21 -> 0 | F91: =$D91*CAPEX_нормы!K$21 -> 0 | G91: =$D91*CAPEX_нормы!L$21 -> 0 | H91: =$D91*CAPEX_нормы!M$21 -> 0 | I91: =$D91*CAPEX_нормы!N$21 -> 0 | J91: =$D91*CAPEX_нормы!O$21 -> 0 | K91: =$D91*CAPEX_нормы!P$21 -> 0 | L91: =$D91*CAPEX_нормы!Q$21 -> 0 | ... W91: =$D91*CAPEX_нормы!AB$21 -> 17.954231 | X91: 0 | Y91: 0 | Z91: 0 | AA91: 0 | AB91: 0 | AC91: 0 | AD91: 0 | AE91: 0 | AF91: 0 | AG91: 0 | AH91: 0 | AI91: 0 | AJ91: 0 | AK91: 0 | AL91: 0 | AM91: 0 | AN91: 0 | AO91: 0 | AP91: 0 | AQ91: 0 | AR91: 0
B92: GTL-установка у ст. Бованенково + налив | C92: млрд руб | D92: =$D$32*$D$17*INDEX(CAPEX_нормы!$E$22:$I$22,MATCH($D$16,CAPEX_нормы!$E$5:$I$5,0))*$D$28 -> 0 | E92: =$D92*CAPEX_нормы!J$22 -> 0 | F92: =$D92*CAPEX_нормы!K$22 -> 0 | G92: =$D92*CAPEX_нормы!L$22 -> 0 | H92: =$D92*CAPEX_нормы!M$22 -> 0 | I92: =$D92*CAPEX_нормы!N$22 -> 0 | J92: =$D92*CAPEX_нормы!O$22 -> 0 | K92: =$D92*CAPEX_нормы!P$22 -> 0 | L92: =$D92*CAPEX_нормы!Q$22 -> 0 | ... W92: =$D92*CAPEX_нормы!AB$22 -> 0 | X92: 0 | Y92: 0 | Z92: 0 | AA92: 0 | AB92: 0 | AC92: 0 | AD92: 0 | AE92: 0 | AF92: 0 | AG92: 0 | AH92: 0 | AI92: 0 | AJ92: 0 | AK92: 0 | AL92: 0 | AM92: 0 | AN92: 0 | AO92: 0 | AP92: 0 | AQ92: 0 | AR92: 0
B93: CAPEX всего | C93: млрд руб | D93: =SUM(E93:AR93) -> 351.54439 | E93: =SUM(E76:E92) -> 15 | F93: =SUM(F76:F92) -> 76.898861 | G93: =SUM(G76:G92) -> 112.80565 | H93: =SUM(H76:H92) -> 80.322886 | I93: =SUM(I76:I92) -> 6.8571429 | J93: =SUM(J76:J92) -> 0 | K93: =SUM(K76:K92) -> 0 | L93: =SUM(L76:L92) -> 0 | ... AR93: =SUM(AR76:AR92) -> 0
B94: Накопленный CAPEX | C94: млрд руб | E94: =E93 -> 15 | F94: =E94+F93 -> 91.898861 | G94: =F94+G93 -> 204.70451 | H94: =G94+H93 -> 285.0274 | I94: =H94+I93 -> 291.88454 | J94: =I94+J93 -> 291.88454 | K94: =J94+K93 -> 291.88454 | L94: =K94+L93 -> 291.88454 | M94: =L94+M93 -> 291.88454 | ... AR94: =AQ94+AR93 -> 351.54439
B95: Операционные затраты, амортизация, налоги, млрд руб
B96: Признак добычи | C96: 0/1 | E96: =IF(E52>0,1,0) -> 0 | F96: =IF(F52>0,1,0) -> 0 | G96: =IF(G52>0,1,0) -> 0 | H96: =IF(H52>0,1,0) -> 0 | I96: =IF(I52>0,1,0) -> 1 | J96: =IF(J52>0,1,0) -> 1 | K96: =IF(K52>0,1,0) -> 1 | L96: =IF(L52>0,1,0) -> 1 | ... AR96: =IF(AR52>0,1,0) -> 1
B97: OPEX (пост. + перем. + СУГ + терминал + GTL + чужой ВЖК) | C97: млрд руб | D97: =SUM(E97:AR97) -> 228.75483 | E97: =E96*Исходные!$C$33*E94+E52*Исходные!$C$34/1000+E62*Исходные!$C$35/1000+(E61+E62)*Исходные!$C$36/1000+IF(E59>0,$D$43*Исходные!$C$41/1000,0)+E96*$D$33 -> 0 | F97: =F96*Исходные!$C$33*F94+F52*Исходные!$C$34/1000+F62*Исходные!$C$35/1000+(F61+F62)*Исходные!$C$36/1000+IF(F59>0,$D$43*Исходные!$C$41/1000,0)+F96*$D$33 -> 0 | G97: =G96*Исходные!$C$33*G94+G52*Исходные!$C$34/1000+G62*Исходные!$C$35/1000+(G61+G62)*Исходные!$C$36/1000+IF(G59>0,$D$43*Исходные!$C$41/1000,0)+G96*$D$33 -> 0 | H97: =H96*Исходные!$C$33*H94+H52*Исходные!$C$34/1000+H62*Исходные!$C$35/1000+(H61+H62)*Исходные!$C$36/1000+IF(H59>0,$D$43*Исходные!$C$41/1000,0)+H96*$D$33 -> 0 | I97: =I96*Исходные!$C$33*I94+I52*Исходные!$C$34/1000+I62*Исходные!$C$35/1000+(I61+I62)*Исходные!$C$36/1000+IF(I59>0,$D$43*Исходные!$C$41/1000,0)+I96*$D$33 -> 5.1079277 | J97: =J96*Исходные!$C$33*J94+J52*Исходные!$C$34/1000+J62*Исходные!$C$35/1000+(J61+J62)*Исходные!$C$36/1000+IF(J59>0,$D$43*Исходные!$C$41/1000,0)+J96*$D$33 -> 5.8375873 | K97: =K96*Исходные!$C$33*K94+K52*Исходные!$C$34/1000+K62*Исходные!$C$35/1000+(K61+K62)*Исходные!$C$36/1000+IF(K59>0,$D$43*Исходные!$C$41/1000,0)+K96*$D$33 -> 6.4213149 | L97: =L96*Исходные!$C$33*L94+L52*Исходные!$C$34/1000+L62*Исходные!$C$35/1000+(L61+L62)*Исходные!$C$36/1000+IF(L59>0,$D$43*Исходные!$C$41/1000,0)+L96*$D$33 -> 6.4213149 | ... AR97: =AR96*Исходные!$C$33*AR94+AR52*Исходные!$C$34/1000+AR62*Исходные!$C$35/1000+(AR61+AR62)*Исходные!$C$36/1000+IF(AR59>0,$D$43*Исходные!$C$41/1000,0)+AR96*$D$33 -> 5.6647025
B98: Ввод основных средств | C98: млрд руб | D98: =SUM(E98:AR98) -> 351.54439 | E98: 0 | F98: 0 | G98: 0 | H98: 0 | I98: =SUM(E93:H93) -> 285.0274 | J98: =I93 -> 6.8571429 | K98: =J93 -> 0 | L98: =K93 -> 0 | M98: =L93 -> 0 | N98: =M93 -> 0 | O98: =N93 -> 2.5714286 | P98: =O93 -> 16.037102 | Q98: =P93 -> 20.52566 | ... AR98: =AQ93 -> 0
B99: Амортизация | C99: млрд руб | D99: =SUM(E99:AR99) -> 351.54439 | E99: =SUM(OFFSET(E98,0,-MIN(Исходные!$C$32-1,E47),1,MIN(Исходные!$C$32,E47+1)))/Исходные!$C$32 -> 0 | F99: =SUM(OFFSET(F98,0,-MIN(Исходные!$C$32-1,F47),1,MIN(Исходные!$C$32,F47+1)))/Исходные!$C$32 -> 0 | G99: =SUM(OFFSET(G98,0,-MIN(Исходные!$C$32-1,G47),1,MIN(Исходные!$C$32,G47+1)))/Исходные!$C$32 -> 0 | H99: =SUM(OFFSET(H98,0,-MIN(Исходные!$C$32-1,H47),1,MIN(Исходные!$C$32,H47+1)))/Исходные!$C$32 -> 0 | I99: =SUM(OFFSET(I98,0,-MIN(Исходные!$C$32-1,I47),1,MIN(Исходные!$C$32,I47+1)))/Исходные!$C$32 -> 19.001827 | J99: =SUM(OFFSET(J98,0,-MIN(Исходные!$C$32-1,J47),1,MIN(Исходные!$C$32,J47+1)))/Исходные!$C$32 -> 19.45897 | K99: =SUM(OFFSET(K98,0,-MIN(Исходные!$C$32-1,K47),1,MIN(Исходные!$C$32,K47+1)))/Исходные!$C$32 -> 19.45897 | L99: =SUM(OFFSET(L98,0,-MIN(Исходные!$C$32-1,L47),1,MIN(Исходные!$C$32,L47+1)))/Исходные!$C$32 -> 19.45897 | ... AR99: =SUM(OFFSET(AR98,0,-MIN(Исходные!$C$32-1,AR47),1,MIN(Исходные!$C$32,AR47+1)))/Исходные!$C$32 -> 0
B100: Накопленная амортизация | C100: млрд руб | E100: =E99 -> 0 | F100: =E100+F99 -> 0 | G100: =F100+G99 -> 0 | H100: =G100+H99 -> 0 | I100: =H100+I99 -> 19.001827 | J100: =I100+J99 -> 38.460796 | K100: =J100+K99 -> 57.919766 | L100: =K100+L99 -> 77.378735 | M100: =L100+M99 -> 96.837705 | ... AR100: =AQ100+AR99 -> 351.54439
B101: Налог на имущество | C101: млрд руб | D101: =SUM(E101:AR101) -> 55.60121 | E101: =E96*Исходные!$C$31*(E94-E100) -> 0 | F101: =F96*Исходные!$C$31*(F94-F100) -> 0 | G101: =G96*Исходные!$C$31*(G94-G100) -> 0 | H101: =H96*Исходные!$C$31*(H94-H100) -> 0 | I101: =I96*Исходные!$C$31*(I94-I100) -> 6.0034198 | J101: =J96*Исходные!$C$31*(J94-J100) -> 5.5753224 | K101: =K96*Исходные!$C$31*(K94-K100) -> 5.1472251 | L101: =L96*Исходные!$C$31*(L94-L100) -> 4.7191278 | ... AR101: =AR96*Исходные!$C$31*(AR94-AR100) -> 0
B102: EBITDA | C102: млрд руб | D102: =SUM(E102:AR102) -> 1259.4489 | E102: =E73-E74-E97-E101 -> 0 | F102: =F73-F74-F97-F101 -> 0 | G102: =G73-G74-G97-G101 -> 0 | H102: =H73-H74-H97-H101 -> 0 | I102: =I73-I74-I97-I101 -> 14.450941 | J102: =J73-J74-J97-J101 -> 39.4434 | K102: =K73-K74-K97-K101 -> 59.25472 | L102: =L73-L74-L97-L101 -> 59.307243 | ... AR102: =AR73-AR74-AR97-AR101 -> 6.9909251
B103: Налог на прибыль | C103: млрд руб | D103: =SUM(E103:AR103) -> 228.11384 | E103: =MAX(0,E102-E99)*Исходные!$C$30 -> 0 | F103: =MAX(0,F102-F99)*Исходные!$C$30 -> 0 | G103: =MAX(0,G102-G99)*Исходные!$C$30 -> 0 | H103: =MAX(0,H102-H99)*Исходные!$C$30 -> 0 | I103: =MAX(0,I102-I99)*Исходные!$C$30 -> 0 | J103: =MAX(0,J102-J99)*Исходные!$C$30 -> 4.9961077 | K103: =MAX(0,K102-K99)*Исходные!$C$30 -> 9.9489375 | L103: =MAX(0,L102-L99)*Исходные!$C$30 -> 9.9620683 | ... AR103: =MAX(0,AR102-AR99)*Исходные!$C$30 -> 1.7477313
...

Sheet Расчёт_Наш
B2: Расчёт: Наш выбор: ТДА + GTL 40+30
B3: Базовый вариант решения команды. Денежный поток по годам, млрд руб. (реальные цены 2026 г.)
B5: ЧДД (NPV) при ставке варианта, млрд руб | C5: =SUM(E107:AR107) -> 22.511796
B6: ВНД (IRR), реальная | C6: =IRR(E105:AR105,0.1) -> 0.11044479
B7: Дисконтированная окупаемость, год | C7: =IF(SUM(E109:AR109)=0,"нет",2067-SUM(E109:AR109)) -> 2048
B8: Индекс доходности (PI) | C8: =1+C5/SUMPRODUCT(E93:AR93,E106:AR106) -> 1.0878941
B9: CAPEX всего, млрд руб | C9: =D93 -> 362.29439
B10: Фонд скважин, шт. | C10: =$D$42 -> 57.142857
B11: Проверка: Σ профиля − извлекаемые (должно быть ≈ 0), млрд м³ | C11: =D50-Исходные!$C$8 -> 0.0003531191
B13: Показатель | C13: Ед. | D13: Итого / знач. | E13: 2027 | F13: 2028 | G13: 2029 | H13: 2030 | I13: 2031 | J13: 2032 | K13: 2033 | L13: 2034 | M13: 2035 | N13: 2036 | O13: 2037 | P13: 2038 | Q13: 2039 | R13: 2040 | S13: 2041 | T13: 2042 | U13: 2043 | V13: 2044 | W13: 2045 | X13: 2046 | Y13: 2047 | Z13: 2048 | AA13: 2049 | AB13: 2050 | AC13: 2051 | AD13: 2052 | AE13: 2053 | AF13: 2054 | AG13: 2055 | AH13: 2056 | AI13: 2057 | AJ13: 2058 | AK13: 2059 | AL13: 2060 | AM13: 2061 | AN13: 2062 | AO13: 2063 | AP13: 2064 | AQ13: 2065 | AR13: 2066
B14: Параметры варианта (ссылки на «Сценарии» и «Исходные»)
B15: Технология (столбец баланса) | C15: код | D15: =Сценарии!$H$6 -> T
B16: Состав CAPEX | C16: код | D16: =Сценарии!$H$7 -> T
B17: GTL (1 — есть) | C17: 0/1 | D17: =Сценарии!$H$8 -> 1
B18: Полка добычи | C18: млрд м³/год | D18: =Сценарии!$H$9 -> 12
B19: Темп падения | C19: 1/год | D19: =Сценарии!$H$10 -> 0.071752
B20: Стоимость скважины | C20: млрд руб | D20: =Сценарии!$H$11 -> 1.5
B21: Дебит скважины | C21: млн м³/сут | D21: =Сценарии!$H$12 -> 0.75
B22: Кр (п-ов Ямал) в НДПИ | C22: 0/1 | D22: =Сценарии!$H$13 -> 1
B23: Цена ДТ GTL | C23: руб/т | D23: =Сценарии!$H$14 -> 56100
B24: Цена керосина GTL | C24: руб/т | D24: =Сценарии!$H$15 -> 64500
B25: Цена газа | C25: руб/1000 м³ | D25: =Сценарии!$H$16 -> 4705
B26: Brent | C26: $/барр. | D26: =Сценарии!$H$17 -> 65
B27: Ставка дисконтирования | C27: доля | D27: =Сценарии!$H$18 -> 0.1
B28: Множитель CAPEX | C28: x | D28: =Сценарии!$H$19 -> 1
B29: Множитель добычи | C29: x | D29: =Сценарии!$H$20 -> 1
B30: ВЖК у УКПГ | C30: млрд руб | D30: =Сценарии!$H$21 -> 4
B31: Автодорога | C31: млрд руб | D31: =Сценарии!$H$22 -> 24
B32: GTL + налив | C32: млрд руб | D32: =Сценарии!$H$23 -> 10.75
B33: Услуги чужого ВЖК | C33: млрд руб/год | D33: =Сценарии!$H$24 -> 0
B34: Выход конденсата | C34: кг/1000 м³ | D34: =INDEX(Баланс!$D$18:$G$18,MATCH($D$15,Баланс!$D$17:$G$17,0)) -> 41.334488
B35: Выход СУГ | C35: кг/1000 м³ | D35: =INDEX(Баланс!$D$19:$G$19,MATCH($D$15,Баланс!$D$17:$G$17,0)) -> 0
B36: Выход этана | C36: кг/1000 м³ | D36: =INDEX(Баланс!$D$20:$G$20,MATCH($D$15,Баланс!$D$17:$G$17,0)) -> 0
B37: Товарный газ | C37: м³/1000 м³ | D37: =INDEX(Баланс!$D$21:$G$21,MATCH($D$15,Баланс!$D$17:$G$17,0)) -> 988.42921
B38: Теплота сгорания товарного газа | C38: МДж/м³ | D38: =INDEX(Баланс!$D$22:$G$22,MATCH($D$15,Баланс!$D$17:$G$17,0)) -> 36.565304
B39: Цена товарного газа с учётом теплоты | C39: руб/1000 м³ | D39: =$D$25*$D$38/Исходные!$C$12 -> 5201.3911
B40: Нетбэк конденсата на промысле | C40: руб/т | D40: =($D$26-Исходные!$C$16)*Исходные!$C$17*Исходные!$C$15-Исходные!$C$18 -> 37376
B41: Коэффициент масштаба объектов (полка/14)^0,7 | C41: x | D41: =($D$18/14)^0.7 -> 0.89771245
B42: Фонд эксплуатационных скважин | C42: шт. | D42: =100*$D$18/14*0.5/$D$21 -> 57.142857
B43: GTL: синтетические УВ | C43: млн т/год | D43: =(Исходные!$C$39+Исходные!$C$40)/Исходные!$C$38/1000 -> 0.076502732
B44: GTL: газ на установку | C44: млрд м³/год | D44: =$D$43/Исходные!$C$37 -> 0.18659203
B45: Добыча и продукция
B46: Год | E46: 2027 | F46: 2028 | G46: 2029 | H46: 2030 | I46: 2031 | J46: 2032 | K46: 2033 | L46: 2034 | M46: 2035 | N46: 2036 | O46: 2037 | P46: 2038 | Q46: 2039 | R46: 2040 | S46: 2041 | T46: 2042 | U46: 2043 | V46: 2044 | W46: 2045 | X46: 2046 | Y46: 2047 | Z46: 2048 | AA46: 2049 | AB46: 2050 | AC46: 2051 | AD46: 2052 | AE46: 2053 | AF46: 2054 | AG46: 2055 | AH46: 2056 | AI46: 2057 | AJ46: 2058 | AK46: 2059 | AL46: 2060 | AM46: 2061 | AN46: 2062 | AO46: 2063 | AP46: 2064 | AQ46: 2065 | AR46: 2066
B47: Номер года от начала (для дисконтирования) | E47: =E46-2027 -> 0 | F47: =F46-2027 -> 1 | G47: =G46-2027 -> 2 | H47: =H46-2027 -> 3 | I47: =I46-2027 -> 4 | J47: =J46-2027 -> 5 | K47: =K46-2027 -> 6 | L47: =L46-2027 -> 7 | ... AR47: =AR46-2027 -> 39
B48: Признак падения добычи | C48: 0/1 | E48: 0 | F48: =IF(F46<=Исходные!$C$9+1,0,IF(OR(E48=1,E51+$D$18>Исходные!$C$10*Исходные!$C$8),1,0)) -> 0 | G48: =IF(G46<=Исходные!$C$9+1,0,IF(OR(F48=1,F51+$D$18>Исходные!$C$10*Исходные!$C$8),1,0)) -> 0 | H48: =IF(H46<=Исходные!$C$9+1,0,IF(OR(G48=1,G51+$D$18>Исходные!$C$10*Исходные!$C$8),1,0)) -> 0 | I48: =IF(I46<=Исходные!$C$9+1,0,IF(OR(H48=1,H51+$D$18>Исходные!$C$10*Исходные!$C$8),1,0)) -> 0 | J48: =IF(J46<=Исходные!$C$9+1,0,IF(OR(I48=1,I51+$D$18>Исходные!$C$10*Исходные!$C$8),1,0)) -> 0 | K48: =IF(K46<=Исходные!$C$9+1,0,IF(OR(J48=1,J51+$D$18>Исходные!$C$10*Исходные!$C$8),1,0)) -> 0 | L48: =IF(L46<=Исходные!$C$9+1,0,IF(OR(K48=1,K51+$D$18>Исходные!$C$10*Исходные!$C$8),1,0)) -> 0 | M48: =IF(M46<=Исходные!$C$9+1,0,IF(OR(L48=1,L51+$D$18>Исходные!$C$10*Исходные!$C$8),1,0)) -> 0 | ... AR48: =IF(AR46<=Исходные!$C$9+1,0,IF(OR(AQ48=1,AQ51+$D$18>Исходные!$C$10*Исходные!$C$8),1,0)) -> 1
B49: Год падения, порядковый | E49: 0 | F49: =IF(F48=1,E49+1,0) -> 0 | G49: =IF(G48=1,F49+1,0) -> 0 | H49: =IF(H48=1,G49+1,0) -> 0 | I49: =IF(I48=1,H49+1,0) -> 0 | J49: =IF(J48=1,I49+1,0) -> 0 | K49: =IF(K48=1,J49+1,0) -> 0 | L49: =IF(L48=1,K49+1,0) -> 0 | M49: =IF(M48=1,L49+1,0) -> 0 | ... AR49: =IF(AR48=1,AQ49+1,0) -> 23
B50: Профиль добычи (до множителя) | C50: млрд м³ | D50: =SUM(E50:AR50) -> 275.20035 | E50: =IF(E46<Исходные!$C$9,0,IF(E46=Исходные!$C$9,$D$18*5/14,IF(E46=Исходные!$C$9+1,$D$18*10/14,IF(E48=1,$D$18*EXP(-$D$19*E49),$D$18)))) -> 0 | F50: =IF(F46<Исходные!$C$9,0,IF(F46=Исходные!$C$9,$D$18*5/14,IF(F46=Исходные!$C$9+1,$D$18*10/14,IF(F48=1,$D$18*EXP(-$D$19*F49),$D$18)))) -> 0 | G50: =IF(G46<Исходные!$C$9,0,IF(G46=Исходные!$C$9,$D$18*5/14,IF(G46=Исходные!$C$9+1,$D$18*10/14,IF(G48=1,$D$18*EXP(-$D$19*G49),$D$18)))) -> 0 | H50: =IF(H46<Исходные!$C$9,0,IF(H46=Исходные!$C$9,$D$18*5/14,IF(H46=Исходные!$C$9+1,$D$18*10/14,IF(H48=1,$D$18*EXP(-$D$19*H49),$D$18)))) -> 0 | I50: =IF(I46<Исходные!$C$9,0,IF(I46=Исходные!$C$9,$D$18*5/14,IF(I46=Исходные!$C$9+1,$D$18*10/14,IF(I48=1,$D$18*EXP(-$D$19*I49),$D$18)))) -> 4.2857143 | J50: =IF(J46<Исходные!$C$9,0,IF(J46=Исходные!$C$9,$D$18*5/14,IF(J46=Исходные!$C$9+1,$D$18*10/14,IF(J48=1,$D$18*EXP(-$D$19*J49),$D$18)))) -> 8.5714286 | K50: =IF(K46<Исходные!$C$9,0,IF(K46=Исходные!$C$9,$D$18*5/14,IF(K46=Исходные!$C$9+1,$D$18*10/14,IF(K48=1,$D$18*EXP(-$D$19*K49),$D$18)))) -> 12 | L50: =IF(L46<Исходные!$C$9,0,IF(L46=Исходные!$C$9,$D$18*5/14,IF(L46=Исходные!$C$9+1,$D$18*10/14,IF(L48=1,$D$18*EXP(-$D$19*L49),$D$18)))) -> 12 | ... AR50: =IF(AR46<Исходные!$C$9,0,IF(AR46=Исходные!$C$9,$D$18*5/14,IF(AR46=Исходные!$C$9+1,$D$18*10/14,IF(AR48=1,$D$18*EXP(-$D$19*AR49),$D$18)))) -> 2.3039168
B51: Накопленный профиль | C51: млрд м³ | E51: =E50 -> 0 | F51: =E51+F50 -> 0 | G51: =F51+G50 -> 0 | H51: =G51+H50 -> 0 | I51: =H51+I50 -> 4.2857143 | J51: =I51+J50 -> 12.857143 | K51: =J51+K50 -> 24.857143 | L51: =K51+L50 -> 36.857143 | M51: =L51+M50 -> 48.857143 | ... AR51: =AQ51+AR50 -> 275.20035
B52: Добыча сырого газа | C52: млрд м³ | D52: =SUM(E52:AR52) -> 275.20035 | E52: =E50*$D$29 -> 0 | F52: =F50*$D$29 -> 0 | G52: =G50*$D$29 -> 0 | H52: =H50*$D$29 -> 0 | I52: =I50*$D$29 -> 4.2857143 | J52: =J50*$D$29 -> 8.5714286 | K52: =K50*$D$29 -> 12 | L52: =L50*$D$29 -> 12 | ... AR52: =AR50*$D$29 -> 2.3039168
B53: Накопленная добыча | C53: млрд м³ | E53: =E52 -> 0 | F53: =E53+F52 -> 0 | G53: =F53+G52 -> 0 | H53: =G53+H52 -> 0 | I53: =H53+I52 -> 4.2857143 | J53: =I53+J52 -> 12.857143 | K53: =J53+K52 -> 24.857143 | L53: =K53+L52 -> 36.857143 | M53: =L53+M52 -> 48.857143 | ... AR53: =AQ53+AR52 -> 275.20035
B54: Выработанность > 1 % НГЗ (старт Кр) | C54: 0/1 | E54: =IF(E53/Исходные!$C$6>Исходные!$C$29,1,0) -> 0 | F54: =IF(OR(E54=1,F53/Исходные!$C$6>Исходные!$C$29),1,0) -> 0 | G54: =IF(OR(F54=1,G53/Исходные!$C$6>Исходные!$C$29),1,0) -> 0 | H54: =IF(OR(G54=1,H53/Исходные!$C$6>Исходные!$C$29),1,0) -> 0 | I54: =IF(OR(H54=1,I53/Исходные!$C$6>Исходные!$C$29),1,0) -> 1 | J54: =IF(OR(I54=1,J53/Исходные!$C$6>Исходные!$C$29),1,0) -> 1 | K54: =IF(OR(J54=1,K53/Исходные!$C$6>Исходные!$C$29),1,0) -> 1 | L54: =IF(OR(K54=1,L53/Исходные!$C$6>Исходные!$C$29),1,0) -> 1 | M54: =IF(OR(L54=1,M53/Исходные!$C$6>Исходные!$C$29),1,0) -> 1 | ... AR54: =IF(OR(AQ54=1,AR53/Исходные!$C$6>Исходные!$C$29),1,0) -> 1
B55: n для Кр (порядковый год) | E55: =1 -> 1 | F55: =IF(F54=1,IF(E54=1,E55+1,1),1) -> 1 | G55: =IF(G54=1,IF(F54=1,F55+1,1),1) -> 1 | H55: =IF(H54=1,IF(G54=1,G55+1,1),1) -> 1 | I55: =IF(I54=1,IF(H54=1,H55+1,1),1) -> 1 | J55: =IF(J54=1,IF(I54=1,I55+1,1),1) -> 2 | K55: =IF(K54=1,IF(J54=1,J55+1,1),1) -> 3 | L55: =IF(L54=1,IF(K54=1,K55+1,1),1) -> 4 | M55: =IF(M54=1,IF(L54=1,L55+1,1),1) -> 5 | ... AR55: =IF(AR54=1,IF(AQ54=1,AQ55+1,1),1) -> 36
B56: Коэффициент Кр | E56: =IF($D$22=0,1,IF(E55>Исходные!$C$28,1,MIN(1,Исходные!$C$26*E55+Исходные!$C$27))) -> 0.21 | F56: =IF($D$22=0,1,IF(F55>Исходные!$C$28,1,MIN(1,Исходные!$C$26*F55+Исходные!$C$27))) -> 0.21 | G56: =IF($D$22=0,1,IF(G55>Исходные!$C$28,1,MIN(1,Исходные!$C$26*G55+Исходные!$C$27))) -> 0.21 | H56: =IF($D$22=0,1,IF(H55>Исходные!$C$28,1,MIN(1,Исходные!$C$26*H55+Исходные!$C$27))) -> 0.21 | I56: =IF($D$22=0,1,IF(I55>Исходные!$C$28,1,MIN(1,Исходные!$C$26*I55+Исходные!$C$27))) -> 0.21 | J56: =IF($D$22=0,1,IF(J55>Исходные!$C$28,1,MIN(1,Исходные!$C$26*J55+Исходные!$C$27))) -> 0.276 | K56: =IF($D$22=0,1,IF(K55>Исходные!$C$28,1,MIN(1,Исходные!$C$26*K55+Исходные!$C$27))) -> 0.342 | L56: =IF($D$22=0,1,IF(L55>Исходные!$C$28,1,MIN(1,Исходные!$C$26*L55+Исходные!$C$27))) -> 0.408 | ... AR56: =IF($D$22=0,1,IF(AR55>Исходные!$C$28,1,MIN(1,Исходные!$C$26*AR55+Исходные!$C$27))) -> 1
B57: Собственные нужды | C57: доля | E57: =IF(E46>=2038,Исходные!$C$22,Исходные!$C$21) -> 0.02 | F57: =IF(F46>=2038,Исходные!$C$22,Исходные!$C$21) -> 0.02 | G57: =IF(G46>=2038,Исходные!$C$22,Исходные!$C$21) -> 0.02 | H57: =IF(H46>=2038,Исходные!$C$22,Исходные!$C$21) -> 0.02 | I57: =IF(I46>=2038,Исходные!$C$22,Исходные!$C$21) -> 0.02 | J57: =IF(J46>=2038,Исходные!$C$22,Исходные!$C$21) -> 0.02 | K57: =IF(K46>=2038,Исходные!$C$22,Исходные!$C$21) -> 0.02 | L57: =IF(L46>=2038,Исходные!$C$22,Исходные!$C$21) -> 0.02 | ... AR57: =IF(AR46>=2038,Исходные!$C$22,Исходные!$C$21) -> 0.035
B58: Газ на подготовку | C58: млрд м³ | D58: =SUM(E58:AR58) -> 266.6612 | E58: =E52*(1-E57) -> 0 | F58: =F52*(1-F57) -> 0 | G58: =G52*(1-G57) -> 0 | H58: =H52*(1-H57) -> 0 | I58: =I52*(1-I57) -> 4.2 | J58: =J52*(1-J57) -> 8.4 | K58: =K52*(1-K57) -> 11.76 | L58: =L52*(1-L57) -> 11.76 | ... AR58: =AR52*(1-AR57) -> 2.2232798
B59: Газ на GTL | C59: млрд м³ | D59: =SUM(E59:AR59) -> 6.344129 | E59: =IF(AND($D$17=1,E46>=Исходные!$C$42,E52>0),$D$44,0) -> 0 | F59: =IF(AND($D$17=1,F46>=Исходные!$C$42,F52>0),$D$44,0) -> 0 | G59: =IF(AND($D$17=1,G46>=Исходные!$C$42,G52>0),$D$44,0) -> 0 | H59: =IF(AND($D$17=1,H46>=Исходные!$C$42,H52>0),$D$44,0) -> 0 | I59: =IF(AND($D$17=1,I46>=Исходные!$C$42,I52>0),$D$44,0) -> 0 | J59: =IF(AND($D$17=1,J46>=Исходные!$C$42,J52>0),$D$44,0) -> 0 | K59: =IF(AND($D$17=1,K46>=Исходные!$C$42,K52>0),$D$44,0) -> 0.18659203 | L59: =IF(AND($D$17=1,L46>=Исходные!$C$42,L52>0),$D$44,0) -> 0.18659203 | ... AR59: =IF(AND($D$17=1,AR46>=Исходные!$C$42,AR52>0),$D$44,0) -> 0.18659203
B60: Товарный газ в ЕСГ | C60: млрд м³ | D60: =SUM(E60:AR60) -> 257.23159 | E60: =E58*$D$37/1000-E59 -> 0 | F60: =F58*$D$37/1000-F59 -> 0 | G60: =G58*$D$37/1000-G59 -> 0 | H60: =H58*$D$37/1000-H59 -> 0 | I60: =I58*$D$37/1000-I59 -> 4.1514027 | J60: =J58*$D$37/1000-J59 -> 8.3028054 | K60: =K58*$D$37/1000-K59 -> 11.437336 | L60: =L58*$D$37/1000-L59 -> 11.437336 | ... AR60: =AR58*$D$37/1000-AR59 -> 2.0109626
B61: Стабильный конденсат | C61: млн т | D61: =SUM(E61:AR61) -> 11.022304 | E61: =E58*$D$34/1000 -> 0 | F61: =F58*$D$34/1000 -> 0 | G61: =G58*$D$34/1000 -> 0 | H61: =H58*$D$34/1000 -> 0 | I61: =I58*$D$34/1000 -> 0.17360485 | J61: =J58*$D$34/1000 -> 0.3472097 | K61: =K58*$D$34/1000 -> 0.48609358 | L61: =L58*$D$34/1000 -> 0.48609358 | ... AR61: =AR58*$D$34/1000 -> 0.091898131
B62: СУГ | C62: млн т | D62: =SUM(E62:AR62) -> 0 | E62: =E58*$D$35/1000 -> 0 | F62: =F58*$D$35/1000 -> 0 | G62: =G58*$D$35/1000 -> 0 | H62: =H58*$D$35/1000 -> 0 | I62: =I58*$D$35/1000 -> 0 | J62: =J58*$D$35/1000 -> 0 | K62: =K58*$D$35/1000 -> 0 | L62: =L58*$D$35/1000 -> 0 | ... AR62: =AR58*$D$35/1000 -> 0
B63: Этан | C63: млн т | D63: =SUM(E63:AR63) -> 0 | E63: =E58*$D$36/1000 -> 0 | F63: =F58*$D$36/1000 -> 0 | G63: =G58*$D$36/1000 -> 0 | H63: =H58*$D$36/1000 -> 0 | I63: =I58*$D$36/1000 -> 0 | J63: =J58*$D$36/1000 -> 0 | K63: =K58*$D$36/1000 -> 0 | L63: =L58*$D$36/1000 -> 0 | ... AR63: =AR58*$D$36/1000 -> 0
B64: Синтетическое ДТ | C64: млн т | D64: =SUM(E64:AR64) -> 1.36 | E64: =IF(E59>0,Исходные!$C$39/1000,0) -> 0 | F64: =IF(F59>0,Исходные!$C$39/1000,0) -> 0 | G64: =IF(G59>0,Исходные!$C$39/1000,0) -> 0 | H64: =IF(H59>0,Исходные!$C$39/1000,0) -> 0 | I64: =IF(I59>0,Исходные!$C$39/1000,0) -> 0 | J64: =IF(J59>0,Исходные!$C$39/1000,0) -> 0 | K64: =IF(K59>0,Исходные!$C$39/1000,0) -> 0.04 | L64: =IF(L59>0,Исходные!$C$39/1000,0) -> 0.04 | ... AR64: =IF(AR59>0,Исходные!$C$39/1000,0) -> 0.04
B65: Синтетический авиакеросин | C65: млн т | D65: =SUM(E65:AR65) -> 1.02 | E65: =IF(E59>0,Исходные!$C$40/1000,0) -> 0 | F65: =IF(F59>0,Исходные!$C$40/1000,0) -> 0 | G65: =IF(G59>0,Исходные!$C$40/1000,0) -> 0 | H65: =IF(H59>0,Исходные!$C$40/1000,0) -> 0 | I65: =IF(I59>0,Исходные!$C$40/1000,0) -> 0 | J65: =IF(J59>0,Исходные!$C$40/1000,0) -> 0 | K65: =IF(K59>0,Исходные!$C$40/1000,0) -> 0.03 | L65: =IF(L59>0,Исходные!$C$40/1000,0) -> 0.03 | ... AR65: =IF(AR59>0,Исходные!$C$40/1000,0) -> 0.03
B66: Нафта GTL (сдаётся с конденсатом) | C66: млн т | D66: =SUM(E66:AR66) -> 0.2210929 | E66: =IF(E59>0,$D$43-E64-E65,0) -> 0 | F66: =IF(F59>0,$D$43-F64-F65,0) -> 0 | G66: =IF(G59>0,$D$43-G64-G65,0) -> 0 | H66: =IF(H59>0,$D$43-H64-H65,0) -> 0 | I66: =IF(I59>0,$D$43-I64-I65,0) -> 0 | J66: =IF(J59>0,$D$43-J64-J65,0) -> 0 | K66: =IF(K59>0,$D$43-K64-K65,0) -> 0.0065027322 | L66: =IF(L59>0,$D$43-L64-L65,0) -> 0.0065027322 | ... AR66: =IF(AR59>0,$D$43-AR64-AR65,0) -> 0.0065027322
B67: Выручка, налоги, затраты, млрд руб
B68: Выручка: газ | C68: млрд руб | D68: =SUM(E68:AR68) -> 1337.9621 | E68: =E60*$D$39/1000 -> 0 | F68: =F60*$D$39/1000 -> 0 | G68: =G60*$D$39/1000 -> 0 | H68: =H60*$D$39/1000 -> 0 | I68: =I60*$D$39/1000 -> 21.593069 | J68: =J60*$D$39/1000 -> 43.186138 | K68: =K60*$D$39/1000 -> 59.490055 | L68: =L60*$D$39/1000 -> 59.490055 | ... AR68: =AR60*$D$39/1000 -> 10.459803
B69: Выручка: конденсат и нафта | C69: млрд руб | D69: =SUM(E69:AR69) -> 420.23321 | E69: =(E61+E66)*$D$40/1000 -> 0 | F69: =(F61+F66)*$D$40/1000 -> 0 | G69: =(G61+G66)*$D$40/1000 -> 0 | H69: =(H61+H66)*$D$40/1000 -> 0 | I69: =(I61+I66)*$D$40/1000 -> 6.4886549 | J69: =(J61+J66)*$D$40/1000 -> 12.97731 | K69: =(K61+K66)*$D$40/1000 -> 18.41128 | L69: =(L61+L66)*$D$40/1000 -> 18.41128 | ... AR69: =(AR61+AR66)*$D$40/1000 -> 3.6778307
B70: Выручка: СУГ и этан | C70: млрд руб | D70: =SUM(E70:AR70) -> 0 | E70: =E62*Исходные!$C$19/1000+E63*Исходные!$C$20/1000 -> 0 | F70: =F62*Исходные!$C$19/1000+F63*Исходные!$C$20/1000 -> 0 | G70: =G62*Исходные!$C$19/1000+G63*Исходные!$C$20/1000 -> 0 | H70: =H62*Исходные!$C$19/1000+H63*Исходные!$C$20/1000 -> 0 | I70: =I62*Исходные!$C$19/1000+I63*Исходные!$C$20/1000 -> 0 | J70: =J62*Исходные!$C$19/1000+J63*Исходные!$C$20/1000 -> 0 | K70: =K62*Исходные!$C$19/1000+K63*Исходные!$C$20/1000 -> 0 | L70: =L62*Исходные!$C$19/1000+L63*Исходные!$C$20/1000 -> 0 | ... AR70: =AR62*Исходные!$C$19/1000+AR63*Исходные!$C$20/1000 -> 0
B71: Выручка: ДТ GTL | C71: млрд руб | D71: =SUM(E71:AR71) -> 76.296 | E71: =E64*$D$23/1000 -> 0 | F71: =F64*$D$23/1000 -> 0 | G71: =G64*$D$23/1000 -> 0 | H71: =H64*$D$23/1000 -> 0 | I71: =I64*$D$23/1000 -> 0 | J71: =J64*$D$23/1000 -> 0 | K71: =K64*$D$23/1000 -> 2.244 | L71: =L64*$D$23/1000 -> 2.244 | ... AR71: =AR64*$D$23/1000 -> 2.244
B72: Выручка: керосин GTL | C72: млрд руб | D72: =SUM(E72:AR72) -> 65.79 | E72: =E65*$D$24/1000 -> 0 | F72: =F65*$D$24/1000 -> 0 | G72: =G65*$D$24/1000 -> 0 | H72: =H65*$D$24/1000 -> 0 | I72: =I65*$D$24/1000 -> 0 | J72: =J65*$D$24/1000 -> 0 | K72: =K65*$D$24/1000 -> 1.935 | L72: =L65*$D$24/1000 -> 1.935 | ... AR72: =AR65*$D$24/1000 -> 1.935
B73: Выручка всего | C73: млрд руб | D73: =SUM(E73:AR73) -> 1900.2813 | E73: =SUM(E68:E72) -> 0 | F73: =SUM(F68:F72) -> 0 | G73: =SUM(G68:G72) -> 0 | H73: =SUM(H68:H72) -> 0 | I73: =SUM(I68:I72) -> 28.081724 | J73: =SUM(J68:J72) -> 56.163448 | K73: =SUM(K68:K72) -> 82.080335 | L73: =SUM(L68:L72) -> 82.080335 | ... AR73: =SUM(AR68:AR72) -> 18.316634
B74: НДПИ (газ + жидкие УВ, с Кр) | C74: млрд руб | D74: =SUM(E74:AR74) -> 240.23307 | E74: =E52*$D$37/1000*(Исходные!$C$23+Исходные!$C$24*E56)/1000+Исходные!$C$25*E56*(E69+E70) -> 0 | F74: =F52*$D$37/1000*(Исходные!$C$23+Исходные!$C$24*F56)/1000+Исходные!$C$25*F56*(F69+F70) -> 0 | G74: =G52*$D$37/1000*(Исходные!$C$23+Исходные!$C$24*G56)/1000+Исходные!$C$25*G56*(G69+G70) -> 0 | H74: =H52*$D$37/1000*(Исходные!$C$23+Исходные!$C$24*H56)/1000+Исходные!$C$25*H56*(H69+H70) -> 0 | I74: =I52*$D$37/1000*(Исходные!$C$23+Исходные!$C$24*I56)/1000+Исходные!$C$25*I56*(I69+I70) -> 2.5194351 | J74: =J52*$D$37/1000*(Исходные!$C$23+Исходные!$C$24*J56)/1000+Исходные!$C$25*J56*(J69+J70) -> 5.3071376 | K74: =K52*$D$37/1000*(Исходные!$C$23+Исходные!$C$24*K56)/1000+Исходные!$C$25*K56*(K69+K70) -> 7.8180354 | L74: =L52*$D$37/1000*(Исходные!$C$23+Исходные!$C$24*L56)/1000+Исходные!$C$25*L56*(L69+L70) -> 8.1960161 | ... AR74: =AR52*$D$37/1000*(Исходные!$C$23+Исходные!$C$24*AR56)/1000+Исходные!$C$25*AR56*(AR69+AR70) -> 2.2459551
B75: Капитальные вложения, млрд руб
B76: Доразведка, 3D, ТЭО и проектная документация | C76: млрд руб | D76: =CAPEX_нормы!$C$6*INDEX(CAPEX_нормы!$E$6:$I$6,MATCH($D$16,CAPEX_нормы!$E$5:$I$5,0))*$D$28 -> 15 | E76: =$D76*CAPEX_нормы!J$6 -> 15 | F76: =$D76*CAPEX_нормы!K$6 -> 0 | G76: =$D76*CAPEX_нормы!L$6 -> 0 | H76: =$D76*CAPEX_нормы!M$6 -> 0 | I76: =$D76*CAPEX_нормы!N$6 -> 0 | J76: =$D76*CAPEX_нормы!O$6 -> 0 | K76: =$D76*CAPEX_нормы!P$6 -> 0 | L76: =$D76*CAPEX_нормы!Q$6 -> 0 | ... W76: =$D76*CAPEX_нормы!AB$6 -> 0 | X76: 0 | Y76: 0 | Z76: 0 | AA76: 0 | AB76: 0 | AC76: 0 | AD76: 0 | AE76: 0 | AF76: 0 | AG76: 0 | AH76: 0 | AI76: 0 | AJ76: 0 | AK76: 0 | AL76: 0 | AM76: 0 | AN76: 0 | AO76: 0 | AP76: 0 | AQ76: 0 | AR76: 0
B77: Эксплуатационные скважины | C77: млрд руб | D77: =$D$42*$D$20*INDEX(CAPEX_нормы!$E$7:$I$7,MATCH($D$16,CAPEX_нормы!$E$5:$I$5,0))*$D$28 -> 85.714286 | E77: =$D77*CAPEX_нормы!J$7 -> 0 | F77: =$D77*CAPEX_нормы!K$7 -> 17.142857 | G77: =$D77*CAPEX_нормы!L$7 -> 25.714286 | H77: =$D77*CAPEX_нормы!M$7 -> 25.714286 | I77: =$D77*CAPEX_нормы!N$7 -> 6.8571429 | J77: =$D77*CAPEX_нормы!O$7 -> 0 | K77: =$D77*CAPEX_нормы!P$7 -> 0 | L77: =$D77*CAPEX_нормы!Q$7 -> 0 | ... W77: =$D77*CAPEX_нормы!AB$7 -> 0 | X77: 0 | Y77: 0 | Z77: 0 | AA77: 0 | AB77: 0 | AC77: 0 | AD77: 0 | AE77: 0 | AF77: 0 | AG77: 0 | AH77: 0 | AI77: 0 | AJ77: 0 | AK77: 0 | AL77: 0 | AM77: 0 | AN77: 0 | AO77: 0 | AP77: 0 | AQ77: 0 | AR77: 0
B78: Кусты скважин и газосборная сеть | C78: млрд руб | D78: =CAPEX_нормы!$C$8*$D$41*INDEX(CAPEX_нормы!$E$8:$I$8,MATCH($D$16,CAPEX_нормы!$E$5:$I$5,0))*$D$28 -> 41.743629 | E78: =$D78*CAPEX_нормы!J$8 -> 0 | F78: =$D78*CAPEX_нормы!K$8 -> 12.523089 | G78: =$D78*CAPEX_нормы!L$8 -> 16.697452 | H78: =$D78*CAPEX_нормы!M$8 -> 12.523089 | I78: =$D78*CAPEX_нормы!N$8 -> 0 | J78: =$D78*CAPEX_нормы!O$8 -> 0 | K78: =$D78*CAPEX_нормы!P$8 -> 0 | L78: =$D78*CAPEX_нормы!Q$8 -> 0 | ... W78: =$D78*CAPEX_нормы!AB$8 -> 0 | X78: 0 | Y78: 0 | Z78: 0 | AA78: 0 | AB78: 0 | AC78: 0 | AD78: 0 | AE78: 0 | AF78: 0 | AG78: 0 | AH78: 0 | AI78: 0 | AJ78: 0 | AK78: 0 | AL78: 0 | AM78: 0 | AN78: 0 | AO78: 0 | AP78: 0 | AQ78: 0 | AR78: 0
B79: УКПГ: НТС, регенерация метанола, стабилизация | C79: млрд руб | D79: =CAPEX_нормы!$C$9*$D$41*INDEX(CAPEX_нормы!$E$9:$I$9,MATCH($D$16,CAPEX_нормы!$E$5:$I$5,0))*$D$28 -> 70.129296 | E79: =$D79*CAPEX_нормы!J$9 -> 0 | F79: =$D79*CAPEX_нормы!K$9 -> 20.871811 | G79: =$D79*CAPEX_нормы!L$9 -> 29.220564 | H79: =$D79*CAPEX_нормы!M$9 -> 20.036922 | I79: =$D79*CAPEX_нормы!N$9 -> 0 | J79: =$D79*CAPEX_нормы!O$9 -> 0 | K79: =$D79*CAPEX_нормы!P$9 -> 0 | L79: =$D79*CAPEX_нормы!Q$9 -> 0 | ... W79: =$D79*CAPEX_нормы!AB$9 -> 0 | X79: 0 | Y79: 0 | Z79: 0 | AA79: 0 | AB79: 0 | AC79: 0 | AD79: 0 | AE79: 0 | AF79: 0 | AG79: 0 | AH79: 0 | AI79: 0 | AJ79: 0 | AK79: 0 | AL79: 0 | AM79: 0 | AN79: 0 | AO79: 0 | AP79: 0 | AQ79: 0 | AR79: 0
B80: Турбодетандерные агрегаты (5 шт.) | C80: млрд руб | D80: =CAPEX_нормы!$C$10*$D$41*INDEX(CAPEX_нормы!$E$10:$I$10,MATCH($D$16,CAPEX_нормы!$E$5:$I$5,0))*$D$28 -> 4.4885622 | E80: =$D80*CAPEX_нормы!J$10 -> 0 | F80: =$D80*CAPEX_нормы!K$10 -> 0 | G80: =$D80*CAPEX_нормы!L$10 -> 2.2442811 | H80: =$D80*CAPEX_нормы!M$10 -> 2.2442811 | I80: =$D80*CAPEX_нормы!N$10 -> 0 | J80: =$D80*CAPEX_нормы!O$10 -> 0 | K80: =$D80*CAPEX_нормы!P$10 -> 0 | L80: =$D80*CAPEX_нормы!Q$10 -> 0 | ... W80: =$D80*CAPEX_нормы!AB$10 -> 0 | X80: 0 | Y80: 0 | Z80: 0 | AA80: 0 | AB80: 0 | AC80: 0 | AD80: 0 | AE80: 0 | AF80: 0 | AG80: 0 | AH80: 0 | AI80: 0 | AJ80: 0 | AK80: 0 | AL80: 0 | AM80: 0 | AN80: 0 | AO80: 0 | AP80: 0 | AQ80: 0 | AR80: 0
B81: ТДА + деэтанизация + ГФУ + парк СУГ | C81: млрд руб | D81: =CAPEX_нормы!$C$11*$D$41*INDEX(CAPEX_нормы!$E$11:$I$11,MATCH($D$16,CAPEX_нормы!$E$5:$I$5,0))*$D$28 -> 0 | E81: =$D81*CAPEX_нормы!J$11 -> 0 | F81: =$D81*CAPEX_нормы!K$11 -> 0 | G81: =$D81*CAPEX_нормы!L$11 -> 0 | H81: =$D81*CAPEX_нормы!M$11 -> 0 | I81: =$D81*CAPEX_нормы!N$11 -> 0 | J81: =$D81*CAPEX_нормы!O$11 -> 0 | K81: =$D81*CAPEX_нормы!P$11 -> 0 | L81: =$D81*CAPEX_нормы!Q$11 -> 0 | ... W81: =$D81*CAPEX_нормы!AB$11 -> 0 | X81: 0 | Y81: 0 | Z81: 0 | AA81: 0 | AB81: 0 | AC81: 0 | AD81: 0 | AE81: 0 | AF81: 0 | AG81: 0 | AH81: 0 | AI81: 0 | AJ81: 0 | AK81: 0 | AL81: 0 | AM81: 0 | AN81: 0 | AO81: 0 | AP81: 0 | AQ81: 0 | AR81: 0
B82: Продуктопровод СУГ 120 км | C82: млрд руб | D82: =CAPEX_нормы!$C$12*$D$41*INDEX(CAPEX_нормы!$E$12:$I$12,MATCH($D$16,CAPEX_нормы!$E$5:$I$5,0))*$D$28 -> 0 | E82: =$D82*CAPEX_нормы!J$12 -> 0 | F82: =$D82*CAPEX_нормы!K$12 -> 0 | G82: =$D82*CAPEX_нормы!L$12 -> 0 | H82: =$D82*CAPEX_нормы!M$12 -> 0 | I82: =$D82*CAPEX_нормы!N$12 -> 0 | J82: =$D82*CAPEX_нормы!O$12 -> 0 | K82: =$D82*CAPEX_нормы!P$12 -> 0 | L82: =$D82*CAPEX_нормы!Q$12 -> 0 | ... W82: =$D82*CAPEX_нормы!AB$12 -> 0 | X82: 0 | Y82: 0 | Z82: 0 | AA82: 0 | AB82: 0 | AC82: 0 | AD82: 0 | AE82: 0 | AF82: 0 | AG82: 0 | AH82: 0 | AI82: 0 | AJ82: 0 | AK82: 0 | AL82: 0 | AM82: 0 | AN82: 0 | AO82: 0 | AP82: 0 | AQ82: 0 | AR82: 0
B83: Налив СУГ на ж/д | C83: млрд руб | D83: =CAPEX_нормы!$C$13*$D$41*INDEX(CAPEX_нормы!$E$13:$I$13,MATCH($D$16,CAPEX_нормы!$E$5:$I$5,0))*$D$28 -> 0 | E83: =$D83*CAPEX_нормы!J$13 -> 0 | F83: =$D83*CAPEX_нормы!K$13 -> 0 | G83: =$D83*CAPEX_нормы!L$13 -> 0 | H83: =$D83*CAPEX_нормы!M$13 -> 0 | I83: =$D83*CAPEX_нормы!N$13 -> 0 | J83: =$D83*CAPEX_нормы!O$13 -> 0 | K83: =$D83*CAPEX_нормы!P$13 -> 0 | L83: =$D83*CAPEX_нормы!Q$13 -> 0 | ... W83: =$D83*CAPEX_нормы!AB$13 -> 0 | X83: 0 | Y83: 0 | Z83: 0 | AA83: 0 | AB83: 0 | AC83: 0 | AD83: 0 | AE83: 0 | AF83: 0 | AG83: 0 | AH83: 0 | AI83: 0 | AJ83: 0 | AK83: 0 | AL83: 0 | AM83: 0 | AN83: 0 | AO83: 0 | AP83: 0 | AQ83: 0 | AR83: 0
B84: Пропановая холодильная установка | C84: млрд руб | D84: =CAPEX_нормы!$C$14*$D$41*INDEX(CAPEX_нормы!$E$14:$I$14,MATCH($D$16,CAPEX_нормы!$E$5:$I$5,0))*$D$28 -> 0 | E84: =$D84*CAPEX_нормы!J$14 -> 0 | F84: =$D84*CAPEX_нормы!K$14 -> 0 | G84: =$D84*CAPEX_нормы!L$14 -> 0 | H84: =$D84*CAPEX_нормы!M$14 -> 0 | I84: =$D84*CAPEX_нормы!N$14 -> 0 | J84: =$D84*CAPEX_нормы!O$14 -> 0 | K84: =$D84*CAPEX_нормы!P$14 -> 0 | L84: =$D84*CAPEX_нормы!Q$14 -> 0 | ... W84: =$D84*CAPEX_нормы!AB$14 -> 0 | X84: 0 | Y84: 0 | Z84: 0 | AA84: 0 | AB84: 0 | AC84: 0 | AD84: 0 | AE84: 0 | AF84: 0 | AG84: 0 | AH84: 0 | AI84: 0 | AJ84: 0 | AK84: 0 | AL84: 0 | AM84: 0 | AN84: 0 | AO84: 0 | AP84: 0 | AQ84: 0 | AR84: 0
B85: Криогенный блок извлечения этана | C85: млрд руб | D85: =CAPEX_нормы!$C$15*$D$41*INDEX(CAPEX_нормы!$E$15:$I$15,MATCH($D$16,CAPEX_нормы!$E$5:$I$5,0))*$D$28 -> 0 | E85: =$D85*CAPEX_нормы!J$15 -> 0 | F85: =$D85*CAPEX_нормы!K$15 -> 0 | G85: =$D85*CAPEX_нормы!L$15 -> 0 | H85: =$D85*CAPEX_нормы!M$15 -> 0 | I85: =$D85*CAPEX_нормы!N$15 -> 0 | J85: =$D85*CAPEX_нормы!O$15 -> 0 | K85: =$D85*CAPEX_нормы!P$15 -> 0 | L85: =$D85*CAPEX_нормы!Q$15 -> 0 | ... W85: =$D85*CAPEX_нормы!AB$15 -> 0 | X85: 0 | Y85: 0 | Z85: 0 | AA85: 0 | AB85: 0 | AC85: 0 | AD85: 0 | AE85: 0 | AF85: 0 | AG85: 0 | AH85: 0 | AI85: 0 | AJ85: 0 | AK85: 0 | AL85: 0 | AM85: 0 | AN85: 0 | AO85: 0 | AP85: 0 | AQ85: 0 | AR85: 0
B86: Энергоцентр (ЭСН), промбаза | C86: млрд руб | D86: =CAPEX_нормы!$C$16*$D$41*INDEX(CAPEX_нормы!$E$16:$I$16,MATCH($D$16,CAPEX_нормы!$E$5:$I$5,0))*$D$28 -> 10.772549 | E86: =$D86*CAPEX_нормы!J$16 -> 0 | F86: =$D86*CAPEX_нормы!K$16 -> 4.4885658 | G86: =$D86*CAPEX_нормы!L$16 -> 4.4885658 | H86: =$D86*CAPEX_нормы!M$16 -> 1.7954285 | I86: =$D86*CAPEX_нормы!N$16 -> 0 | J86: =$D86*CAPEX_нормы!O$16 -> 0 | K86: =$D86*CAPEX_нормы!P$16 -> 0 | L86: =$D86*CAPEX_нормы!Q$16 -> 0 | ... W86: =$D86*CAPEX_нормы!AB$16 -> 0 | X86: 0 | Y86: 0 | Z86: 0 | AA86: 0 | AB86: 0 | AC86: 0 | AD86: 0 | AE86: 0 | AF86: 0 | AG86: 0 | AH86: 0 | AI86: 0 | AJ86: 0 | AK86: 0 | AL86: 0 | AM86: 0 | AN86: 0 | AO86: 0 | AP86: 0 | AQ86: 0 | AR86: 0
B87: Вахтовый жилой комплекс у УКПГ | C87: млрд руб | D87: =$D$30*INDEX(CAPEX_нормы!$E$17:$I$17,MATCH($D$16,CAPEX_нормы!$E$5:$I$5,0))*$D$28 -> 4 | E87: =$D87*CAPEX_нормы!J$17 -> 0 | F87: =$D87*CAPEX_нормы!K$17 -> 1.5 | G87: =$D87*CAPEX_нормы!L$17 -> 1.5 | H87: =$D87*CAPEX_нормы!M$17 -> 1 | I87: =$D87*CAPEX_нормы!N$17 -> 0 | J87: =$D87*CAPEX_нормы!O$17 -> 0 | K87: =$D87*CAPEX_нормы!P$17 -> 0 | L87: =$D87*CAPEX_нормы!Q$17 -> 0 | ... W87: =$D87*CAPEX_нормы!AB$17 -> 0 | X87: 0 | Y87: 0 | Z87: 0 | AA87: 0 | AB87: 0 | AC87: 0 | AD87: 0 | AE87: 0 | AF87: 0 | AG87: 0 | AH87: 0 | AI87: 0 | AJ87: 0 | AK87: 0 | AL87: 0 | AM87: 0 | AN87: 0 | AO87: 0 | AP87: 0 | AQ87: 0 | AR87: 0
B88: Автодорога до Бованенково 120 км | C88: млрд руб | D88: =$D$31*INDEX(CAPEX_нормы!$E$18:$I$18,MATCH($D$16,CAPEX_нормы!$E$5:$I$5,0))*$D$28 -> 24 | E88: =$D88*CAPEX_нормы!J$18 -> 0 | F88: =$D88*CAPEX_нормы!K$18 -> 9.6 | G88: =$D88*CAPEX_нормы!L$18 -> 9.6 | H88: =$D88*CAPEX_нормы!M$18 -> 4.8 | I88: =$D88*CAPEX_нормы!N$18 -> 0 | J88: =$D88*CAPEX_нормы!O$18 -> 0 | K88: =$D88*CAPEX_нормы!P$18 -> 0 | L88: =$D88*CAPEX_нормы!Q$18 -> 0 | ... W88: =$D88*CAPEX_нормы!AB$18 -> 0 | X88: 0 | Y88: 0 | Z88: 0 | AA88: 0 | AB88: 0 | AC88: 0 | AD88: 0 | AE88: 0 | AF88: 0 | AG88: 0 | AH88: 0 | AI88: 0 | AJ88: 0 | AK88: 0 | AL88: 0 | AM88: 0 | AN88: 0 | AO88: 0 | AP88: 0 | AQ88: 0 | AR88: 0
B89: Газопровод 120 км до Бованенково | C89: млрд руб | D89: =CAPEX_нормы!$C$19*$D$41*INDEX(CAPEX_нормы!$E$19:$I$19,MATCH($D$16,CAPEX_нормы!$E$5:$I$5,0))*$D$28 -> 37.703923 | E89: =$D89*CAPEX_нормы!J$19 -> 0 | F89: =$D89*CAPEX_нормы!K$19 -> 10.772539 | G89: =$D89*CAPEX_нормы!L$19 -> 17.954231 | H89: =$D89*CAPEX_нормы!M$19 -> 8.9771155 | I89: =$D89*CAPEX_нормы!N$19 -> 0 | J89: =$D89*CAPEX_нормы!O$19 -> 0 | K89: =$D89*CAPEX_нормы!P$19 -> 0 | L89: =$D89*CAPEX_нормы!Q$19 -> 0 | ... W89: =$D89*CAPEX_нормы!AB$19 -> 0 | X89: 0 | Y89: 0 | Z89: 0 | AA89: 0 | AB89: 0 | AC89: 0 | AD89: 0 | AE89: 0 | AF89: 0 | AG89: 0 | AH89: 0 | AI89: 0 | AJ89: 0 | AK89: 0 | AL89: 0 | AM89: 0 | AN89: 0 | AO89: 0 | AP89: 0 | AQ89: 0 | AR89: 0
B90: Конденсатопровод 120 км | C90: млрд руб | D90: =CAPEX_нормы!$C$20*$D$41*INDEX(CAPEX_нормы!$E$20:$I$20,MATCH($D$16,CAPEX_нормы!$E$5:$I$5,0))*$D$28 -> 8.6180395 | E90: =$D90*CAPEX_нормы!J$20 -> 0 | F90: =$D90*CAPEX_нормы!K$20 -> 0 | G90: =$D90*CAPEX_нормы!L$20 -> 5.3862747 | H90: =$D90*CAPEX_нормы!M$20 -> 3.2317648 | I90: =$D90*CAPEX_нормы!N$20 -> 0 | J90: =$D90*CAPEX_нормы!O$20 -> 0 | K90: =$D90*CAPEX_нормы!P$20 -> 0 | L90: =$D90*CAPEX_нормы!Q$20 -> 0 | ... W90: =$D90*CAPEX_нормы!AB$20 -> 0 | X90: 0 | Y90: 0 | Z90: 0 | AA90: 0 | AB90: 0 | AC90: 0 | AD90: 0 | AE90: 0 | AF90: 0 | AG90: 0 | AH90: 0 | AI90: 0 | AJ90: 0 | AK90: 0 | AL90: 0 | AM90: 0 | AN90: 0 | AO90: 0 | AP90: 0 | AQ90: 0 | AR90: 0
